Workbook

Sheet Номенклатура
A1: =IFERROR(__xludf.DUMMYFUNCTION("ARRAYFORMULA(IMPORTRANGE(""https://docs.google.com/spreadsheets/d/1iWfgTn_Pi02Cgzvv2hNxbn5R87Czwggoktc9asHRCjo/"",""Номенклатура!A1:BG1000""))"),"Номер") -> Номер | B1: =IFERROR(__xludf.DUMMYFUNCTION("""COMPUTED_VALUE"""),"Описание") -> Описание | C1: =IFERROR(__xludf.DUMMYFUNCTION("""COMPUTED_VALUE"""),"Цена на ал в 1 бр.") -> Цена на ал в 1 бр. | D1: =IFERROR(__xludf.DUMMYFUNCTION("""COMPUTED_VALUE"""),"Премахване на 0-лите") -> Премахване на 0-лите | E1: =IFERROR(__xludf.DUMMYFUNCTION("""COMPUTED_VALUE"""),"Процент АЛ в детайл") -> Процент АЛ в детайл | F1: =IFERROR(__xludf.DUMMYFUNCTION("""COMPUTED_VALUE"""),"Видове АL") -> Видове АL
F2: =IFERROR(__xludf.DUMMYFUNCTION("""COMPUTED_VALUE"""),"Вид AL за тялото") -> Вид AL за тялото | G2: =IFERROR(__xludf.DUMMYFUNCTION("""COMPUTED_VALUE"""),"Тегло") -> Тегло | H2: =IFERROR(__xludf.DUMMYFUNCTION("""COMPUTED_VALUE"""),"Цена") -> Цена | I2: =IFERROR(__xludf.DUMMYFUNCTION("""COMPUTED_VALUE"""),"Вид AL за Пр. Капаци") -> Вид AL за Пр. Капаци | J2: =IFERROR(__xludf.DUMMYFUNCTION("""COMPUTED_VALUE"""),"Тегло") -> Тегло | K2: =IFERROR(__xludf.DUMMYFUNCTION("""COMPUTED_VALUE"""),"Цена") -> Цена | L2: =IFERROR(__xludf.DUMMYFUNCTION("""COMPUTED_VALUE"""),"Вид AL за З.Капаци") -> Вид AL за З.Капаци | M2: =IFERROR(__xludf.DUMMYFUNCTION("""COMPUTED_VALUE"""),"Тегло") -> Тегло | N2: =IFERROR(__xludf.DUMMYFUNCTION("""COMPUTED_VALUE"""),"Цена") -> Цена | P2: =IFERROR(__xludf.DUMMYFUNCTION("""COMPUTED_VALUE"""),"R Вар. 25 (0.21 .107BGN/unit- .kg/unit; 2.904BGN/unit- .kg/unit; 0.317 .BGN/unit- .kg/unit)") -> R Вар. 25 (0.21 .107BGN/unit- .kg/unit; 2.904BGN/unit- .kg/unit; 0.317 .BGN/unit- .kg/unit)
A3: =IFERROR(__xludf.DUMMYFUNCTION("""COMPUTED_VALUE"""),"575-60044") -> 575-60044 | B3: =IFERROR(__xludf.DUMMYFUNCTION("""COMPUTED_VALUE"""),"DC60 Multiturn Body 3/8'' shaft; Nitrile seal Sq. Flange Side PG9 conn") -> DC60 Multiturn Body 3/8'' shaft; Nitrile seal Sq. Flange Side PG9 conn | C3: =IFERROR(__xludf.DUMMYFUNCTION("""COMPUTED_VALUE"""),2.9035) -> 2.9035 | D3: =IFERROR(__xludf.DUMMYFUNCTION("""COMPUTED_VALUE"""),2.9035) -> 2.9035 | E3: =IFERROR(__xludf.DUMMYFUNCTION("""COMPUTED_VALUE"""),"") | F3: =IFERROR(__xludf.DUMMYFUNCTION("""COMPUTED_VALUE"""),"Ф62 AL 2017 Italy") -> Ф62 AL 2017 Italy | G3: =IFERROR(__xludf.DUMMYFUNCTION("""COMPUTED_VALUE"""),0.21) -> 0.21 | H3: =IFERROR(__xludf.DUMMYFUNCTION("""COMPUTED_VALUE"""),2.7216) -> 2.7216 | I3: =IFERROR(__xludf.DUMMYFUNCTION("""COMPUTED_VALUE"""),"AL USA (pc.)") -> AL USA (pc.) | J3: =IFERROR(__xludf.DUMMYFUNCTION("""COMPUTED_VALUE"""),0.107) -> 0.107 | K3: =IFERROR(__xludf.DUMMYFUNCTION("""COMPUTED_VALUE"""),0.18189999999999998) -> 0.1819 | L3: =IFERROR(__xludf.DUMMYFUNCTION("""COMPUTED_VALUE"""),"") | M3: =IFERROR(__xludf.DUMMYFUNCTION("""COMPUTED_VALUE"""),"") | N3: =IFERROR(__xludf.DUMMYFUNCTION("""COMPUTED_VALUE"""),"")
A4: =IFERROR(__xludf.DUMMYFUNCTION("""COMPUTED_VALUE"""),"575-91001-9") -> 575-91001-9 | B4: =IFERROR(__xludf.DUMMYFUNCTION("""COMPUTED_VALUE"""),"DC25FS </= 9 min IP69Kw hole on shaft no knurl M12 side conn. HARSCO") -> DC25FS </= 9 min IP69Kw hole on shaft no knurl M12 side conn. HARSCO | C4: =IFERROR(__xludf.DUMMYFUNCTION("""COMPUTED_VALUE"""),3.94836) -> 3.94836 | D4: =IFERROR(__xludf.DUMMYFUNCTION("""COMPUTED_VALUE"""),3.94836) -> 3.94836 | E4: =IFERROR(__xludf.DUMMYFUNCTION("""COMPUTED_VALUE"""),"") | F4: =IFERROR(__xludf.DUMMYFUNCTION("""COMPUTED_VALUE"""),"Ф65 AL 2017 Italy") -> Ф65 AL 2017 Italy | G4: =IFERROR(__xludf.DUMMYFUNCTION("""COMPUTED_VALUE"""),0.234) -> 0.234 | H4: =IFERROR(__xludf.DUMMYFUNCTION("""COMPUTED_VALUE"""),3.0326400000000002) -> 3.03264 | I4: =IFERROR(__xludf.DUMMYFUNCTION("""COMPUTED_VALUE"""),"AL USA") -> AL USA | J4: =IFERROR(__xludf.DUMMYFUNCTION("""COMPUTED_VALUE"""),0.066) -> 0.066 | K4: =IFERROR(__xludf.DUMMYFUNCTION("""COMPUTED_VALUE"""),0.11220000000000001) -> 0.1122 | L4: =IFERROR(__xludf.DUMMYFUNCTION("""COMPUTED_VALUE"""),"Ф65 AL 2017 Italy") -> Ф65 AL 2017 Italy | M4: =IFERROR(__xludf.DUMMYFUNCTION("""COMPUTED_VALUE"""),0.062) -> 0.062 | N4: =IFERROR(__xludf.DUMMYFUNCTION("""COMPUTED_VALUE"""),0.80352) -> 0.80352
A5: =IFERROR(__xludf.DUMMYFUNCTION("""COMPUTED_VALUE"""),"575-92015") -> 575-92015 | B5: =IFERROR(__xludf.DUMMYFUNCTION("""COMPUTED_VALUE"""),"DC25FE, Multiturn Body 5/8"" shaft flange end conn.") -> DC25FE, Multiturn Body 5/8" shaft flange end conn. | C5: =IFERROR(__xludf.DUMMYFUNCTION("""COMPUTED_VALUE"""),3.4419000000000004) -> 3.4419 | D5: =IFERROR(__xludf.DUMMYFUNCTION("""COMPUTED_VALUE"""),3.4419000000000004) -> 3.4419 | E5: =IFERROR(__xludf.DUMMYFUNCTION("""COMPUTED_VALUE"""),"") | F5: =IFERROR(__xludf.DUMMYFUNCTION("""COMPUTED_VALUE"""),"Ф65 AL 2017 Italy") -> Ф65 AL 2017 Italy | G5: =IFERROR(__xludf.DUMMYFUNCTION("""COMPUTED_VALUE"""),0.24) -> 0.24 | H5: =IFERROR(__xludf.DUMMYFUNCTION("""COMPUTED_VALUE"""),3.1104000000000003) -> 3.1104 | I5: =IFERROR(__xludf.DUMMYFUNCTION("""COMPUTED_VALUE"""),"AL USA") -> AL USA | J5: =IFERROR(__xludf.DUMMYFUNCTION("""COMPUTED_VALUE"""),0.195) -> 0.195 | K5: =IFERROR(__xludf.DUMMYFUNCTION("""COMPUTED_VALUE"""),0.3315) -> 0.3315 | L5: =IFERROR(__xludf.DUMMYFUNCTION("""COMPUTED_VALUE"""),"") | M5: =IFERROR(__xludf.DUMMYFUNCTION("""COMPUTED_VALUE"""),"") | N5: =IFERROR(__xludf.DUMMYFUNCTION("""COMPUTED_VALUE"""),"")
A6: =IFERROR(__xludf.DUMMYFUNCTION("""COMPUTED_VALUE"""),"575-93001") -> 575-93001 | B6: =IFERROR(__xludf.DUMMYFUNCTION("""COMPUTED_VALUE"""),"H25 Resolver Shaft 5/8"" With MS-16 side conn. w/o seal Short body") -> H25 Resolver Shaft 5/8" With MS-16 side conn. w/o seal Short body | C6: =IFERROR(__xludf.DUMMYFUNCTION("""COMPUTED_VALUE"""),2.0628) -> 2.0628 | D6: =IFERROR(__xludf.DUMMYFUNCTION("""COMPUTED_VALUE"""),2.0628) -> 2.0628 | E6: =IFERROR(__xludf.DUMMYFUNCTION("""COMPUTED_VALUE"""),"") | F6: =IFERROR(__xludf.DUMMYFUNCTION("""COMPUTED_VALUE"""),"Cast AL Bulgaria (pc.)") -> Cast AL Bulgaria (pc.) | G6: =IFERROR(__xludf.DUMMYFUNCTION("""COMPUTED_VALUE"""),0.213) -> 0.213 | H6: =IFERROR(__xludf.DUMMYFUNCTION("""COMPUTED_VALUE"""),0.99258) -> 0.99258 | I6: =IFERROR(__xludf.DUMMYFUNCTION("""COMPUTED_VALUE"""),"AL USA") -> AL USA | J6: =IFERROR(__xludf.DUMMYFUNCTION("""COMPUTED_VALUE"""),0.195) -> 0.195 | K6: =IFERROR(__xludf.DUMMYFUNCTION("""COMPUTED_VALUE"""),0.3315) -> 0.3315 | L6: =IFERROR(__xludf.DUMMYFUNCTION("""COMPUTED_VALUE"""),"Ф65 AL 2017 Italy") -> Ф65 AL 2017 Italy | M6: =IFERROR(__xludf.DUMMYFUNCTION("""COMPUTED_VALUE"""),0.057) -> 0.057 | N6: =IFERROR(__xludf.DUMMYFUNCTION("""COMPUTED_VALUE"""),0.73872) -> 0.73872
A7: =IFERROR(__xludf.DUMMYFUNCTION("""COMPUTED_VALUE"""),"H25-FE-06") -> H25-FE-06 | B7: =IFERROR(__xludf.DUMMYFUNCTION("""COMPUTED_VALUE"""),"Transducer 1 Turn Flange Mntaligned at zero degrees With 3mm Key Way, 3/8""shaft") -> Transducer 1 Turn Flange Mntaligned at zero degrees With 3mm Key Way, 3/8"shaft | C7: =IFERROR(__xludf.DUMMYFUNCTION("""COMPUTED_VALUE"""),4.14956) -> 4.14956 | D7: =IFERROR(__xludf.DUMMYFUNCTION("""COMPUTED_VALUE"""),4.14956) -> 4.14956 | E7: =IFERROR(__xludf.DUMMYFUNCTION("""COMPUTED_VALUE"""),"") | F7: =IFERROR(__xludf.DUMMYFUNCTION("""COMPUTED_VALUE"""),"Ф65 AL 2017 Italy") -> Ф65 AL 2017 Italy | G7: =IFERROR(__xludf.DUMMYFUNCTION("""COMPUTED_VALUE"""),0.311) -> 0.311 | H7: =IFERROR(__xludf.DUMMYFUNCTION("""COMPUTED_VALUE"""),4.03056) -> 4.03056 | I7: =IFERROR(__xludf.DUMMYFUNCTION("""COMPUTED_VALUE"""),"AL USA (pc.)") -> AL USA (pc.) | J7: =IFERROR(__xludf.DUMMYFUNCTION("""COMPUTED_VALUE"""),0.07) -> 0.07 | K7: =IFERROR(__xludf.DUMMYFUNCTION("""COMPUTED_VALUE"""),0.11900000000000001) -> 0.119 | L7: =IFERROR(__xludf.DUMMYFUNCTION("""COMPUTED_VALUE"""),"") | M7: =IFERROR(__xludf.DUMMYFUNCTION("""COMPUTED_VALUE"""),"") | N7: =IFERROR(__xludf.DUMMYFUNCTION("""COMPUTED_VALUE"""),"")
A8: =IFERROR(__xludf.DUMMYFUNCTION("""COMPUTED_VALUE"""),"H25-FE") -> H25-FE | B8: =IFERROR(__xludf.DUMMYFUNCTION("""COMPUTED_VALUE"""),"Size 25 resolver 3/8"" shaft Flange mount End connector 0.95 TR @ 5000 Hz") -> Size 25 resolver 3/8" shaft Flange mount End connector 0.95 TR @ 5000 Hz | C8: =IFERROR(__xludf.DUMMYFUNCTION("""COMPUTED_VALUE"""),4.14956) -> 4.14956 | D8: =IFERROR(__xludf.DUMMYFUNCTION("""COMPUTED_VALUE"""),4.14956) -> 4.14956 | E8: =IFERROR(__xludf.DUMMYFUNCTION("""COMPUTED_VALUE"""),"") | F8: =IFERROR(__xludf.DUMMYFUNCTION("""COMPUTED_VALUE"""),"Ф65 AL 2017 Italy") -> Ф65 AL 2017 Italy | G8: =IFERROR(__xludf.DUMMYFUNCTION("""COMPUTED_VALUE"""),0.311) -> 0.311 | H8: =IFERROR(__xludf.DUMMYFUNCTION("""COMPUTED_VALUE"""),4.03056) -> 4.03056 | I8: =IFERROR(__xludf.DUMMYFUNCTION("""COMPUTED_VALUE"""),"AL USA (pc.)") -> AL USA (pc.) | J8: =IFERROR(__xludf.DUMMYFUNCTION("""COMPUTED_VALUE"""),0.07) -> 0.07 | K8: =IFERROR(__xludf.DUMMYFUNCTION("""COMPUTED_VALUE"""),0.11900000000000001) -> 0.119 | L8: =IFERROR(__xludf.DUMMYFUNCTION("""COMPUTED_VALUE"""),"") | M8: =IFERROR(__xludf.DUMMYFUNCTION("""COMPUTED_VALUE"""),"") | N8: =IFERROR(__xludf.DUMMYFUNCTION("""COMPUTED_VALUE"""),"")
A9: =IFERROR(__xludf.DUMMYFUNCTION("""COMPUTED_VALUE"""),"575-60007") -> 575-60007 | B9: =IFERROR(__xludf.DUMMYFUNCTION("""COMPUTED_VALUE"""),"NR-60 Multi Body 10mm shaft Nitrile seal Square flange End conn.") -> NR-60 Multi Body 10mm shaft Nitrile seal Square flange End conn. | C9: =IFERROR(__xludf.DUMMYFUNCTION("""COMPUTED_VALUE"""),2.9812600000000002) -> 2.98126 | D9: =IFERROR(__xludf.DUMMYFUNCTION("""COMPUTED_VALUE"""),2.9812600000000002) -> 2.98126 | E9: =IFERROR(__xludf.DUMMYFUNCTION("""COMPUTED_VALUE"""),"") | F9: =IFERROR(__xludf.DUMMYFUNCTION("""COMPUTED_VALUE"""),"Ф62 AL 2017 Italy") -> Ф62 AL 2017 Italy | G9: =IFERROR(__xludf.DUMMYFUNCTION("""COMPUTED_VALUE"""),0.216) -> 0.216 | H9: =IFERROR(__xludf.DUMMYFUNCTION("""COMPUTED_VALUE"""),2.79936) -> 2.79936 | I9: =IFERROR(__xludf.DUMMYFUNCTION("""COMPUTED_VALUE"""),"AL USA (pc.)") -> AL USA (pc.) | J9: =IFERROR(__xludf.DUMMYFUNCTION("""COMPUTED_VALUE"""),0.107) -> 0.107 | K9: =IFERROR(__xludf.DUMMYFUNCTION("""COMPUTED_VALUE"""),0.18189999999999998) -> 0.1819 | L9: =IFERROR(__xludf.DUMMYFUNCTION("""COMPUTED_VALUE"""),"") | M9: =IFERROR(__xludf.DUMMYFUNCTION("""COMPUTED_VALUE"""),"") | N9: =IFERROR(__xludf.DUMMYFUNCTION("""COMPUTED_VALUE"""),"")
A10: =IFERROR(__xludf.DUMMYFUNCTION("""COMPUTED_VALUE"""),"575-91001") -> 575-91001 | B10: =IFERROR(__xludf.DUMMYFUNCTION("""COMPUTED_VALUE"""),"DC25FE </= 9 min 3/8"" sahft flange end conn.") -> DC25FE </= 9 min 3/8" sahft flange end conn. | C10: =IFERROR(__xludf.DUMMYFUNCTION("""COMPUTED_VALUE"""),3.3849200000000006) -> 3.38492 | D10: =IFERROR(__xludf.DUMMYFUNCTION("""COMPUTED_VALUE"""),3.3849200000000006) -> 3.38492 | E10: =IFERROR(__xludf.DUMMYFUNCTION("""COMPUTED_VALUE"""),"") | F10: =IFERROR(__xludf.DUMMYFUNCTION("""COMPUTED_VALUE"""),"Ф65 AL 2017 Italy") -> Ф65 AL 2017 Italy | G10: =IFERROR(__xludf.DUMMYFUNCTION("""COMPUTED_VALUE"""),0.252) -> 0.252 | H10: =IFERROR(__xludf.DUMMYFUNCTION("""COMPUTED_VALUE"""),3.2659200000000004) -> 3.26592 | I10: =IFERROR(__xludf.DUMMYFUNCTION("""COMPUTED_VALUE"""),"AL USA (pc.)") -> AL USA (pc.) | J10: =IFERROR(__xludf.DUMMYFUNCTION("""COMPUTED_VALUE"""),0.07) -> 0.07 | K10: =IFERROR(__xludf.DUMMYFUNCTION("""COMPUTED_VALUE"""),0.11900000000000001) -> 0.119 | L10: =IFERROR(__xludf.DUMMYFUNCTION("""COMPUTED_VALUE"""),"") | M10: =IFERROR(__xludf.DUMMYFUNCTION("""COMPUTED_VALUE"""),"") | N10: =IFERROR(__xludf.DUMMYFUNCTION("""COMPUTED_VALUE"""),"")
A11: =IFERROR(__xludf.DUMMYFUNCTION("""COMPUTED_VALUE"""),"575-92000") -> 575-92000 | B11: =IFERROR(__xludf.DUMMYFUNCTION("""COMPUTED_VALUE"""),"DC25FS Multiturn Body 3/8"" shaft Flange Multiturn Body 3/8"" shaft MS23 side conn") -> DC25FS Multiturn Body 3/8" shaft Flange Multiturn Body 3/8" shaft MS23 side conn | C11: =IFERROR(__xludf.DUMMYFUNCTION("""COMPUTED_VALUE"""),1.1675) -> 1.1675 | D11: =IFERROR(__xludf.DUMMYFUNCTION("""COMPUTED_VALUE"""),1.1675) -> 1.1675 | E11: =IFERROR(__xludf.DUMMYFUNCTION("""COMPUTED_VALUE"""),"") | F11: =IFERROR(__xludf.DUMMYFUNCTION("""COMPUTED_VALUE"""),"Cast AL Bulgaria (pc.)") -> Cast AL Bulgaria (pc.) | G11: =IFERROR(__xludf.DUMMYFUNCTION("""COMPUTED_VALUE"""),0.225) -> 0.225 | H11: =IFERROR(__xludf.DUMMYFUNCTION("""COMPUTED_VALUE"""),1.0485) -> 1.0485 | I11: =IFERROR(__xludf.DUMMYFUNCTION("""COMPUTED_VALUE"""),"AL USA (pc.)") -> AL USA (pc.) | J11: =IFERROR(__xludf.DUMMYFUNCTION("""COMPUTED_VALUE"""),0.07) -> 0.07 | K11: =IFERROR(__xludf.DUMMYFUNCTION("""COMPUTED_VALUE"""),0.11900000000000001) -> 0.119 | L11: =IFERROR(__xludf.DUMMYFUNCTION("""COMPUTED_VALUE"""),"") | M11: =IFERROR(__xludf.DUMMYFUNCTION("""COMPUTED_VALUE"""),"") | N11: =IFERROR(__xludf.DUMMYFUNCTION("""COMPUTED_VALUE"""),"")
A12: =IFERROR(__xludf.DUMMYFUNCTION("""COMPUTED_VALUE"""),"575-92006") -> 575-92006 | B12: =IFERROR(__xludf.DUMMYFUNCTION("""COMPUTED_VALUE"""),"DC25FE </= 9 min 5/8"" shaft flange end conn") -> DC25FE </= 9 min 5/8" shaft flange end conn | C12: =IFERROR(__xludf.DUMMYFUNCTION("""COMPUTED_VALUE"""),3.5974200000000005) -> 3.59742 | D12: =IFERROR(__xludf.DUMMYFUNCTION("""COMPUTED_VALUE"""),3.5974200000000005) -> 3.59742 | E12: =IFERROR(__xludf.DUMMYFUNCTION("""COMPUTED_VALUE"""),"") | F12: =IFERROR(__xludf.DUMMYFUNCTION("""COMPUTED_VALUE"""),"Ф65 AL 2017 Italy") -> Ф65 AL 2017 Italy | G12: =IFERROR(__xludf.DUMMYFUNCTION("""COMPUTED_VALUE"""),0.252) -> 0.252 | H12: =IFERROR(__xludf.DUMMYFUNCTION("""COMPUTED_VALUE"""),3.2659200000000004) -> 3.26592 | I12: =IFERROR(__xludf.DUMMYFUNCTION("""COMPUTED_VALUE"""),"AL USA") -> AL USA | J12: =IFERROR(__xludf.DUMMYFUNCTION("""COMPUTED_VALUE"""),0.195) -> 0.195 | K12: =IFERROR(__xludf.DUMMYFUNCTION("""COMPUTED_VALUE"""),0.3315) -> 0.3315 | L12: =IFERROR(__xludf.DUMMYFUNCTION("""COMPUTED_VALUE"""),"") | M12: =IFERROR(__xludf.DUMMYFUNCTION("""COMPUTED_VALUE"""),"") | N12: =IFERROR(__xludf.DUMMYFUNCTION("""COMPUTED_VALUE"""),"")
A13: =IFERROR(__xludf.DUMMYFUNCTION("""COMPUTED_VALUE"""),"DC25-2FE") -> DC25-2FE | B13: =IFERROR(__xludf.DUMMYFUNCTION("""COMPUTED_VALUE"""),"DC25 Housing 2Sp. End conn. 3/8"" shaft ") -> DC25 Housing 2Sp. End conn. 3/8" shaft | C13: =IFERROR(__xludf.DUMMYFUNCTION("""COMPUTED_VALUE"""),3.3849200000000006) -> 3.38492 | D13: =IFERROR(__xludf.DUMMYFUNCTION("""COMPUTED_VALUE"""),3.3849200000000006) -> 3.38492 | E13: =IFERROR(__xludf.DUMMYFUNCTION("""COMPUTED_VALUE"""),"") | F13: =IFERROR(__xludf.DUMMYFUNCTION("""COMPUTED_VALUE"""),"Ф65 AL 2017 Italy") -> Ф65 AL 2017 Italy | G13: =IFERROR(__xludf.DUMMYFUNCTION("""COMPUTED_VALUE"""),0.252) -> 0.252 | H13: =IFERROR(__xludf.DUMMYFUNCTION("""COMPUTED_VALUE"""),3.2659200000000004) -> 3.26592 | I13: =IFERROR(__xludf.DUMMYFUNCTION("""COMPUTED_VALUE"""),"AL USA (pc.)") -> AL USA (pc.) | J13: =IFERROR(__xludf.DUMMYFUNCTION("""COMPUTED_VALUE"""),0.07) -> 0.07 | K13: =IFERROR(__xludf.DUMMYFUNCTION("""COMPUTED_VALUE"""),0.11900000000000001) -> 0.119 | L13: =IFERROR(__xludf.DUMMYFUNCTION("""COMPUTED_VALUE"""),"") | M13: =IFERROR(__xludf.DUMMYFUNCTION("""COMPUTED_VALUE"""),"") | N13: =IFERROR(__xludf.DUMMYFUNCTION("""COMPUTED_VALUE"""),"")
A14: =IFERROR(__xludf.DUMMYFUNCTION("""COMPUTED_VALUE"""),"H25-F1E") -> H25-F1E | B14: =IFERROR(__xludf.DUMMYFUNCTION("""COMPUTED_VALUE"""),"Transducer 1 Turn C&A Flange TR=0/95; 5KHz end conn.") -> Transducer 1 Turn C&A Flange TR=0/95; 5KHz end conn. | C14: =IFERROR(__xludf.DUMMYFUNCTION("""COMPUTED_VALUE"""),31.05216) -> 31.05216 | D14: =IFERROR(__xludf.DUMMYFUNCTION("""COMPUTED_VALUE"""),31.05216) -> 31.05216 | E14: =IFERROR(__xludf.DUMMYFUNCTION("""COMPUTED_VALUE"""),"") | F14: =IFERROR(__xludf.DUMMYFUNCTION("""COMPUTED_VALUE"""),"Ф65 AL 2017 Italy") -> Ф65 AL 2017 Italy | G14: =IFERROR(__xludf.DUMMYFUNCTION("""COMPUTED_VALUE"""),0.311) -> 0.311 | H14: =IFERROR(__xludf.DUMMYFUNCTION("""COMPUTED_VALUE"""),4.03056) -> 4.03056 | I14: =IFERROR(__xludf.DUMMYFUNCTION("""COMPUTED_VALUE"""),"Ф65 AL 2017 Italy") -> Ф65 AL 2017 Italy | J14: =IFERROR(__xludf.DUMMYFUNCTION("""COMPUTED_VALUE"""),0.087) -> 0.087 | K14: =IFERROR(__xludf.DUMMYFUNCTION("""COMPUTED_VALUE"""),1.12752) -> 1.12752 | L14: =IFERROR(__xludf.DUMMYFUNCTION("""COMPUTED_VALUE"""),"кв.80 AL2017 Italy") -> кв.80 AL2017 Italy | M14: =IFERROR(__xludf.DUMMYFUNCTION("""COMPUTED_VALUE"""),0.111) -> 0.111 | N14: =IFERROR(__xludf.DUMMYFUNCTION("""COMPUTED_VALUE"""),25.89408) -> 25.89408
A15: =IFERROR(__xludf.DUMMYFUNCTION("""COMPUTED_VALUE"""),"H25-FS-06") -> H25-FS-06 | B15: =IFERROR(__xludf.DUMMYFUNCTION("""COMPUTED_VALUE"""),"Size 25 resolver 3/8"" shaft Flange mount Side connector w/3 mm keyway") -> Size 25 resolver 3/8" shaft Flange mount Side connector w/3 mm keyway | C15: =IFERROR(__xludf.DUMMYFUNCTION("""COMPUTED_VALUE"""),1.8503) -> 1.8503 | D15: =IFERROR(__xludf.DUMMYFUNCTION("""COMPUTED_VALUE"""),1.8503) -> 1.8503 | E15: =IFERROR(__xludf.DUMMYFUNCTION("""COMPUTED_VALUE"""),"") | F15: =IFERROR(__xludf.DUMMYFUNCTION("""COMPUTED_VALUE"""),"Cast AL Bulgaria (pc.)") -> Cast AL Bulgaria (pc.) | G15: =IFERROR(__xludf.DUMMYFUNCTION("""COMPUTED_VALUE"""),0.213) -> 0.213 | H15: =IFERROR(__xludf.DUMMYFUNCTION("""COMPUTED_VALUE"""),0.99258) -> 0.99258 | I15: =IFERROR(__xludf.DUMMYFUNCTION("""COMPUTED_VALUE"""),"AL USA (pc.)") -> AL USA (pc.) | J15: =IFERROR(__xludf.DUMMYFUNCTION("""COMPUTED_VALUE"""),0.07) -> 0.07 | K15: =IFERROR(__xludf.DUMMYFUNCTION("""COMPUTED_VALUE"""),0.11900000000000001) -> 0.119 | L15: =IFERROR(__xludf.DUMMYFUNCTION("""COMPUTED_VALUE"""),"Ф65 AL 2017 Italy") -> Ф65 AL 2017 Italy | M15: =IFERROR(__xludf.DUMMYFUNCTION("""COMPUTED_VALUE"""),0.057) -> 0.057 | N15: =IFERROR(__xludf.DUMMYFUNCTION("""COMPUTED_VALUE"""),0.73872) -> 0.73872
A16: =IFERROR(__xludf.DUMMYFUNCTION("""COMPUTED_VALUE"""),"H25-SE") -> H25-SE | B16: =IFERROR(__xludf.DUMMYFUNCTION("""COMPUTED_VALUE"""),"Size 25 resolver 3/8"" shaft servo mount End connector 0.95 0.95 T.R. @5000 Hz") -> Size 25 resolver 3/8" shaft servo mount End connector 0.95 0.95 T.R. @5000 Hz | C16: =IFERROR(__xludf.DUMMYFUNCTION("""COMPUTED_VALUE"""),4.717440000000001) -> 4.71744 | D16: =IFERROR(__xludf.DUMMYFUNCTION("""COMPUTED_VALUE"""),4.717440000000001) -> 4.71744 | E16: =IFERROR(__xludf.DUMMYFUNCTION("""COMPUTED_VALUE"""),"") | F16: =IFERROR(__xludf.DUMMYFUNCTION("""COMPUTED_VALUE"""),"Ф65 AL 2017 Italy") -> Ф65 AL 2017 Italy | G16: =IFERROR(__xludf.DUMMYFUNCTION("""COMPUTED_VALUE"""),0.311) -> 0.311 | H16: =IFERROR(__xludf.DUMMYFUNCTION("""COMPUTED_VALUE"""),4.03056) -> 4.03056 | I16: =IFERROR(__xludf.DUMMYFUNCTION("""COMPUTED_VALUE"""),"Ф65 AL 2017 Italy") -> Ф65 AL 2017 Italy | J16: =IFERROR(__xludf.DUMMYFUNCTION("""COMPUTED_VALUE"""),0.053) -> 0.053 | K16: =IFERROR(__xludf.DUMMYFUNCTION("""COMPUTED_VALUE"""),0.68688) -> 0.68688 | L16: =IFERROR(__xludf.DUMMYFUNCTION("""COMPUTED_VALUE"""),"") | M16: =IFERROR(__xludf.DUMMYFUNCTION("""COMPUTED_VALUE"""),"") | N16: =IFERROR(__xludf.DUMMYFUNCTION("""COMPUTED_VALUE"""),"")
A17: =IFERROR(__xludf.DUMMYFUNCTION("""COMPUTED_VALUE"""),"575-60021") -> 575-60021 | B17: =IFERROR(__xludf.DUMMYFUNCTION("""COMPUTED_VALUE"""),"NR-60 Encoder Avago assembly,10 mm, multiturn shaft, servo mount, for SIDE CONNECTORS") -> NR-60 Encoder Avago assembly,10 mm, multiturn shaft, servo mount, for SIDE CONNECTORS | C17: =IFERROR(__xludf.DUMMYFUNCTION("""COMPUTED_VALUE"""),2.4499) -> 2.4499 | D17: =IFERROR(__xludf.DUMMYFUNCTION("""COMPUTED_VALUE"""),2.4499) -> 2.4499 | E17: =IFERROR(__xludf.DUMMYFUNCTION("""COMPUTED_VALUE"""),"") | F17: =IFERROR(__xludf.DUMMYFUNCTION("""COMPUTED_VALUE"""),"Ф62 AL 2017 Italy") -> Ф62 AL 2017 Italy | G17: =IFERROR(__xludf.DUMMYFUNCTION("""COMPUTED_VALUE"""),0.175) -> 0.175 | H17: =IFERROR(__xludf.DUMMYFUNCTION("""COMPUTED_VALUE"""),2.268) -> 2.268 | I17: =IFERROR(__xludf.DUMMYFUNCTION("""COMPUTED_VALUE"""),"AL USA (pc.)") -> AL USA (pc.) | J17: =IFERROR(__xludf.DUMMYFUNCTION("""COMPUTED_VALUE"""),0.107) -> 0.107 | K17: =IFERROR(__xludf.DUMMYFUNCTION("""COMPUTED_VALUE"""),0.18189999999999998) -> 0.1819 | L17: =IFERROR(__xludf.DUMMYFUNCTION("""COMPUTED_VALUE"""),"AL cast USA (pc.)") -> AL cast USA (pc.) | M17: =IFERROR(__xludf.DUMMYFUNCTION("""COMPUTED_VALUE"""),0.127) -> 0.127 | N17: =IFERROR(__xludf.DUMMYFUNCTION("""COMPUTED_VALUE"""),"")
A18: =IFERROR(__xludf.DUMMYFUNCTION("""COMPUTED_VALUE"""),"575-91004") -> 575-91004 | B18: =IFERROR(__xludf.DUMMYFUNCTION("""COMPUTED_VALUE"""),"DC25FS14 </= 9 min. 3/8"" shaft flange side con") -> DC25FS14 </= 9 min. 3/8" shaft flange side con | C18: =IFERROR(__xludf.DUMMYFUNCTION("""COMPUTED_VALUE"""),1.18148) -> 1.18148 | D18: =IFERROR(__xludf.DUMMYFUNCTION("""COMPUTED_VALUE"""),1.18148) -> 1.18148 | E18: =IFERROR(__xludf.DUMMYFUNCTION("""COMPUTED_VALUE"""),"") | F18: =IFERROR(__xludf.DUMMYFUNCTION("""COMPUTED_VALUE"""),"Cast AL Bulgaria (pc.)") -> Cast AL Bulgaria (pc.) | G18: =IFERROR(__xludf.DUMMYFUNCTION("""COMPUTED_VALUE"""),0.228) -> 0.228 | H18: =IFERROR(__xludf.DUMMYFUNCTION("""COMPUTED_VALUE"""),1.06248) -> 1.06248 | I18: =IFERROR(__xludf.DUMMYFUNCTION("""COMPUTED_VALUE"""),"AL USA (pc.)") -> AL USA (pc.) | J18: =IFERROR(__xludf.DUMMYFUNCTION("""COMPUTED_VALUE"""),0.07) -> 0.07 | K18: =IFERROR(__xludf.DUMMYFUNCTION("""COMPUTED_VALUE"""),0.11900000000000001) -> 0.119 | L18: =IFERROR(__xludf.DUMMYFUNCTION("""COMPUTED_VALUE"""),"") | M18: =IFERROR(__xludf.DUMMYFUNCTION("""COMPUTED_VALUE"""),"") | N18: =IFERROR(__xludf.DUMMYFUNCTION("""COMPUTED_VALUE"""),"")
A19: =IFERROR(__xludf.DUMMYFUNCTION("""COMPUTED_VALUE"""),"575-92002") -> 575-92002 | B19: =IFERROR(__xludf.DUMMYFUNCTION("""COMPUTED_VALUE"""),"DC25FE multiturn body 3/8"" shaft flange") -> DC25FE multiturn body 3/8" shaft flange | C19: =IFERROR(__xludf.DUMMYFUNCTION("""COMPUTED_VALUE"""),3.2294000000000005) -> 3.2294 | D19: =IFERROR(__xludf.DUMMYFUNCTION("""COMPUTED_VALUE"""),3.2294000000000005) -> 3.2294 | E19: =IFERROR(__xludf.DUMMYFUNCTION("""COMPUTED_VALUE"""),"") | F19: =IFERROR(__xludf.DUMMYFUNCTION("""COMPUTED_VALUE"""),"Ф65 AL 2017 Italy") -> Ф65 AL 2017 Italy | G19: =IFERROR(__xludf.DUMMYFUNCTION("""COMPUTED_VALUE"""),0.24) -> 0.24 | H19: =IFERROR(__xludf.DUMMYFUNCTION("""COMPUTED_VALUE"""),3.1104000000000003) -> 3.1104 | I19: =IFERROR(__xludf.DUMMYFUNCTION("""COMPUTED_VALUE"""),"AL USA (pc.)") -> AL USA (pc.) | J19: =IFERROR(__xludf.DUMMYFUNCTION("""COMPUTED_VALUE"""),0.07) -> 0.07 | K19: =IFERROR(__xludf.DUMMYFUNCTION("""COMPUTED_VALUE"""),0.11900000000000001) -> 0.119 | L19: =IFERROR(__xludf.DUMMYFUNCTION("""COMPUTED_VALUE"""),"") | M19: =IFERROR(__xludf.DUMMYFUNCTION("""COMPUTED_VALUE"""),"") | N19: =IFERROR(__xludf.DUMMYFUNCTION("""COMPUTED_VALUE"""),"")
A20: =IFERROR(__xludf.DUMMYFUNCTION("""COMPUTED_VALUE"""),"DC25-4FS(16)") -> DC25-4FS(16) | B20: =IFERROR(__xludf.DUMMYFUNCTION("""COMPUTED_VALUE"""),"DC25 housing 4 Speed Side Conn. 3/8"" shaft ") -> DC25 housing 4 Speed Side Conn. 3/8" shaft | C20: =IFERROR(__xludf.DUMMYFUNCTION("""COMPUTED_VALUE"""),1.15352) -> 1.15352 | D20: =IFERROR(__xludf.DUMMYFUNCTION("""COMPUTED_VALUE"""),1.15352) -> 1.15352 | E20: =IFERROR(__xludf.DUMMYFUNCTION("""COMPUTED_VALUE"""),"") | F20: =IFERROR(__xludf.DUMMYFUNCTION("""COMPUTED_VALUE"""),"Cast AL Bulgaria (pc.)") -> Cast AL Bulgaria (pc.) | G20: =IFERROR(__xludf.DUMMYFUNCTION("""COMPUTED_VALUE"""),0.222) -> 0.222 | H20: =IFERROR(__xludf.DUMMYFUNCTION("""COMPUTED_VALUE"""),1.03452) -> 1.03452 | I20: =IFERROR(__xludf.DUMMYFUNCTION("""COMPUTED_VALUE"""),"AL USA (pc.)") -> AL USA (pc.) | J20: =IFERROR(__xludf.DUMMYFUNCTION("""COMPUTED_VALUE"""),0.07) -> 0.07 | K20: =IFERROR(__xludf.DUMMYFUNCTION("""COMPUTED_VALUE"""),0.11900000000000001) -> 0.119 | L20: =IFERROR(__xludf.DUMMYFUNCTION("""COMPUTED_VALUE"""),"") | M20: =IFERROR(__xludf.DUMMYFUNCTION("""COMPUTED_VALUE"""),"") | N20: =IFERROR(__xludf.DUMMYFUNCTION("""COMPUTED_VALUE"""),"")
A21: =IFERROR(__xludf.DUMMYFUNCTION("""COMPUTED_VALUE"""),"H25-FS") -> H25-FS | B21: =IFERROR(__xludf.DUMMYFUNCTION("""COMPUTED_VALUE"""),"Size 25 resolver 3/8 shaft Flange mount side connector 0.95 TR @5000Hz") -> Size 25 resolver 3/8 shaft Flange mount side connector 0.95 TR @5000Hz | C21: =IFERROR(__xludf.DUMMYFUNCTION("""COMPUTED_VALUE"""),1.8503) -> 1.8503 | D21: =IFERROR(__xludf.DUMMYFUNCTION("""COMPUTED_VALUE"""),1.8503) -> 1.8503 | E21: =IFERROR(__xludf.DUMMYFUNCTION("""COMPUTED_VALUE"""),"") | F21: =IFERROR(__xludf.DUMMYFUNCTION("""COMPUTED_VALUE"""),"Cast AL Bulgaria (pc.)") -> Cast AL Bulgaria (pc.) | G21: =IFERROR(__xludf.DUMMYFUNCTION("""COMPUTED_VALUE"""),0.213) -> 0.213 | H21: =IFERROR(__xludf.DUMMYFUNCTION("""COMPUTED_VALUE"""),0.99258) -> 0.99258 | I21: =IFERROR(__xludf.DUMMYFUNCTION("""COMPUTED_VALUE"""),"AL USA (pc.)") -> AL USA (pc.) | J21: =IFERROR(__xludf.DUMMYFUNCTION("""COMPUTED_VALUE"""),0.07) -> 0.07 | K21: =IFERROR(__xludf.DUMMYFUNCTION("""COMPUTED_VALUE"""),0.11900000000000001) -> 0.119 | L21: =IFERROR(__xludf.DUMMYFUNCTION("""COMPUTED_VALUE"""),"Ф65 AL 2017 Italy") -> Ф65 AL 2017 Italy | M21: =IFERROR(__xludf.DUMMYFUNCTION("""COMPUTED_VALUE"""),0.057) -> 0.057 | N21: =IFERROR(__xludf.DUMMYFUNCTION("""COMPUTED_VALUE"""),0.73872) -> 0.73872
A22: =IFERROR(__xludf.DUMMYFUNCTION("""COMPUTED_VALUE"""),"575-93002") -> 575-93002 | B22: =IFERROR(__xludf.DUMMYFUNCTION("""COMPUTED_VALUE"""),"H25 Resolver 5/8"" shaft MS-16 end conn. w/o seal Short body") -> H25 Resolver 5/8" shaft MS-16 end conn. w/o seal Short body | C22: =IFERROR(__xludf.DUMMYFUNCTION("""COMPUTED_VALUE"""),4.3620600000000005) -> 4.36206 | D22: =IFERROR(__xludf.DUMMYFUNCTION("""COMPUTED_VALUE"""),4.3620600000000005) -> 4.36206 | E22: =IFERROR(__xludf.DUMMYFUNCTION("""COMPUTED_VALUE"""),"") | F22: =IFERROR(__xludf.DUMMYFUNCTION("""COMPUTED_VALUE"""),"Ф65 AL 2017 Italy") -> Ф65 AL 2017 Italy | G22: =IFERROR(__xludf.DUMMYFUNCTION("""COMPUTED_VALUE"""),0.311) -> 0.311 | H22: =IFERROR(__xludf.DUMMYFUNCTION("""COMPUTED_VALUE"""),4.03056) -> 4.03056 | I22: =IFERROR(__xludf.DUMMYFUNCTION("""COMPUTED_VALUE"""),"AL USA") -> AL USA | J22: =IFERROR(__xludf.DUMMYFUNCTION("""COMPUTED_VALUE"""),0.195) -> 0.195 | K22: =IFERROR(__xludf.DUMMYFUNCTION("""COMPUTED_VALUE"""),0.3315) -> 0.3315 | L22: =IFERROR(__xludf.DUMMYFUNCTION("""COMPUTED_VALUE"""),"") | M22: =IFERROR(__xludf.DUMMYFUNCTION("""COMPUTED_VALUE"""),"") | N22: =IFERROR(__xludf.DUMMYFUNCTION("""COMPUTED_VALUE"""),"")
A23: =IFERROR(__xludf.DUMMYFUNCTION("""COMPUTED_VALUE"""),"575-92011") -> 575-92011 | B23: =IFERROR(__xludf.DUMMYFUNCTION("""COMPUTED_VALUE"""),"DC 25FS Singleturn body 5/8"" shaft flange SSI Dura MS23 side conn </= 9min") -> DC 25FS Singleturn body 5/8" shaft flange SSI Dura MS23 side conn </= 9min | C23: =IFERROR(__xludf.DUMMYFUNCTION("""COMPUTED_VALUE"""),1.4219400000000002) -> 1.42194 | D23: =IFERROR(__xludf.DUMMYFUNCTION("""COMPUTED_VALUE"""),1.4219400000000002) -> 1.42194 | E23: =IFERROR(__xludf.DUMMYFUNCTION("""COMPUTED_VALUE"""),"") | F23: =IFERROR(__xludf.DUMMYFUNCTION("""COMPUTED_VALUE"""),"Cast AL Bulgaria (pc.)") -> Cast AL Bulgaria (pc.) | G23: =IFERROR(__xludf.DUMMYFUNCTION("""COMPUTED_VALUE"""),0.234) -> 0.234 | H23: =IFERROR(__xludf.DUMMYFUNCTION("""COMPUTED_VALUE"""),1.09044) -> 1.09044 | I23: =IFERROR(__xludf.DUMMYFUNCTION("""COMPUTED_VALUE"""),"AL USA") -> AL USA | J23: =IFERROR(__xludf.DUMMYFUNCTION("""COMPUTED_VALUE"""),0.195) -> 0.195 | K23: =IFERROR(__xludf.DUMMYFUNCTION("""COMPUTED_VALUE"""),0.3315) -> 0.3315 | L23: =IFERROR(__xludf.DUMMYFUNCTION("""COMPUTED_VALUE"""),"") | M23: =IFERROR(__xludf.DUMMYFUNCTION("""COMPUTED_VALUE"""),"") | N23: =IFERROR(__xludf.DUMMYFUNCTION("""COMPUTED_VALUE"""),"")
A24: =IFERROR(__xludf.DUMMYFUNCTION("""COMPUTED_VALUE"""),"575-91055") -> 575-91055 | B24: =IFERROR(__xludf.DUMMYFUNCTION("""COMPUTED_VALUE"""),"H25-w/ Special servo nose Two flats on shaft TR=0.95 @ 5KHz") -> H25-w/ Special servo nose Two flats on shaft TR=0.95 @ 5KHz | C24: =IFERROR(__xludf.DUMMYFUNCTION("""COMPUTED_VALUE"""),2.7914000000000003) -> 2.7914 | D24: =IFERROR(__xludf.DUMMYFUNCTION("""COMPUTED_VALUE"""),2.7914000000000003) -> 2.7914 | E24: =IFERROR(__xludf.DUMMYFUNCTION("""COMPUTED_VALUE"""),"") | F24: =IFERROR(__xludf.DUMMYFUNCTION("""COMPUTED_VALUE"""),"Cast AL Bulgaria (pc.)") -> Cast AL Bulgaria (pc.) | G24: =IFERROR(__xludf.DUMMYFUNCTION("""COMPUTED_VALUE"""),0.218) -> 0.218 | H24: =IFERROR(__xludf.DUMMYFUNCTION("""COMPUTED_VALUE"""),1.0158800000000001) -> 1.01588 | I24: =IFERROR(__xludf.DUMMYFUNCTION("""COMPUTED_VALUE"""),"Ф65 AL 2017 Italy") -> Ф65 AL 2017 Italy | J24: =IFERROR(__xludf.DUMMYFUNCTION("""COMPUTED_VALUE"""),0.08) -> 0.08 | K24: =IFERROR(__xludf.DUMMYFUNCTION("""COMPUTED_VALUE"""),1.0368000000000002) -> 1.0368 | L24: =IFERROR(__xludf.DUMMYFUNCTION("""COMPUTED_VALUE"""),"Ф65 AL 2017 Italy") -> Ф65 AL 2017 Italy | M24: =IFERROR(__xludf.DUMMYFUNCTION("""COMPUTED_VALUE"""),0.057) -> 0.057 | N24: =IFERROR(__xludf.DUMMYFUNCTION("""COMPUTED_VALUE"""),0.73872) -> 0.73872
A25: =IFERROR(__xludf.DUMMYFUNCTION("""COMPUTED_VALUE"""),"575-91009") -> 575-91009 | B25: =IFERROR(__xludf.DUMMYFUNCTION("""COMPUTED_VALUE"""),"DC25FS18 </= 9 min 3/8"" shaft flange side conn") -> DC25FS18 </= 9 min 3/8" shaft flange side conn | C25: =IFERROR(__xludf.DUMMYFUNCTION("""COMPUTED_VALUE"""),1.13488) -> 1.13488 | D25: =IFERROR(__xludf.DUMMYFUNCTION("""COMPUTED_VALUE"""),1.13488) -> 1.13488 | E25: =IFERROR(__xludf.DUMMYFUNCTION("""COMPUTED_VALUE"""),"") | F25: =IFERROR(__xludf.DUMMYFUNCTION("""COMPUTED_VALUE"""),"Cast AL Bulgaria (pc.)") -> Cast AL Bulgaria (pc.) | G25: =IFERROR(__xludf.DUMMYFUNCTION("""COMPUTED_VALUE"""),0.218) -> 0.218 | H25: =IFERROR(__xludf.DUMMYFUNCTION("""COMPUTED_VALUE"""),1.0158800000000001) -> 1.01588 | I25: =IFERROR(__xludf.DUMMYFUNCTION("""COMPUTED_VALUE"""),"AL USA (pc.)") -> AL USA (pc.) | J25: =IFERROR(__xludf.DUMMYFUNCTION("""COMPUTED_VALUE"""),0.07) -> 0.07 | K25: =IFERROR(__xludf.DUMMYFUNCTION("""COMPUTED_VALUE"""),0.11900000000000001) -> 0.119 | L25: =IFERROR(__xludf.DUMMYFUNCTION("""COMPUTED_VALUE"""),"") | M25: =IFERROR(__xludf.DUMMYFUNCTION("""COMPUTED_VALUE"""),"") | N25: =IFERROR(__xludf.DUMMYFUNCTION("""COMPUTED_VALUE"""),"")
A26: =IFERROR(__xludf.DUMMYFUNCTION("""COMPUTED_VALUE"""),"22140702A") -> 22140702A | B26: =IFERROR(__xludf.DUMMYFUNCTION("""COMPUTED_VALUE"""),"H25 Body with Shaft zeroed for HT-400x-j Single turn TR=0.95, 5KHz, w/o conn") -> H25 Body with Shaft zeroed for HT-400x-j Single turn TR=0.95, 5KHz, w/o conn | C26: =IFERROR(__xludf.DUMMYFUNCTION("""COMPUTED_VALUE"""),4.03056) -> 4.03056 | D26: =IFERROR(__xludf.DUMMYFUNCTION("""COMPUTED_VALUE"""),4.03056) -> 4.03056 | E26: =IFERROR(__xludf.DUMMYFUNCTION("""COMPUTED_VALUE"""),"") | F26: =IFERROR(__xludf.DUMMYFUNCTION("""COMPUTED_VALUE"""),"Ф65 AL 2017 Italy") -> Ф65 AL 2017 Italy | G26: =IFERROR(__xludf.DUMMYFUNCTION("""COMPUTED_VALUE"""),0.311) -> 0.311 | H26: =IFERROR(__xludf.DUMMYFUNCTION("""COMPUTED_VALUE"""),4.03056) -> 4.03056 | I26: =IFERROR(__xludf.DUMMYFUNCTION("""COMPUTED_VALUE"""),"") | J26: =IFERROR(__xludf.DUMMYFUNCTION("""COMPUTED_VALUE"""),"") | K26: =IFERROR(__xludf.DUMMYFUNCTION("""COMPUTED_VALUE"""),"") | L26: =IFERROR(__xludf.DUMMYFUNCTION("""COMPUTED_VALUE"""),"") | M26: =IFERROR(__xludf.DUMMYFUNCTION("""COMPUTED_VALUE"""),"") | N26: =IFERROR(__xludf.DUMMYFUNCTION("""COMPUTED_VALUE"""),"")
A27: =IFERROR(__xludf.DUMMYFUNCTION("""COMPUTED_VALUE"""),"575-92003") -> 575-92003 | B27: =IFERROR(__xludf.DUMMYFUNCTION("""COMPUTED_VALUE"""),"DC25FS, Singleturn Body 3/8"" shaft, Flange SSI Durac MS23 side conn.") -> DC25FS, Singleturn Body 3/8" shaft, Flange SSI Durac MS23 side conn. | C27: =IFERROR(__xludf.DUMMYFUNCTION("""COMPUTED_VALUE"""),1.20944) -> 1.20944 | D27: =IFERROR(__xludf.DUMMYFUNCTION("""COMPUTED_VALUE"""),1.20944) -> 1.20944 | E27: =IFERROR(__xludf.DUMMYFUNCTION("""COMPUTED_VALUE"""),"") | F27: =IFERROR(__xludf.DUMMYFUNCTION("""COMPUTED_VALUE"""),"Cast AL Bulgaria (pc.)") -> Cast AL Bulgaria (pc.) | G27: =IFERROR(__xludf.DUMMYFUNCTION("""COMPUTED_VALUE"""),0.234) -> 0.234 | H27: =IFERROR(__xludf.DUMMYFUNCTION("""COMPUTED_VALUE"""),1.09044) -> 1.09044 | I27: =IFERROR(__xludf.DUMMYFUNCTION("""COMPUTED_VALUE"""),"AL USA (pc.)") -> AL USA (pc.) | J27: =IFERROR(__xludf.DUMMYFUNCTION("""COMPUTED_VALUE"""),0.07) -> 0.07 | K27: =IFERROR(__xludf.DUMMYFUNCTION("""COMPUTED_VALUE"""),0.11900000000000001) -> 0.119 | L27: =IFERROR(__xludf.DUMMYFUNCTION("""COMPUTED_VALUE"""),"") | M27: =IFERROR(__xludf.DUMMYFUNCTION("""COMPUTED_VALUE"""),"") | N27: =IFERROR(__xludf.DUMMYFUNCTION("""COMPUTED_VALUE"""),"")
A28: =IFERROR(__xludf.DUMMYFUNCTION("""COMPUTED_VALUE"""),"H25-FS-R3N") -> H25-FS-R3N | B28: =IFERROR(__xludf.DUMMYFUNCTION("""COMPUTED_VALUE"""),"Size 25 resolver 3/8"" shaft side mount w/ 10 pin conn") -> Size 25 resolver 3/8" shaft side mount w/ 10 pin conn | C28: =IFERROR(__xludf.DUMMYFUNCTION("""COMPUTED_VALUE"""),1.77574) -> 1.77574 | D28: =IFERROR(__xludf.DUMMYFUNCTION("""COMPUTED_VALUE"""),1.77574) -> 1.77574 | E28: =IFERROR(__xludf.DUMMYFUNCTION("""COMPUTED_VALUE"""),"") | F28: =IFERROR(__xludf.DUMMYFUNCTION("""COMPUTED_VALUE"""),"Cast AL Bulgaria (pc.)") -> Cast AL Bulgaria (pc.) | G28: =IFERROR(__xludf.DUMMYFUNCTION("""COMPUTED_VALUE"""),0.197) -> 0.197 | H28: =IFERROR(__xludf.DUMMYFUNCTION("""COMPUTED_VALUE"""),0.9180200000000001) -> 0.91802 | I28: =IFERROR(__xludf.DUMMYFUNCTION("""COMPUTED_VALUE"""),"AL USA (pc.)") -> AL USA (pc.) | J28: =IFERROR(__xludf.DUMMYFUNCTION("""COMPUTED_VALUE"""),0.07) -> 0.07 | K28: =IFERROR(__xludf.DUMMYFUNCTION("""COMPUTED_VALUE"""),0.11900000000000001) -> 0.119 | L28: =IFERROR(__xludf.DUMMYFUNCTION("""COMPUTED_VALUE"""),"Ф65 AL 2017 Italy") -> Ф65 AL 2017 Italy | M28: =IFERROR(__xludf.DUMMYFUNCTION("""COMPUTED_VALUE"""),0.057) -> 0.057 | N28: =IFERROR(__xludf.DUMMYFUNCTION("""COMPUTED_VALUE"""),0.73872) -> 0.73872
A29: =IFERROR(__xludf.DUMMYFUNCTION("""COMPUTED_VALUE"""),"H25-SE-10") -> H25-SE-10 | B29: =IFERROR(__xludf.DUMMYFUNCTION("""COMPUTED_VALUE"""),"Transducer 1 Turn C&A Flange servo mount with 10mm shaft") -> Transducer 1 Turn C&A Flange servo mount with 10mm shaft | C29: =IFERROR(__xludf.DUMMYFUNCTION("""COMPUTED_VALUE"""),4.717440000000001) -> 4.71744 | D29: =IFERROR(__xludf.DUMMYFUNCTION("""COMPUTED_VALUE"""),4.717440000000001) -> 4.71744 | E29: =IFERROR(__xludf.DUMMYFUNCTION("""COMPUTED_VALUE"""),"") | F29: =IFERROR(__xludf.DUMMYFUNCTION("""COMPUTED_VALUE"""),"Ф65 AL 2017 Italy") -> Ф65 AL 2017 Italy | G29: =IFERROR(__xludf.DUMMYFUNCTION("""COMPUTED_VALUE"""),0.311) -> 0.311 | H29: =IFERROR(__xludf.DUMMYFUNCTION("""COMPUTED_VALUE"""),4.03056) -> 4.03056 | I29: =IFERROR(__xludf.DUMMYFUNCTION("""COMPUTED_VALUE"""),"Ф65 AL 2017 Italy") -> Ф65 AL 2017 Italy | J29: =IFERROR(__xludf.DUMMYFUNCTION("""COMPUTED_VALUE"""),0.053) -> 0.053 | K29: =IFERROR(__xludf.DUMMYFUNCTION("""COMPUTED_VALUE"""),0.68688) -> 0.68688 | L29: =IFERROR(__xludf.DUMMYFUNCTION("""COMPUTED_VALUE"""),"") | M29: =IFERROR(__xludf.DUMMYFUNCTION("""COMPUTED_VALUE"""),"") | N29: =IFERROR(__xludf.DUMMYFUNCTION("""COMPUTED_VALUE"""),"")
A30: =IFERROR(__xludf.DUMMYFUNCTION("""COMPUTED_VALUE"""),"22140701А") -> 22140701А | B30: =IFERROR(__xludf.DUMMYFUNCTION("""COMPUTED_VALUE"""),"H25 Body with Shaft zeroed for HT-400x-L Single turn TR=1,4, 5KHz,2250Hz w/o conn") -> H25 Body with Shaft zeroed for HT-400x-L Single turn TR=1,4, 5KHz,2250Hz w/o conn | C30: =IFERROR(__xludf.DUMMYFUNCTION("""COMPUTED_VALUE"""),4.03056) -> 4.03056 | D30: =IFERROR(__xludf.DUMMYFUNCTION("""COMPUTED_VALUE"""),4.03056) -> 4.03056 | E30: =IFERROR(__xludf.DUMMYFUNCTION("""COMPUTED_VALUE"""),"") | F30: =IFERROR(__xludf.DUMMYFUNCTION("""COMPUTED_VALUE"""),"Ф65 AL 2017 Italy") -> Ф65 AL 2017 Italy | G30: =IFERROR(__xludf.DUMMYFUNCTION("""COMPUTED_VALUE"""),0.311) -> 0.311 | H30: =IFERROR(__xludf.DUMMYFUNCTION("""COMPUTED_VALUE"""),4.03056) -> 4.03056 | I30: =IFERROR(__xludf.DUMMYFUNCTION("""COMPUTED_VALUE"""),"") | J30: =IFERROR(__xludf.DUMMYFUNCTION("""COMPUTED_VALUE"""),"") | K30: =IFERROR(__xludf.DUMMYFUNCTION("""COMPUTED_VALUE"""),"") | L30: =IFERROR(__xludf.DUMMYFUNCTION("""COMPUTED_VALUE"""),"") | M30: =IFERROR(__xludf.DUMMYFUNCTION("""COMPUTED_VALUE"""),"") | N30: =IFERROR(__xludf.DUMMYFUNCTION("""COMPUTED_VALUE"""),"")
A31: =IFERROR(__xludf.DUMMYFUNCTION("""COMPUTED_VALUE"""),"575-91007") -> 575-91007 | B31: =IFERROR(__xludf.DUMMYFUNCTION("""COMPUTED_VALUE"""),"DC25FS16 </=9 min. 3/8"" shaft, flange , side conn") -> DC25FS16 </=9 min. 3/8" shaft, flange , side conn | C31: =IFERROR(__xludf.DUMMYFUNCTION("""COMPUTED_VALUE"""),1.15352) -> 1.15352 | D31: =IFERROR(__xludf.DUMMYFUNCTION("""COMPUTED_VALUE"""),1.15352) -> 1.15352 | E31: =IFERROR(__xludf.DUMMYFUNCTION("""COMPUTED_VALUE"""),"") | F31: =IFERROR(__xludf.DUMMYFUNCTION("""COMPUTED_VALUE"""),"Cast AL Bulgaria (pc.)") -> Cast AL Bulgaria (pc.) | G31: =IFERROR(__xludf.DUMMYFUNCTION("""COMPUTED_VALUE"""),0.222) -> 0.222 | H31: =IFERROR(__xludf.DUMMYFUNCTION("""COMPUTED_VALUE"""),1.03452) -> 1.03452 | I31: =IFERROR(__xludf.DUMMYFUNCTION("""COMPUTED_VALUE"""),"AL USA (pc.)") -> AL USA (pc.) | J31: =IFERROR(__xludf.DUMMYFUNCTION("""COMPUTED_VALUE"""),0.07) -> 0.07 | K31: =IFERROR(__xludf.DUMMYFUNCTION("""COMPUTED_VALUE"""),0.11900000000000001) -> 0.119 | L31: =IFERROR(__xludf.DUMMYFUNCTION("""COMPUTED_VALUE"""),"") | M31: =IFERROR(__xludf.DUMMYFUNCTION("""COMPUTED_VALUE"""),"") | N31: =IFERROR(__xludf.DUMMYFUNCTION("""COMPUTED_VALUE"""),"")
A32: =IFERROR(__xludf.DUMMYFUNCTION("""COMPUTED_VALUE"""),"H25-FE-10") -> H25-FE-10 | B32: =IFERROR(__xludf.DUMMYFUNCTION("""COMPUTED_VALUE"""),"Transducer 1 Turn C&A Flange TR=0.95, 5KHz, w/o conn") -> Transducer 1 Turn C&A Flange TR=0.95, 5KHz, w/o conn | C32: =IFERROR(__xludf.DUMMYFUNCTION("""COMPUTED_VALUE"""),4.14956) -> 4.14956 | D32: =IFERROR(__xludf.DUMMYFUNCTION("""COMPUTED_VALUE"""),4.14956) -> 4.14956 | E32: =IFERROR(__xludf.DUMMYFUNCTION("""COMPUTED_VALUE"""),"") | F32: =IFERROR(__xludf.DUMMYFUNCTION("""COMPUTED_VALUE"""),"Ф65 AL 2017 Italy") -> Ф65 AL 2017 Italy | G32: =IFERROR(__xludf.DUMMYFUNCTION("""COMPUTED_VALUE"""),0.311) -> 0.311 | H32: =IFERROR(__xludf.DUMMYFUNCTION("""COMPUTED_VALUE"""),4.03056) -> 4.03056 | I32: =IFERROR(__xludf.DUMMYFUNCTION("""COMPUTED_VALUE"""),"AL USA (pc.)") -> AL USA (pc.) | J32: =IFERROR(__xludf.DUMMYFUNCTION("""COMPUTED_VALUE"""),0.07) -> 0.07 | K32: =IFERROR(__xludf.DUMMYFUNCTION("""COMPUTED_VALUE"""),0.11900000000000001) -> 0.119 | L32: =IFERROR(__xludf.DUMMYFUNCTION("""COMPUTED_VALUE"""),"") | M32: =IFERROR(__xludf.DUMMYFUNCTION("""COMPUTED_VALUE"""),"") | N32: =IFERROR(__xludf.DUMMYFUNCTION("""COMPUTED_VALUE"""),"")
A33: =IFERROR(__xludf.DUMMYFUNCTION("""COMPUTED_VALUE"""),"H25-SS") -> H25-SS | B33: =IFERROR(__xludf.DUMMYFUNCTION("""COMPUTED_VALUE"""),"Size 25 resolver servo with side connector 0.95 TR@5000Hz 3/8"" shaft") -> Size 25 resolver servo with side connector 0.95 TR@5000Hz 3/8" shaft | C33: =IFERROR(__xludf.DUMMYFUNCTION("""COMPUTED_VALUE"""),2.4181800000000004) -> 2.41818 | D33: =IFERROR(__xludf.DUMMYFUNCTION("""COMPUTED_VALUE"""),2.4181800000000004) -> 2.41818 | E33: =IFERROR(__xludf.DUMMYFUNCTION("""COMPUTED_VALUE"""),"") | F33: =IFERROR(__xludf.DUMMYFUNCTION("""COMPUTED_VALUE"""),"Cast AL Bulgaria (pc.)") -> Cast AL Bulgaria (pc.) | G33: =IFERROR(__xludf.DUMMYFUNCTION("""COMPUTED_VALUE"""),0.213) -> 0.213 | H33: =IFERROR(__xludf.DUMMYFUNCTION("""COMPUTED_VALUE"""),0.99258) -> 0.99258 | I33: =IFERROR(__xludf.DUMMYFUNCTION("""COMPUTED_VALUE"""),"Ф65 AL 2017 Italy") -> Ф65 AL 2017 Italy | J33: =IFERROR(__xludf.DUMMYFUNCTION("""COMPUTED_VALUE"""),0.053) -> 0.053 | K33: =IFERROR(__xludf.DUMMYFUNCTION("""COMPUTED_VALUE"""),0.68688) -> 0.68688 | L33: =IFERROR(__xludf.DUMMYFUNCTION("""COMPUTED_VALUE"""),"Ф65 AL 2017 Italy") -> Ф65 AL 2017 Italy | M33: =IFERROR(__xludf.DUMMYFUNCTION("""COMPUTED_VALUE"""),0.057) -> 0.057 | N33: =IFERROR(__xludf.DUMMYFUNCTION("""COMPUTED_VALUE"""),0.73872) -> 0.73872
A34: =IFERROR(__xludf.DUMMYFUNCTION("""COMPUTED_VALUE"""),"575-01921") -> 575-01921 | B34: =IFERROR(__xludf.DUMMYFUNCTION("""COMPUTED_VALUE"""),"Resolver size 11, TR=0.5 2500 Hz, Control Transmitter +/- 7min.; 0,12"" shaft") -> Resolver size 11, TR=0.5 2500 Hz, Control Transmitter +/- 7min.; 0,12" shaft | C34: =IFERROR(__xludf.DUMMYFUNCTION("""COMPUTED_VALUE"""),0.0) -> 0 | D34: =IFERROR(__xludf.DUMMYFUNCTION("""COMPUTED_VALUE"""),"") | E34: =IFERROR(__xludf.DUMMYFUNCTION("""COMPUTED_VALUE"""),"") | G34: =IFERROR(__xludf.DUMMYFUNCTION("""COMPUTED_VALUE"""),"") | H34: =IFERROR(__xludf.DUMMYFUNCTION("""COMPUTED_VALUE"""),"") | I34: =IFERROR(__xludf.DUMMYFUNCTION("""COMPUTED_VALUE"""),"") | J34: =IFERROR(__xludf.DUMMYFUNCTION("""COMPUTED_VALUE"""),"") | K34: =IFERROR(__xludf.DUMMYFUNCTION("""COMPUTED_VALUE"""),"") | L34: =IFERROR(__xludf.DUMMYFUNCTION("""COMPUTED_VALUE"""),"") | M34: =IFERROR(__xludf.DUMMYFUNCTION("""COMPUTED_VALUE"""),"") | N34: =IFERROR(__xludf.DUMMYFUNCTION("""COMPUTED_VALUE"""),"")
A35: =IFERROR(__xludf.DUMMYFUNCTION("""COMPUTED_VALUE"""),"575-01912-3") -> 575-01912-3 | B35: =IFERROR(__xludf.DUMMYFUNCTION("""COMPUTED_VALUE"""),"Resolver size 11, TR=0,45 1000Hz, Acc. 3min. Transmitter; 0,12"" shaft with flat") -> Resolver size 11, TR=0,45 1000Hz, Acc. 3min. Transmitter; 0,12" shaft with flat | C35: =IFERROR(__xludf.DUMMYFUNCTION("""COMPUTED_VALUE"""),0.0) -> 0 | D35: =IFERROR(__xludf.DUMMYFUNCTION("""COMPUTED_VALUE"""),"") | E35: =IFERROR(__xludf.DUMMYFUNCTION("""COMPUTED_VALUE"""),"") | G35: =IFERROR(__xludf.DUMMYFUNCTION("""COMPUTED_VALUE"""),"") | H35: =IFERROR(__xludf.DUMMYFUNCTION("""COMPUTED_VALUE"""),"") | I35: =IFERROR(__xludf.DUMMYFUNCTION("""COMPUTED_VALUE"""),"") | J35: =IFERROR(__xludf.DUMMYFUNCTION("""COMPUTED_VALUE"""),"") | K35: =IFERROR(__xludf.DUMMYFUNCTION("""COMPUTED_VALUE"""),"") | L35: =IFERROR(__xludf.DUMMYFUNCTION("""COMPUTED_VALUE"""),"") | M35: =IFERROR(__xludf.DUMMYFUNCTION("""COMPUTED_VALUE"""),"") | N35: =IFERROR(__xludf.DUMMYFUNCTION("""COMPUTED_VALUE"""),"")
A36: =IFERROR(__xludf.DUMMYFUNCTION("""COMPUTED_VALUE"""),"575-01902") -> 575-01902 | B36: =IFERROR(__xludf.DUMMYFUNCTION("""COMPUTED_VALUE"""),"Resolver size 11, TR-0,95 Transmitter 5KHz; sorted into -1,-4,-8,-10") -> Resolver size 11, TR-0,95 Transmitter 5KHz; sorted into -1,-4,-8,-10 | C36: =IFERROR(__xludf.DUMMYFUNCTION("""COMPUTED_VALUE"""),0.0) -> 0 | D36: =IFERROR(__xludf.DUMMYFUNCTION("""COMPUTED_VALUE"""),"") | E36: =IFERROR(__xludf.DUMMYFUNCTION("""COMPUTED_VALUE"""),"") | G36: =IFERROR(__xludf.DUMMYFUNCTION("""COMPUTED_VALUE"""),"") | H36: =IFERROR(__xludf.DUMMYFUNCTION("""COMPUTED_VALUE"""),"") | I36: =IFERROR(__xludf.DUMMYFUNCTION("""COMPUTED_VALUE"""),"") | J36: =IFERROR(__xludf.DUMMYFUNCTION("""COMPUTED_VALUE"""),"") | K36: =IFERROR(__xludf.DUMMYFUNCTION("""COMPUTED_VALUE"""),"") | L36: =IFERROR(__xludf.DUMMYFUNCTION("""COMPUTED_VALUE"""),"") | M36: =IFERROR(__xludf.DUMMYFUNCTION("""COMPUTED_VALUE"""),"") | N36: =IFERROR(__xludf.DUMMYFUNCTION("""COMPUTED_VALUE"""),"")
A37: =IFERROR(__xludf.DUMMYFUNCTION("""COMPUTED_VALUE"""),"575-01911-2") -> 575-01911-2 | B37: =IFERROR(__xludf.DUMMYFUNCTION("""COMPUTED_VALUE"""),"Resolver size 11, TR=,50 2500Hz ACCUR.=<7 with .30"" shaft lengt") -> Resolver size 11, TR=,50 2500Hz ACCUR.=<7 with .30" shaft lengt | C37: =IFERROR(__xludf.DUMMYFUNCTION("""COMPUTED_VALUE"""),0.0) -> 0 | D37: =IFERROR(__xludf.DUMMYFUNCTION("""COMPUTED_VALUE"""),"") | E37: =IFERROR(__xludf.DUMMYFUNCTION("""COMPUTED_VALUE"""),"") | G37: =IFERROR(__xludf.DUMMYFUNCTION("""COMPUTED_VALUE"""),"") | H37: =IFERROR(__xludf.DUMMYFUNCTION("""COMPUTED_VALUE"""),"") | I37: =IFERROR(__xludf.DUMMYFUNCTION("""COMPUTED_VALUE"""),"") | J37: =IFERROR(__xludf.DUMMYFUNCTION("""COMPUTED_VALUE"""),"") | K37: =IFERROR(__xludf.DUMMYFUNCTION("""COMPUTED_VALUE"""),"") | L37: =IFERROR(__xludf.DUMMYFUNCTION("""COMPUTED_VALUE"""),"") | M37: =IFERROR(__xludf.DUMMYFUNCTION("""COMPUTED_VALUE"""),"") | N37: =IFERROR(__xludf.DUMMYFUNCTION("""COMPUTED_VALUE"""),"")
A38: =IFERROR(__xludf.DUMMYFUNCTION("""COMPUTED_VALUE"""),"575-01912") -> 575-01912 | B38: =IFERROR(__xludf.DUMMYFUNCTION("""COMPUTED_VALUE"""),"Resolver size 11, TR=0,45 1000Hz, Transmitter Acc. Unsorted") -> Resolver size 11, TR=0,45 1000Hz, Transmitter Acc. Unsorted | C38: =IFERROR(__xludf.DUMMYFUNCTION("""COMPUTED_VALUE"""),0.0) -> 0 | D38: =IFERROR(__xludf.DUMMYFUNCTION("""COMPUTED_VALUE"""),"") | E38: =IFERROR(__xludf.DUMMYFUNCTION("""COMPUTED_VALUE"""),"") | G38: =IFERROR(__xludf.DUMMYFUNCTION("""COMPUTED_VALUE"""),"") | H38: =IFERROR(__xludf.DUMMYFUNCTION("""COMPUTED_VALUE"""),"") | I38: =IFERROR(__xludf.DUMMYFUNCTION("""COMPUTED_VALUE"""),"") | J38: =IFERROR(__xludf.DUMMYFUNCTION("""COMPUTED_VALUE"""),"") | K38: =IFERROR(__xludf.DUMMYFUNCTION("""COMPUTED_VALUE"""),"") | L38: =IFERROR(__xludf.DUMMYFUNCTION("""COMPUTED_VALUE"""),"") | M38: =IFERROR(__xludf.DUMMYFUNCTION("""COMPUTED_VALUE"""),"") | N38: =IFERROR(__xludf.DUMMYFUNCTION("""COMPUTED_VALUE"""),"")
A39: =IFERROR(__xludf.DUMMYFUNCTION("""COMPUTED_VALUE"""),"575-01924") -> 575-01924 | B39: =IFERROR(__xludf.DUMMYFUNCTION("""COMPUTED_VALUE"""),"Resolver size 11, TR=1,0 1000Hz, control Transmitter +/-7 min") -> Resolver size 11, TR=1,0 1000Hz, control Transmitter +/-7 min | C39: =IFERROR(__xludf.DUMMYFUNCTION("""COMPUTED_VALUE"""),0.0) -> 0 | D39: =IFERROR(__xludf.DUMMYFUNCTION("""COMPUTED_VALUE"""),"") | E39: =IFERROR(__xludf.DUMMYFUNCTION("""COMPUTED_VALUE"""),"") | G39: =IFERROR(__xludf.DUMMYFUNCTION("""COMPUTED_VALUE"""),"") | H39: =IFERROR(__xludf.DUMMYFUNCTION("""COMPUTED_VALUE"""),"") | I39: =IFERROR(__xludf.DUMMYFUNCTION("""COMPUTED_VALUE"""),"") | J39: =IFERROR(__xludf.DUMMYFUNCTION("""COMPUTED_VALUE"""),"") | K39: =IFERROR(__xludf.DUMMYFUNCTION("""COMPUTED_VALUE"""),"") | L39: =IFERROR(__xludf.DUMMYFUNCTION("""COMPUTED_VALUE"""),"") | M39: =IFERROR(__xludf.DUMMYFUNCTION("""COMPUTED_VALUE"""),"") | N39: =IFERROR(__xludf.DUMMYFUNCTION("""COMPUTED_VALUE"""),"")
A40: =IFERROR(__xludf.DUMMYFUNCTION("""COMPUTED_VALUE"""),"575-01920-1") -> 575-01920-1 | B40: =IFERROR(__xludf.DUMMYFUNCTION("""COMPUTED_VALUE"""),"Resolver size 11, TR=0.45 400Hz,Transmitter w/ flat; Acc.=<7 min.") -> Resolver size 11, TR=0.45 400Hz,Transmitter w/ flat; Acc.=<7 min. | C40: =IFERROR(__xludf.DUMMYFUNCTION("""COMPUTED_VALUE"""),0.0) -> 0 | D40: =IFERROR(__xludf.DUMMYFUNCTION("""COMPUTED_VALUE"""),"") | E40: =IFERROR(__xludf.DUMMYFUNCTION("""COMPUTED_VALUE"""),"") | G40: =IFERROR(__xludf.DUMMYFUNCTION("""COMPUTED_VALUE"""),"") | H40: =IFERROR(__xludf.DUMMYFUNCTION("""COMPUTED_VALUE"""),"") | I40: =IFERROR(__xludf.DUMMYFUNCTION("""COMPUTED_VALUE"""),"") | J40: =IFERROR(__xludf.DUMMYFUNCTION("""COMPUTED_VALUE"""),"") | K40: =IFERROR(__xludf.DUMMYFUNCTION("""COMPUTED_VALUE"""),"") | L40: =IFERROR(__xludf.DUMMYFUNCTION("""COMPUTED_VALUE"""),"") | M40: =IFERROR(__xludf.DUMMYFUNCTION("""COMPUTED_VALUE"""),"") | N40: =IFERROR(__xludf.DUMMYFUNCTION("""COMPUTED_VALUE"""),"")
A41: =IFERROR(__xludf.DUMMYFUNCTION("""COMPUTED_VALUE"""),"575-01907") -> 575-01907 | B41: =IFERROR(__xludf.DUMMYFUNCTION("""COMPUTED_VALUE"""),"Resolver size 11, TR=1,40 2250Hz") -> Resolver size 11, TR=1,40 2250Hz | C41: =IFERROR(__xludf.DUMMYFUNCTION("""COMPUTED_VALUE"""),0.0) -> 0 | D41: =IFERROR(__xludf.DUMMYFUNCTION("""COMPUTED_VALUE"""),"") | E41: =IFERROR(__xludf.DUMMYFUNCTION("""COMPUTED_VALUE"""),"") | G41: =IFERROR(__xludf.DUMMYFUNCTION("""COMPUTED_VALUE"""),"") | H41: =IFERROR(__xludf.DUMMYFUNCTION("""COMPUTED_VALUE"""),"") | I41: =IFERROR(__xludf.DUMMYFUNCTION("""COMPUTED_VALUE"""),"") | J41: =IFERROR(__xludf.DUMMYFUNCTION("""COMPUTED_VALUE"""),"") | K41: =IFERROR(__xludf.DUMMYFUNCTION("""COMPUTED_VALUE"""),"") | L41: =IFERROR(__xludf.DUMMYFUNCTION("""COMPUTED_VALUE"""),"") | M41: =IFERROR(__xludf.DUMMYFUNCTION("""COMPUTED_VALUE"""),"") | N41: =IFERROR(__xludf.DUMMYFUNCTION("""COMPUTED_VALUE"""),"")
A42: =IFERROR(__xludf.DUMMYFUNCTION("""COMPUTED_VALUE"""),"575-01909") -> 575-01909 | B42: =IFERROR(__xludf.DUMMYFUNCTION("""COMPUTED_VALUE"""),"Resolver size 11,</=20min TR=0,95 5КHz 2speed") -> Resolver size 11,</=20min TR=0,95 5КHz 2speed | C42: =IFERROR(__xludf.DUMMYFUNCTION("""COMPUTED_VALUE"""),0.0) -> 0 | D42: =IFERROR(__xludf.DUMMYFUNCTION("""COMPUTED_VALUE"""),"") | E42: =IFERROR(__xludf.DUMMYFUNCTION("""COMPUTED_VALUE"""),"") | G42: =IFERROR(__xludf.DUMMYFUNCTION("""COMPUTED_VALUE"""),"") | H42: =IFERROR(__xludf.DUMMYFUNCTION("""COMPUTED_VALUE"""),"") | I42: =IFERROR(__xludf.DUMMYFUNCTION("""COMPUTED_VALUE"""),"") | J42: =IFERROR(__xludf.DUMMYFUNCTION("""COMPUTED_VALUE"""),"") | K42: =IFERROR(__xludf.DUMMYFUNCTION("""COMPUTED_VALUE"""),"") | L42: =IFERROR(__xludf.DUMMYFUNCTION("""COMPUTED_VALUE"""),"") | M42: =IFERROR(__xludf.DUMMYFUNCTION("""COMPUTED_VALUE"""),"") | N42: =IFERROR(__xludf.DUMMYFUNCTION("""COMPUTED_VALUE"""),"")
A43: =IFERROR(__xludf.DUMMYFUNCTION("""COMPUTED_VALUE"""),"575-60025") -> 575-60025 | B43: =IFERROR(__xludf.DUMMYFUNCTION("""COMPUTED_VALUE"""),"NR60 Multiturn Body 3/8"" shaft; Nitrile seal Sq. Flange; End conn.") -> NR60 Multiturn Body 3/8" shaft; Nitrile seal Sq. Flange; End conn. | C43: =IFERROR(__xludf.DUMMYFUNCTION("""COMPUTED_VALUE"""),2.9812600000000002) -> 2.98126 | D43: =IFERROR(__xludf.DUMMYFUNCTION("""COMPUTED_VALUE"""),2.9812600000000002) -> 2.98126 | E43: =IFERROR(__xludf.DUMMYFUNCTION("""COMPUTED_VALUE"""),"") | F43: =IFERROR(__xludf.DUMMYFUNCTION("""COMPUTED_VALUE"""),"Ф62 AL 2017 Italy") -> Ф62 AL 2017 Italy | G43: =IFERROR(__xludf.DUMMYFUNCTION("""COMPUTED_VALUE"""),0.216) -> 0.216 | H43: =IFERROR(__xludf.DUMMYFUNCTION("""COMPUTED_VALUE"""),2.79936) -> 2.79936 | I43: =IFERROR(__xludf.DUMMYFUNCTION("""COMPUTED_VALUE"""),"AL USA (pc.)") -> AL USA (pc.) | J43: =IFERROR(__xludf.DUMMYFUNCTION("""COMPUTED_VALUE"""),0.107) -> 0.107 | K43: =IFERROR(__xludf.DUMMYFUNCTION("""COMPUTED_VALUE"""),0.18189999999999998) -> 0.1819 | L43: =IFERROR(__xludf.DUMMYFUNCTION("""COMPUTED_VALUE"""),"") | M43: =IFERROR(__xludf.DUMMYFUNCTION("""COMPUTED_VALUE"""),"") | N43: =IFERROR(__xludf.DUMMYFUNCTION("""COMPUTED_VALUE"""),"")
A44: =IFERROR(__xludf.DUMMYFUNCTION("""COMPUTED_VALUE"""),"H25V-FE-10") -> H25V-FE-10 | B44: =IFERROR(__xludf.DUMMYFUNCTION("""COMPUTED_VALUE"""),"H25 Flange mount, Viton Seal, End Connector w/10mm shaft 0.95 TR @ 5000Hz") -> H25 Flange mount, Viton Seal, End Connector w/10mm shaft 0.95 TR @ 5000Hz | C44: =IFERROR(__xludf.DUMMYFUNCTION("""COMPUTED_VALUE"""),4.14956) -> 4.14956 | D44: =IFERROR(__xludf.DUMMYFUNCTION("""COMPUTED_VALUE"""),4.14956) -> 4.14956 | E44: =IFERROR(__xludf.DUMMYFUNCTION("""COMPUTED_VALUE"""),"") | F44: =IFERROR(__xludf.DUMMYFUNCTION("""COMPUTED_VALUE"""),"Ф65 AL 2017 Italy") -> Ф65 AL 2017 Italy | G44: =IFERROR(__xludf.DUMMYFUNCTION("""COMPUTED_VALUE"""),0.311) -> 0.311 | H44: =IFERROR(__xludf.DUMMYFUNCTION("""COMPUTED_VALUE"""),4.03056) -> 4.03056 | I44: =IFERROR(__xludf.DUMMYFUNCTION("""COMPUTED_VALUE"""),"AL USA (pc.)") -> AL USA (pc.) | J44: =IFERROR(__xludf.DUMMYFUNCTION("""COMPUTED_VALUE"""),0.07) -> 0.07 | K44: =IFERROR(__xludf.DUMMYFUNCTION("""COMPUTED_VALUE"""),0.11900000000000001) -> 0.119 | L44: =IFERROR(__xludf.DUMMYFUNCTION("""COMPUTED_VALUE"""),"") | M44: =IFERROR(__xludf.DUMMYFUNCTION("""COMPUTED_VALUE"""),"") | N44: =IFERROR(__xludf.DUMMYFUNCTION("""COMPUTED_VALUE"""),"")
A45: =IFERROR(__xludf.DUMMYFUNCTION("""COMPUTED_VALUE"""),"575-01921-704") -> 575-01921-704 | B45: =IFERROR(__xludf.DUMMYFUNCTION("""COMPUTED_VALUE"""),"Resolver size 11 w/seal 2.5Khz 0.5TR 0,1200"" shaft +/- 7min,12"" side leads") -> Resolver size 11 w/seal 2.5Khz 0.5TR 0,1200" shaft +/- 7min,12" side leads | C45: =IFERROR(__xludf.DUMMYFUNCTION("""COMPUTED_VALUE"""),0.0) -> 0 | D45: =IFERROR(__xludf.DUMMYFUNCTION("""COMPUTED_VALUE"""),"") | E45: =IFERROR(__xludf.DUMMYFUNCTION("""COMPUTED_VALUE"""),"") | F45: =IFERROR(__xludf.DUMMYFUNCTION("""COMPUTED_VALUE"""),"Ф28 S303") -> Ф28 S303 | G45: =IFERROR(__xludf.DUMMYFUNCTION("""COMPUTED_VALUE"""),"") | H45: =IFERROR(__xludf.DUMMYFUNCTION("""COMPUTED_VALUE"""),"") | I45: =IFERROR(__xludf.DUMMYFUNCTION("""COMPUTED_VALUE"""),"") | J45: =IFERROR(__xludf.DUMMYFUNCTION("""COMPUTED_VALUE"""),"") | K45: =IFERROR(__xludf.DUMMYFUNCTION("""COMPUTED_VALUE"""),"") | L45: =IFERROR(__xludf.DUMMYFUNCTION("""COMPUTED_VALUE"""),"") | M45: =IFERROR(__xludf.DUMMYFUNCTION("""COMPUTED_VALUE"""),"") | N45: =IFERROR(__xludf.DUMMYFUNCTION("""COMPUTED_VALUE"""),"")
A46: =IFERROR(__xludf.DUMMYFUNCTION("""COMPUTED_VALUE"""),"575-01903") -> 575-01903 | B46: =IFERROR(__xludf.DUMMYFUNCTION("""COMPUTED_VALUE"""),"Harowe11 BRW-300-M95B-01 AMCI # R11W-M10/7-1") -> Harowe11 BRW-300-M95B-01 AMCI # R11W-M10/7-1 | C46: =IFERROR(__xludf.DUMMYFUNCTION("""COMPUTED_VALUE"""),0.0) -> 0 | D46: =IFERROR(__xludf.DUMMYFUNCTION("""COMPUTED_VALUE"""),"") | E46: =IFERROR(__xludf.DUMMYFUNCTION("""COMPUTED_VALUE"""),"") | G46: =IFERROR(__xludf.DUMMYFUNCTION("""COMPUTED_VALUE"""),"") | H46: =IFERROR(__xludf.DUMMYFUNCTION("""COMPUTED_VALUE"""),"") | I46: =IFERROR(__xludf.DUMMYFUNCTION("""COMPUTED_VALUE"""),"") | J46: =IFERROR(__xludf.DUMMYFUNCTION("""COMPUTED_VALUE"""),"") | K46: =IFERROR(__xludf.DUMMYFUNCTION("""COMPUTED_VALUE"""),"") | L46: =IFERROR(__xludf.DUMMYFUNCTION("""COMPUTED_VALUE"""),"") | M46: =IFERROR(__xludf.DUMMYFUNCTION("""COMPUTED_VALUE"""),"") | N46: =IFERROR(__xludf.DUMMYFUNCTION("""COMPUTED_VALUE"""),"")
A47: =IFERROR(__xludf.DUMMYFUNCTION("""COMPUTED_VALUE"""),"575-60001") -> 575-60001 | B47: =IFERROR(__xludf.DUMMYFUNCTION("""COMPUTED_VALUE"""),"NR 60 Multiturn Body 6mm shaft; Nitrile seal; 58mm servo; End conn") -> NR 60 Multiturn Body 6mm shaft; Nitrile seal; 58mm servo; End conn | C47: =IFERROR(__xludf.DUMMYFUNCTION("""COMPUTED_VALUE"""),3.6806400000000004) -> 3.68064 | D47: =IFERROR(__xludf.DUMMYFUNCTION("""COMPUTED_VALUE"""),3.6806400000000004) -> 3.68064 | E47: =IFERROR(__xludf.DUMMYFUNCTION("""COMPUTED_VALUE"""),"") | F47: =IFERROR(__xludf.DUMMYFUNCTION("""COMPUTED_VALUE"""),"Ф62 AL 2017 Italy") -> Ф62 AL 2017 Italy | G47: =IFERROR(__xludf.DUMMYFUNCTION("""COMPUTED_VALUE"""),0.216) -> 0.216 | H47: =IFERROR(__xludf.DUMMYFUNCTION("""COMPUTED_VALUE"""),2.79936) -> 2.79936 | I47: =IFERROR(__xludf.DUMMYFUNCTION("""COMPUTED_VALUE"""),"Ф62 AL 2017 Italy") -> Ф62 AL 2017 Italy | J47: =IFERROR(__xludf.DUMMYFUNCTION("""COMPUTED_VALUE"""),0.068) -> 0.068 | K47: =IFERROR(__xludf.DUMMYFUNCTION("""COMPUTED_VALUE"""),0.8812800000000002) -> 0.88128 | L47: =IFERROR(__xludf.DUMMYFUNCTION("""COMPUTED_VALUE"""),"") | M47: =IFERROR(__xludf.DUMMYFUNCTION("""COMPUTED_VALUE"""),"") | N47: =IFERROR(__xludf.DUMMYFUNCTION("""COMPUTED_VALUE"""),"")
A48: =IFERROR(__xludf.DUMMYFUNCTION("""COMPUTED_VALUE"""),"575-60005") -> 575-60005 | C48: =IFERROR(__xludf.DUMMYFUNCTION("""COMPUTED_VALUE"""),2.9812600000000002) -> 2.98126 | D48: =IFERROR(__xludf.DUMMYFUNCTION("""COMPUTED_VALUE"""),2.9812600000000002) -> 2.98126 | E48: =IFERROR(__xludf.DUMMYFUNCTION("""COMPUTED_VALUE"""),"") | F48: =IFERROR(__xludf.DUMMYFUNCTION("""COMPUTED_VALUE"""),"Ф62 AL 2017 Italy") -> Ф62 AL 2017 Italy | G48: =IFERROR(__xludf.DUMMYFUNCTION("""COMPUTED_VALUE"""),0.216) -> 0.216 | H48: =IFERROR(__xludf.DUMMYFUNCTION("""COMPUTED_VALUE"""),2.79936) -> 2.79936 | I48: =IFERROR(__xludf.DUMMYFUNCTION("""COMPUTED_VALUE"""),"AL USA (pc.)") -> AL USA (pc.) | J48: =IFERROR(__xludf.DUMMYFUNCTION("""COMPUTED_VALUE"""),0.107) -> 0.107 | K48: =IFERROR(__xludf.DUMMYFUNCTION("""COMPUTED_VALUE"""),0.18189999999999998) -> 0.1819 | L48: =IFERROR(__xludf.DUMMYFUNCTION("""COMPUTED_VALUE"""),"") | M48: =IFERROR(__xludf.DUMMYFUNCTION("""COMPUTED_VALUE"""),"") | N48: =IFERROR(__xludf.DUMMYFUNCTION("""COMPUTED_VALUE"""),"")
A49: =IFERROR(__xludf.DUMMYFUNCTION("""COMPUTED_VALUE"""),"575-60023") -> 575-60023 | C49: =IFERROR(__xludf.DUMMYFUNCTION("""COMPUTED_VALUE"""),3.6806400000000004) -> 3.68064 | D49: =IFERROR(__xludf.DUMMYFUNCTION("""COMPUTED_VALUE"""),3.6806400000000004) -> 3.68064 | E49: =IFERROR(__xludf.DUMMYFUNCTION("""COMPUTED_VALUE"""),"") | F49: =IFERROR(__xludf.DUMMYFUNCTION("""COMPUTED_VALUE"""),"Ф62 AL 2017 Italy") -> Ф62 AL 2017 Italy | G49: =IFERROR(__xludf.DUMMYFUNCTION("""COMPUTED_VALUE"""),0.216) -> 0.216 | H49: =IFERROR(__xludf.DUMMYFUNCTION("""COMPUTED_VALUE"""),2.79936) -> 2.79936 | I49: =IFERROR(__xludf.DUMMYFUNCTION("""COMPUTED_VALUE"""),"Ф62 AL 2017 Italy") -> Ф62 AL 2017 Italy | J49: =IFERROR(__xludf.DUMMYFUNCTION("""COMPUTED_VALUE"""),0.068) -> 0.068 | K49: =IFERROR(__xludf.DUMMYFUNCTION("""COMPUTED_VALUE"""),0.8812800000000002) -> 0.88128 | L49: =IFERROR(__xludf.DUMMYFUNCTION("""COMPUTED_VALUE"""),"") | M49: =IFERROR(__xludf.DUMMYFUNCTION("""COMPUTED_VALUE"""),"") | N49: =IFERROR(__xludf.DUMMYFUNCTION("""COMPUTED_VALUE"""),"")
A50: =IFERROR(__xludf.DUMMYFUNCTION("""COMPUTED_VALUE"""),"575-60027") -> 575-60027 | C50: =IFERROR(__xludf.DUMMYFUNCTION("""COMPUTED_VALUE"""),3.6806400000000004) -> 3.68064 | D50: =IFERROR(__xludf.DUMMYFUNCTION("""COMPUTED_VALUE"""),3.6806400000000004) -> 3.68064 | E50: =IFERROR(__xludf.DUMMYFUNCTION("""COMPUTED_VALUE"""),"") | F50: =IFERROR(__xludf.DUMMYFUNCTION("""COMPUTED_VALUE"""),"Ф62 AL 2017 Italy") -> Ф62 AL 2017 Italy | G50: =IFERROR(__xludf.DUMMYFUNCTION("""COMPUTED_VALUE"""),0.216) -> 0.216 | H50: =IFERROR(__xludf.DUMMYFUNCTION("""COMPUTED_VALUE"""),2.79936) -> 2.79936 | I50: =IFERROR(__xludf.DUMMYFUNCTION("""COMPUTED_VALUE"""),"Ф62 AL 2017 Italy") -> Ф62 AL 2017 Italy | J50: =IFERROR(__xludf.DUMMYFUNCTION("""COMPUTED_VALUE"""),0.068) -> 0.068 | K50: =IFERROR(__xludf.DUMMYFUNCTION("""COMPUTED_VALUE"""),0.8812800000000002) -> 0.88128 | L50: =IFERROR(__xludf.DUMMYFUNCTION("""COMPUTED_VALUE"""),"") | M50: =IFERROR(__xludf.DUMMYFUNCTION("""COMPUTED_VALUE"""),"") | N50: =IFERROR(__xludf.DUMMYFUNCTION("""COMPUTED_VALUE"""),"")
A51: =IFERROR(__xludf.DUMMYFUNCTION("""COMPUTED_VALUE"""),"575-60029") -> 575-60029 | C51: =IFERROR(__xludf.DUMMYFUNCTION("""COMPUTED_VALUE"""),2.9812600000000002) -> 2.98126 | D51: =IFERROR(__xludf.DUMMYFUNCTION("""COMPUTED_VALUE"""),2.9812600000000002) -> 2.98126 | E51: =IFERROR(__xludf.DUMMYFUNCTION("""COMPUTED_VALUE"""),"") | F51: =IFERROR(__xludf.DUMMYFUNCTION("""COMPUTED_VALUE"""),"Ф62 AL 2017 Italy") -> Ф62 AL 2017 Italy | G51: =IFERROR(__xludf.DUMMYFUNCTION("""COMPUTED_VALUE"""),0.216) -> 0.216 | H51: =IFERROR(__xludf.DUMMYFUNCTION("""COMPUTED_VALUE"""),2.79936) -> 2.79936 | I51: =IFERROR(__xludf.DUMMYFUNCTION("""COMPUTED_VALUE"""),"AL USA (pc.)") -> AL USA (pc.) | J51: =IFERROR(__xludf.DUMMYFUNCTION("""COMPUTED_VALUE"""),0.107) -> 0.107 | K51: =IFERROR(__xludf.DUMMYFUNCTION("""COMPUTED_VALUE"""),0.18189999999999998) -> 0.1819 | L51: =IFERROR(__xludf.DUMMYFUNCTION("""COMPUTED_VALUE"""),"") | M51: =IFERROR(__xludf.DUMMYFUNCTION("""COMPUTED_VALUE"""),"") | N51: =IFERROR(__xludf.DUMMYFUNCTION("""COMPUTED_VALUE"""),"")
A52: =IFERROR(__xludf.DUMMYFUNCTION("""COMPUTED_VALUE"""),"575-01910") -> 575-01910 | B52: =IFERROR(__xludf.DUMMYFUNCTION("""COMPUTED_VALUE"""),"Res. For HT-6 R11X-J 12/7 w/0,7""I. shaft") -> Res. For HT-6 R11X-J 12/7 w/0,7"I. shaft | C52: =IFERROR(__xludf.DUMMYFUNCTION("""COMPUTED_VALUE"""),0.0) -> 0 | D52: =IFERROR(__xludf.DUMMYFUNCTION("""COMPUTED_VALUE"""),"") | E52: =IFERROR(__xludf.DUMMYFUNCTION("""COMPUTED_VALUE"""),"") | G52: =IFERROR(__xludf.DUMMYFUNCTION("""COMPUTED_VALUE"""),"") | H52: =IFERROR(__xludf.DUMMYFUNCTION("""COMPUTED_VALUE"""),"") | I52: =IFERROR(__xludf.DUMMYFUNCTION("""COMPUTED_VALUE"""),"") | J52: =IFERROR(__xludf.DUMMYFUNCTION("""COMPUTED_VALUE"""),"") | K52: =IFERROR(__xludf.DUMMYFUNCTION("""COMPUTED_VALUE"""),"") | L52: =IFERROR(__xludf.DUMMYFUNCTION("""COMPUTED_VALUE"""),"") | M52: =IFERROR(__xludf.DUMMYFUNCTION("""COMPUTED_VALUE"""),"") | N52: =IFERROR(__xludf.DUMMYFUNCTION("""COMPUTED_VALUE"""),"")
A53: =IFERROR(__xludf.DUMMYFUNCTION("""COMPUTED_VALUE"""),"575-01911") -> 575-01911 | B53: =IFERROR(__xludf.DUMMYFUNCTION("""COMPUTED_VALUE"""),"Res. Size 11 Freq.=2500 Hz, T.R.=.50, Acc=<7, control xfmr.") -> Res. Size 11 Freq.=2500 Hz, T.R.=.50, Acc=<7, control xfmr. | C53: =IFERROR(__xludf.DUMMYFUNCTION("""COMPUTED_VALUE"""),0.0) -> 0 | D53: =IFERROR(__xludf.DUMMYFUNCTION("""COMPUTED_VALUE"""),"") | E53: =IFERROR(__xludf.DUMMYFUNCTION("""COMPUTED_VALUE"""),"") | G53: =IFERROR(__xludf.DUMMYFUNCTION("""COMPUTED_VALUE"""),"") | H53: =IFERROR(__xludf.DUMMYFUNCTION("""COMPUTED_VALUE"""),"") | I53: =IFERROR(__xludf.DUMMYFUNCTION("""COMPUTED_VALUE"""),"") | J53: =IFERROR(__xludf.DUMMYFUNCTION("""COMPUTED_VALUE"""),"") | K53: =IFERROR(__xludf.DUMMYFUNCTION("""COMPUTED_VALUE"""),"") | L53: =IFERROR(__xludf.DUMMYFUNCTION("""COMPUTED_VALUE"""),"") | M53: =IFERROR(__xludf.DUMMYFUNCTION("""COMPUTED_VALUE"""),"") | N53: =IFERROR(__xludf.DUMMYFUNCTION("""COMPUTED_VALUE"""),"")
A54: =IFERROR(__xludf.DUMMYFUNCTION("""COMPUTED_VALUE"""),"575-01913") -> 575-01913 | B54: =IFERROR(__xludf.DUMMYFUNCTION("""COMPUTED_VALUE"""),"Res. Size 11 Freq.=2500 Hz, T.R.=.98, Acc<7") -> Res. Size 11 Freq.=2500 Hz, T.R.=.98, Acc<7 | C54: =IFERROR(__xludf.DUMMYFUNCTION("""COMPUTED_VALUE"""),0.0) -> 0 | D54: =IFERROR(__xludf.DUMMYFUNCTION("""COMPUTED_VALUE"""),"") | E54: =IFERROR(__xludf.DUMMYFUNCTION("""COMPUTED_VALUE"""),"") | G54: =IFERROR(__xludf.DUMMYFUNCTION("""COMPUTED_VALUE"""),"") | H54: =IFERROR(__xludf.DUMMYFUNCTION("""COMPUTED_VALUE"""),"") | I54: =IFERROR(__xludf.DUMMYFUNCTION("""COMPUTED_VALUE"""),"") | J54: =IFERROR(__xludf.DUMMYFUNCTION("""COMPUTED_VALUE"""),"") | K54: =IFERROR(__xludf.DUMMYFUNCTION("""COMPUTED_VALUE"""),"") | L54: =IFERROR(__xludf.DUMMYFUNCTION("""COMPUTED_VALUE"""),"") | M54: =IFERROR(__xludf.DUMMYFUNCTION("""COMPUTED_VALUE"""),"") | N54: =IFERROR(__xludf.DUMMYFUNCTION("""COMPUTED_VALUE"""),"")
A55: =IFERROR(__xludf.DUMMYFUNCTION("""COMPUTED_VALUE"""),"575-01917") -> 575-01917 | B55: =IFERROR(__xludf.DUMMYFUNCTION("""COMPUTED_VALUE"""),"Res. Size 11, T.R.=.50 Freq.=2.5k, Accur.=<10, Control Transfoemer , 2 Speed") -> Res. Size 11, T.R.=.50 Freq.=2.5k, Accur.=<10, Control Transfoemer , 2 Speed | C55: =IFERROR(__xludf.DUMMYFUNCTION("""COMPUTED_VALUE"""),0.0) -> 0 | D55: =IFERROR(__xludf.DUMMYFUNCTION("""COMPUTED_VALUE"""),"") | E55: =IFERROR(__xludf.DUMMYFUNCTION("""COMPUTED_VALUE"""),"") | G55: =IFERROR(__xludf.DUMMYFUNCTION("""COMPUTED_VALUE"""),"") | H55: =IFERROR(__xludf.DUMMYFUNCTION("""COMPUTED_VALUE"""),"") | I55: =IFERROR(__xludf.DUMMYFUNCTION("""COMPUTED_VALUE"""),"") | J55: =IFERROR(__xludf.DUMMYFUNCTION("""COMPUTED_VALUE"""),"") | K55: =IFERROR(__xludf.DUMMYFUNCTION("""COMPUTED_VALUE"""),"") | L55: =IFERROR(__xludf.DUMMYFUNCTION("""COMPUTED_VALUE"""),"") | M55: =IFERROR(__xludf.DUMMYFUNCTION("""COMPUTED_VALUE"""),"") | N55: =IFERROR(__xludf.DUMMYFUNCTION("""COMPUTED_VALUE"""),"")
A56: =IFERROR(__xludf.DUMMYFUNCTION("""COMPUTED_VALUE"""),"575-01918") -> 575-01918 | B56: =IFERROR(__xludf.DUMMYFUNCTION("""COMPUTED_VALUE"""),"Res. Size 11 T.R.=0.54, Freq.= 4 k. ACCUR.=<7, Control Transmitter") -> Res. Size 11 T.R.=0.54, Freq.= 4 k. ACCUR.=<7, Control Transmitter | C56: =IFERROR(__xludf.DUMMYFUNCTION("""COMPUTED_VALUE"""),0.0) -> 0 | D56: =IFERROR(__xludf.DUMMYFUNCTION("""COMPUTED_VALUE"""),"") | E56: =IFERROR(__xludf.DUMMYFUNCTION("""COMPUTED_VALUE"""),"") | G56: =IFERROR(__xludf.DUMMYFUNCTION("""COMPUTED_VALUE"""),"") | H56: =IFERROR(__xludf.DUMMYFUNCTION("""COMPUTED_VALUE"""),"") | I56: =IFERROR(__xludf.DUMMYFUNCTION("""COMPUTED_VALUE"""),"") | J56: =IFERROR(__xludf.DUMMYFUNCTION("""COMPUTED_VALUE"""),"") | K56: =IFERROR(__xludf.DUMMYFUNCTION("""COMPUTED_VALUE"""),"") | L56: =IFERROR(__xludf.DUMMYFUNCTION("""COMPUTED_VALUE"""),"") | M56: =IFERROR(__xludf.DUMMYFUNCTION("""COMPUTED_VALUE"""),"") | N56: =IFERROR(__xludf.DUMMYFUNCTION("""COMPUTED_VALUE"""),"")
A57: =IFERROR(__xludf.DUMMYFUNCTION("""COMPUTED_VALUE"""),"575-01920") -> 575-01920 | B57: =IFERROR(__xludf.DUMMYFUNCTION("""COMPUTED_VALUE"""),"Res. Size 11. T.R.=.45, FREQ.= 400 Hz, ACCUR. =<7") -> Res. Size 11. T.R.=.45, FREQ.= 400 Hz, ACCUR. =<7 | C57: =IFERROR(__xludf.DUMMYFUNCTION("""COMPUTED_VALUE"""),0.0) -> 0 | D57: =IFERROR(__xludf.DUMMYFUNCTION("""COMPUTED_VALUE"""),"") | E57: =IFERROR(__xludf.DUMMYFUNCTION("""COMPUTED_VALUE"""),"") | G57: =IFERROR(__xludf.DUMMYFUNCTION("""COMPUTED_VALUE"""),"") | H57: =IFERROR(__xludf.DUMMYFUNCTION("""COMPUTED_VALUE"""),"") | I57: =IFERROR(__xludf.DUMMYFUNCTION("""COMPUTED_VALUE"""),"") | J57: =IFERROR(__xludf.DUMMYFUNCTION("""COMPUTED_VALUE"""),"") | K57: =IFERROR(__xludf.DUMMYFUNCTION("""COMPUTED_VALUE"""),"") | L57: =IFERROR(__xludf.DUMMYFUNCTION("""COMPUTED_VALUE"""),"") | M57: =IFERROR(__xludf.DUMMYFUNCTION("""COMPUTED_VALUE"""),"") | N57: =IFERROR(__xludf.DUMMYFUNCTION("""COMPUTED_VALUE"""),"")
A58: =IFERROR(__xludf.DUMMYFUNCTION("""COMPUTED_VALUE"""),"575-01921-701") -> 575-01921-701 | B58: =IFERROR(__xludf.DUMMYFUNCTION("""COMPUTED_VALUE"""),"Res. Size 11 Transmitter, T.R.=0.5, Freq.=2.5 КHz, Acc =+/- 7 min. With Conn. & seal") -> Res. Size 11 Transmitter, T.R.=0.5, Freq.=2.5 КHz, Acc =+/- 7 min. With Conn. & seal | C58: =IFERROR(__xludf.DUMMYFUNCTION("""COMPUTED_VALUE"""),0.0) -> 0 | D58: =IFERROR(__xludf.DUMMYFUNCTION("""COMPUTED_VALUE"""),"") | E58: =IFERROR(__xludf.DUMMYFUNCTION("""COMPUTED_VALUE"""),"") | F58: =IFERROR(__xludf.DUMMYFUNCTION("""COMPUTED_VALUE"""),"Ф28 S303") -> Ф28 S303 | G58: =IFERROR(__xludf.DUMMYFUNCTION("""COMPUTED_VALUE"""),"") | H58: =IFERROR(__xludf.DUMMYFUNCTION("""COMPUTED_VALUE"""),"") | I58: =IFERROR(__xludf.DUMMYFUNCTION("""COMPUTED_VALUE"""),"") | J58: =IFERROR(__xludf.DUMMYFUNCTION("""COMPUTED_VALUE"""),"") | K58: =IFERROR(__xludf.DUMMYFUNCTION("""COMPUTED_VALUE"""),"") | L58: =IFERROR(__xludf.DUMMYFUNCTION("""COMPUTED_VALUE"""),"") | M58: =IFERROR(__xludf.DUMMYFUNCTION("""COMPUTED_VALUE"""),"") | N58: =IFERROR(__xludf.DUMMYFUNCTION("""COMPUTED_VALUE"""),"")
A59: =IFERROR(__xludf.DUMMYFUNCTION("""COMPUTED_VALUE"""),"575-01922") -> 575-01922 | B59: =IFERROR(__xludf.DUMMYFUNCTION("""COMPUTED_VALUE"""),"Res. Size 11 T.R.=1.75, Freq.= 400 Hz, Control Transformer, w/ 18"" leads") -> Res. Size 11 T.R.=1.75, Freq.= 400 Hz, Control Transformer, w/ 18" leads | C59: =IFERROR(__xludf.DUMMYFUNCTION("""COMPUTED_VALUE"""),0.0) -> 0 | D59: =IFERROR(__xludf.DUMMYFUNCTION("""COMPUTED_VALUE"""),"") | E59: =IFERROR(__xludf.DUMMYFUNCTION("""COMPUTED_VALUE"""),"") | G59: =IFERROR(__xludf.DUMMYFUNCTION("""COMPUTED_VALUE"""),"") | H59: =IFERROR(__xludf.DUMMYFUNCTION("""COMPUTED_VALUE"""),"") | I59: =IFERROR(__xludf.DUMMYFUNCTION("""COMPUTED_VALUE"""),"") | J59: =IFERROR(__xludf.DUMMYFUNCTION("""COMPUTED_VALUE"""),"") | K59: =IFERROR(__xludf.DUMMYFUNCTION("""COMPUTED_VALUE"""),"") | L59: =IFERROR(__xludf.DUMMYFUNCTION("""COMPUTED_VALUE"""),"") | M59: =IFERROR(__xludf.DUMMYFUNCTION("""COMPUTED_VALUE"""),"") | N59: =IFERROR(__xludf.DUMMYFUNCTION("""COMPUTED_VALUE"""),"")
A60: =IFERROR(__xludf.DUMMYFUNCTION("""COMPUTED_VALUE"""),"575-01923") -> 575-01923 | B60: =IFERROR(__xludf.DUMMYFUNCTION("""COMPUTED_VALUE"""),"Res. Size 11 T.R.=1.93, Freq.= 400 Hz, Control Transformer") -> Res. Size 11 T.R.=1.93, Freq.= 400 Hz, Control Transformer | C60: =IFERROR(__xludf.DUMMYFUNCTION("""COMPUTED_VALUE"""),0.0) -> 0 | D60: =IFERROR(__xludf.DUMMYFUNCTION("""COMPUTED_VALUE"""),"") | E60: =IFERROR(__xludf.DUMMYFUNCTION("""COMPUTED_VALUE"""),"") | G60: =IFERROR(__xludf.DUMMYFUNCTION("""COMPUTED_VALUE"""),"") | H60: =IFERROR(__xludf.DUMMYFUNCTION("""COMPUTED_VALUE"""),"") | I60: =IFERROR(__xludf.DUMMYFUNCTION("""COMPUTED_VALUE"""),"") | J60: =IFERROR(__xludf.DUMMYFUNCTION("""COMPUTED_VALUE"""),"") | K60: =IFERROR(__xludf.DUMMYFUNCTION("""COMPUTED_VALUE"""),"") | L60: =IFERROR(__xludf.DUMMYFUNCTION("""COMPUTED_VALUE"""),"") | M60: =IFERROR(__xludf.DUMMYFUNCTION("""COMPUTED_VALUE"""),"") | N60: =IFERROR(__xludf.DUMMYFUNCTION("""COMPUTED_VALUE"""),"")
A61: =IFERROR(__xludf.DUMMYFUNCTION("""COMPUTED_VALUE"""),"575-15903") -> 575-15903 | B61: =IFERROR(__xludf.DUMMYFUNCTION("""COMPUTED_VALUE"""),"Res. Size 11 Transmitter, T.R.=0.95, Freq.=2.5 КHz, Acc =< 7 ") -> Res. Size 11 Transmitter, T.R.=0.95, Freq.=2.5 КHz, Acc =< 7 | C61: =IFERROR(__xludf.DUMMYFUNCTION("""COMPUTED_VALUE"""),0.0) -> 0 | D61: =IFERROR(__xludf.DUMMYFUNCTION("""COMPUTED_VALUE"""),"") | E61: =IFERROR(__xludf.DUMMYFUNCTION("""COMPUTED_VALUE"""),"") | G61: =IFERROR(__xludf.DUMMYFUNCTION("""COMPUTED_VALUE"""),"") | H61: =IFERROR(__xludf.DUMMYFUNCTION("""COMPUTED_VALUE"""),"") | I61: =IFERROR(__xludf.DUMMYFUNCTION("""COMPUTED_VALUE"""),"") | J61: =IFERROR(__xludf.DUMMYFUNCTION("""COMPUTED_VALUE"""),"") | K61: =IFERROR(__xludf.DUMMYFUNCTION("""COMPUTED_VALUE"""),"") | L61: =IFERROR(__xludf.DUMMYFUNCTION("""COMPUTED_VALUE"""),"") | M61: =IFERROR(__xludf.DUMMYFUNCTION("""COMPUTED_VALUE"""),"") | N61: =IFERROR(__xludf.DUMMYFUNCTION("""COMPUTED_VALUE"""),"")
A62: =IFERROR(__xludf.DUMMYFUNCTION("""COMPUTED_VALUE"""),2.11387E8) -> 211387000 | B62: =IFERROR(__xludf.DUMMYFUNCTION("""COMPUTED_VALUE"""),"TURCK 10 mm MULTITURN SHAFT") -> TURCK 10 mm MULTITURN SHAFT | C62: =IFERROR(__xludf.DUMMYFUNCTION("""COMPUTED_VALUE"""),0.0) -> 0 | D62: =IFERROR(__xludf.DUMMYFUNCTION("""COMPUTED_VALUE"""),"") | E62: =IFERROR(__xludf.DUMMYFUNCTION("""COMPUTED_VALUE"""),"") | F62: =IFERROR(__xludf.DUMMYFUNCTION("""COMPUTED_VALUE"""),"") | G62: =IFERROR(__xludf.DUMMYFUNCTION("""COMPUTED_VALUE"""),"") | H62: =IFERROR(__xludf.DUMMYFUNCTION("""COMPUTED_VALUE"""),"") | I62: =IFERROR(__xludf.DUMMYFUNCTION("""COMPUTED_VALUE"""),"") | J62: =IFERROR(__xludf.DUMMYFUNCTION("""COMPUTED_VALUE"""),"") | K62: =IFERROR(__xludf.DUMMYFUNCTION("""COMPUTED_VALUE"""),"") | ... N62: =IFERROR(__xludf.DUMMYFUNCTION("""COMPUTED_VALUE"""),"")
A63: =IFERROR(__xludf.DUMMYFUNCTION("""COMPUTED_VALUE"""),"21108801A") -> 21108801A | B63: =IFERROR(__xludf.DUMMYFUNCTION("""COMPUTED_VALUE"""),"Shaft DC-425.375 Dia .250End") -> Shaft DC-425.375 Dia .250End | C63: =IFERROR(__xludf.DUMMYFUNCTION("""COMPUTED_VALUE"""),0.0) -> 0 | D63: =IFERROR(__xludf.DUMMYFUNCTION("""COMPUTED_VALUE"""),"") | E63: =IFERROR(__xludf.DUMMYFUNCTION("""COMPUTED_VALUE"""),"") | F63: =IFERROR(__xludf.DUMMYFUNCTION("""COMPUTED_VALUE"""),"") | G63: =IFERROR(__xludf.DUMMYFUNCTION("""COMPUTED_VALUE"""),"") | H63: =IFERROR(__xludf.DUMMYFUNCTION("""COMPUTED_VALUE"""),"") | I63: =IFERROR(__xludf.DUMMYFUNCTION("""COMPUTED_VALUE"""),"") | J63: =IFERROR(__xludf.DUMMYFUNCTION("""COMPUTED_VALUE"""),"") | K63: =IFERROR(__xludf.DUMMYFUNCTION("""COMPUTED_VALUE"""),"") | ... N63: =IFERROR(__xludf.DUMMYFUNCTION("""COMPUTED_VALUE"""),"")
A64: =IFERROR(__xludf.DUMMYFUNCTION("""COMPUTED_VALUE"""),"21114201B") -> 21114201B | B64: =IFERROR(__xludf.DUMMYFUNCTION("""COMPUTED_VALUE"""),"5/8"" Shaft w/o Keyway with Front slot Across Shaft for DC425") -> 5/8" Shaft w/o Keyway with Front slot Across Shaft for DC425 | C64: =IFERROR(__xludf.DUMMYFUNCTION("""COMPUTED_VALUE"""),0.0) -> 0 | D64: =IFERROR(__xludf.DUMMYFUNCTION("""COMPUTED_VALUE"""),"") | E64: =IFERROR(__xludf.DUMMYFUNCTION("""COMPUTED_VALUE"""),"") | F64: =IFERROR(__xludf.DUMMYFUNCTION("""COMPUTED_VALUE"""),"") | G64: =IFERROR(__xludf.DUMMYFUNCTION("""COMPUTED_VALUE"""),"") | H64: =IFERROR(__xludf.DUMMYFUNCTION("""COMPUTED_VALUE"""),"") | I64: =IFERROR(__xludf.DUMMYFUNCTION("""COMPUTED_VALUE"""),"") | J64: =IFERROR(__xludf.DUMMYFUNCTION("""COMPUTED_VALUE"""),"") | K64: =IFERROR(__xludf.DUMMYFUNCTION("""COMPUTED_VALUE"""),"") | ... N64: =IFERROR(__xludf.DUMMYFUNCTION("""COMPUTED_VALUE"""),"")
A65: =IFERROR(__xludf.DUMMYFUNCTION("""COMPUTED_VALUE"""),"22146700A") -> 22146700A | B65: =IFERROR(__xludf.DUMMYFUNCTION("""COMPUTED_VALUE"""),"DC60 Rear Cover with PG9 hole and LED pipe for Analog DC60") -> DC60 Rear Cover with PG9 hole and LED pipe for Analog DC60 | C65: =IFERROR(__xludf.DUMMYFUNCTION("""COMPUTED_VALUE"""),0.80352) -> 0.80352 | D65: =IFERROR(__xludf.DUMMYFUNCTION("""COMPUTED_VALUE"""),0.80352) -> 0.80352 | E65: =IFERROR(__xludf.DUMMYFUNCTION("""COMPUTED_VALUE"""),1.0) -> 1 | F65: =IFERROR(__xludf.DUMMYFUNCTION("""COMPUTED_VALUE"""),"") | G65: =IFERROR(__xludf.DUMMYFUNCTION("""COMPUTED_VALUE"""),"") | H65: =IFERROR(__xludf.DUMMYFUNCTION("""COMPUTED_VALUE"""),"") | I65: =IFERROR(__xludf.DUMMYFUNCTION("""COMPUTED_VALUE"""),"") | J65: =IFERROR(__xludf.DUMMYFUNCTION("""COMPUTED_VALUE"""),"") | K65: =IFERROR(__xludf.DUMMYFUNCTION("""COMPUTED_VALUE"""),"") | L65: =IFERROR(__xludf.DUMMYFUNCTION("""COMPUTED_VALUE"""),"Ф62 AL 2017 Italy") -> Ф62 AL 2017 Italy | M65: =IFERROR(__xludf.DUMMYFUNCTION("""COMPUTED_VALUE"""),0.062) -> 0.062 | N65: =IFERROR(__xludf.DUMMYFUNCTION("""COMPUTED_VALUE"""),0.80352) -> 0.80352
A66: =IFERROR(__xludf.DUMMYFUNCTION("""COMPUTED_VALUE"""),"21130000B") -> 21130000B | B66: =IFERROR(__xludf.DUMMYFUNCTION("""COMPUTED_VALUE"""),"Aluminium flange for size 25 Hub Shaft units for 26mm nitrile seal") -> Aluminium flange for size 25 Hub Shaft units for 26mm nitrile seal | C66: =IFERROR(__xludf.DUMMYFUNCTION("""COMPUTED_VALUE"""),0.0) -> 0 | D66: =IFERROR(__xludf.DUMMYFUNCTION("""COMPUTED_VALUE"""),"") | E66: =IFERROR(__xludf.DUMMYFUNCTION("""COMPUTED_VALUE"""),"") | F66: =IFERROR(__xludf.DUMMYFUNCTION("""COMPUTED_VALUE"""),"") | G66: =IFERROR(__xludf.DUMMYFUNCTION("""COMPUTED_VALUE"""),"") | H66: =IFERROR(__xludf.DUMMYFUNCTION("""COMPUTED_VALUE"""),"") | I66: =IFERROR(__xludf.DUMMYFUNCTION("""COMPUTED_VALUE"""),"Ф65 AL 2017 Italy") -> Ф65 AL 2017 Italy | J66: =IFERROR(__xludf.DUMMYFUNCTION("""COMPUTED_VALUE"""),0.0) -> 0 | K66: =IFERROR(__xludf.DUMMYFUNCTION("""COMPUTED_VALUE"""),0.0) -> 0 | L66: =IFERROR(__xludf.DUMMYFUNCTION("""COMPUTED_VALUE"""),"") | M66: =IFERROR(__xludf.DUMMYFUNCTION("""COMPUTED_VALUE"""),"") | N66: =IFERROR(__xludf.DUMMYFUNCTION("""COMPUTED_VALUE"""),"")
A67: =IFERROR(__xludf.DUMMYFUNCTION("""COMPUTED_VALUE"""),"21134200C") -> 21134200C | B67: =IFERROR(__xludf.DUMMYFUNCTION("""COMPUTED_VALUE"""),"NR25 Ethernet Multiturn end conn. Rear cover") -> NR25 Ethernet Multiturn end conn. Rear cover | C67: =IFERROR(__xludf.DUMMYFUNCTION("""COMPUTED_VALUE"""),1.1016000000000001) -> 1.1016 | D67: =IFERROR(__xludf.DUMMYFUNCTION("""COMPUTED_VALUE"""),1.1016000000000001) -> 1.1016 | E67: =IFERROR(__xludf.DUMMYFUNCTION("""COMPUTED_VALUE"""),1.0) -> 1 | F67: =IFERROR(__xludf.DUMMYFUNCTION("""COMPUTED_VALUE"""),"") | G67: =IFERROR(__xludf.DUMMYFUNCTION("""COMPUTED_VALUE"""),"") | H67: =IFERROR(__xludf.DUMMYFUNCTION("""COMPUTED_VALUE"""),"") | I67: =IFERROR(__xludf.DUMMYFUNCTION("""COMPUTED_VALUE"""),"") | J67: =IFERROR(__xludf.DUMMYFUNCTION("""COMPUTED_VALUE"""),"") | K67: =IFERROR(__xludf.DUMMYFUNCTION("""COMPUTED_VALUE"""),"") | L67: =IFERROR(__xludf.DUMMYFUNCTION("""COMPUTED_VALUE"""),"Ф65 AL 2017 Italy") -> Ф65 AL 2017 Italy | M67: =IFERROR(__xludf.DUMMYFUNCTION("""COMPUTED_VALUE"""),0.085) -> 0.085 | N67: =IFERROR(__xludf.DUMMYFUNCTION("""COMPUTED_VALUE"""),1.1016000000000001) -> 1.1016
A68: =IFERROR(__xludf.DUMMYFUNCTION("""COMPUTED_VALUE"""),"RM-5") -> RM-5 | B68: =IFERROR(__xludf.DUMMYFUNCTION("""COMPUTED_VALUE"""),"Reference Module Harowe #11BRCX-300-C10 For 0.45 TR resolver") -> Reference Module Harowe #11BRCX-300-C10 For 0.45 TR resolver | C68: =IFERROR(__xludf.DUMMYFUNCTION("""COMPUTED_VALUE"""),0.0) -> 0 | D68: =IFERROR(__xludf.DUMMYFUNCTION("""COMPUTED_VALUE"""),"") | E68: =IFERROR(__xludf.DUMMYFUNCTION("""COMPUTED_VALUE"""),"") | F68: =IFERROR(__xludf.DUMMYFUNCTION("""COMPUTED_VALUE"""),"") | G68: =IFERROR(__xludf.DUMMYFUNCTION("""COMPUTED_VALUE"""),"") | H68: =IFERROR(__xludf.DUMMYFUNCTION("""COMPUTED_VALUE"""),"") | I68: =IFERROR(__xludf.DUMMYFUNCTION("""COMPUTED_VALUE"""),"") | J68: =IFERROR(__xludf.DUMMYFUNCTION("""COMPUTED_VALUE"""),"") | K68: =IFERROR(__xludf.DUMMYFUNCTION("""COMPUTED_VALUE"""),"") | ... N68: =IFERROR(__xludf.DUMMYFUNCTION("""COMPUTED_VALUE"""),"")
A69: =IFERROR(__xludf.DUMMYFUNCTION("""COMPUTED_VALUE"""),2.11174E8) -> 211174000 | B69: =IFERROR(__xludf.DUMMYFUNCTION("""COMPUTED_VALUE"""),"Modified Size 11 resolver Made from 575-01902-1 machined flat on the body") -> Modified Size 11 resolver Made from 575-01902-1 machined flat on the body | C69: =IFERROR(__xludf.DUMMYFUNCTION("""COMPUTED_VALUE"""),0.0) -> 0 | D69: =IFERROR(__xludf.DUMMYFUNCTION("""COMPUTED_VALUE"""),"") | E69: =IFERROR(__xludf.DUMMYFUNCTION("""COMPUTED_VALUE"""),"") | G69: =IFERROR(__xludf.DUMMYFUNCTION("""COMPUTED_VALUE"""),"") | H69: =IFERROR(__xludf.DUMMYFUNCTION("""COMPUTED_VALUE"""),"") | I69: =IFERROR(__xludf.DUMMYFUNCTION("""COMPUTED_VALUE"""),"") | J69: =IFERROR(__xludf.DUMMYFUNCTION("""COMPUTED_VALUE"""),"") | K69: =IFERROR(__xludf.DUMMYFUNCTION("""COMPUTED_VALUE"""),"") | L69: =IFERROR(__xludf.DUMMYFUNCTION("""COMPUTED_VALUE"""),"") | M69: =IFERROR(__xludf.DUMMYFUNCTION("""COMPUTED_VALUE"""),"") | N69: =IFERROR(__xludf.DUMMYFUNCTION("""COMPUTED_VALUE"""),"")
A70: =IFERROR(__xludf.DUMMYFUNCTION("""COMPUTED_VALUE"""),"21111202E") -> 21111202E | B70: =IFERROR(__xludf.DUMMYFUNCTION("""COMPUTED_VALUE"""),"DC-25 Rear Cover Size 18") -> DC-25 Rear Cover Size 18 | C70: =IFERROR(__xludf.DUMMYFUNCTION("""COMPUTED_VALUE"""),0.6220800000000001) -> 0.62208 | D70: =IFERROR(__xludf.DUMMYFUNCTION("""COMPUTED_VALUE"""),0.6220800000000001) -> 0.62208 | E70: =IFERROR(__xludf.DUMMYFUNCTION("""COMPUTED_VALUE"""),1.0) -> 1 | F70: =IFERROR(__xludf.DUMMYFUNCTION("""COMPUTED_VALUE"""),"") | G70: =IFERROR(__xludf.DUMMYFUNCTION("""COMPUTED_VALUE"""),"") | H70: =IFERROR(__xludf.DUMMYFUNCTION("""COMPUTED_VALUE"""),"") | I70: =IFERROR(__xludf.DUMMYFUNCTION("""COMPUTED_VALUE"""),"") | J70: =IFERROR(__xludf.DUMMYFUNCTION("""COMPUTED_VALUE"""),"") | K70: =IFERROR(__xludf.DUMMYFUNCTION("""COMPUTED_VALUE"""),"") | L70: =IFERROR(__xludf.DUMMYFUNCTION("""COMPUTED_VALUE"""),"Ф65 AL 2017 Italy") -> Ф65 AL 2017 Italy | M70: =IFERROR(__xludf.DUMMYFUNCTION("""COMPUTED_VALUE"""),0.048) -> 0.048 | N70: =IFERROR(__xludf.DUMMYFUNCTION("""COMPUTED_VALUE"""),0.6220800000000001) -> 0.62208
A71: =IFERROR(__xludf.DUMMYFUNCTION("""COMPUTED_VALUE"""),"22124400K") -> 22124400K | B71: =IFERROR(__xludf.DUMMYFUNCTION("""COMPUTED_VALUE"""),"H25/DC25 Servo Nose in 6061 AL new stile") -> H25/DC25 Servo Nose in 6061 AL new stile | C71: =IFERROR(__xludf.DUMMYFUNCTION("""COMPUTED_VALUE"""),0.68688) -> 0.68688 | D71: =IFERROR(__xludf.DUMMYFUNCTION("""COMPUTED_VALUE"""),0.68688) -> 0.68688 | E71: =IFERROR(__xludf.DUMMYFUNCTION("""COMPUTED_VALUE"""),1.0) -> 1 | F71: =IFERROR(__xludf.DUMMYFUNCTION("""COMPUTED_VALUE"""),"") | G71: =IFERROR(__xludf.DUMMYFUNCTION("""COMPUTED_VALUE"""),"") | H71: =IFERROR(__xludf.DUMMYFUNCTION("""COMPUTED_VALUE"""),"") | I71: =IFERROR(__xludf.DUMMYFUNCTION("""COMPUTED_VALUE"""),"Ф65 AL 2017 Italy") -> Ф65 AL 2017 Italy | J71: =IFERROR(__xludf.DUMMYFUNCTION("""COMPUTED_VALUE"""),0.053) -> 0.053 | K71: =IFERROR(__xludf.DUMMYFUNCTION("""COMPUTED_VALUE"""),0.68688) -> 0.68688 | L71: =IFERROR(__xludf.DUMMYFUNCTION("""COMPUTED_VALUE"""),"") | M71: =IFERROR(__xludf.DUMMYFUNCTION("""COMPUTED_VALUE"""),"") | N71: =IFERROR(__xludf.DUMMYFUNCTION("""COMPUTED_VALUE"""),"")
A72: =IFERROR(__xludf.DUMMYFUNCTION("""COMPUTED_VALUE"""),"22903700B") -> 22903700B | B72: =IFERROR(__xludf.DUMMYFUNCTION("""COMPUTED_VALUE"""),"AC Steppers Transformer Uses heavy wire 630-02228 for SD17060x, SD3045x") -> AC Steppers Transformer Uses heavy wire 630-02228 for SD17060x, SD3045x | C72: =IFERROR(__xludf.DUMMYFUNCTION("""COMPUTED_VALUE"""),0.0) -> 0 | D72: =IFERROR(__xludf.DUMMYFUNCTION("""COMPUTED_VALUE"""),"") | E72: =IFERROR(__xludf.DUMMYFUNCTION("""COMPUTED_VALUE"""),"") | F72: =IFERROR(__xludf.DUMMYFUNCTION("""COMPUTED_VALUE"""),"") | G72: =IFERROR(__xludf.DUMMYFUNCTION("""COMPUTED_VALUE"""),"") | H72: =IFERROR(__xludf.DUMMYFUNCTION("""COMPUTED_VALUE"""),"") | I72: =IFERROR(__xludf.DUMMYFUNCTION("""COMPUTED_VALUE"""),"") | J72: =IFERROR(__xludf.DUMMYFUNCTION("""COMPUTED_VALUE"""),"") | K72: =IFERROR(__xludf.DUMMYFUNCTION("""COMPUTED_VALUE"""),"") | ... N72: =IFERROR(__xludf.DUMMYFUNCTION("""COMPUTED_VALUE"""),"")
A73: =IFERROR(__xludf.DUMMYFUNCTION("""COMPUTED_VALUE"""),2.11389E8) -> 211389000 | C73: =IFERROR(__xludf.DUMMYFUNCTION("""COMPUTED_VALUE"""),0.0) -> 0 | D73: =IFERROR(__xludf.DUMMYFUNCTION("""COMPUTED_VALUE"""),"") | E73: =IFERROR(__xludf.DUMMYFUNCTION("""COMPUTED_VALUE"""),"") | F73: =IFERROR(__xludf.DUMMYFUNCTION("""COMPUTED_VALUE"""),"") | G73: =IFERROR(__xludf.DUMMYFUNCTION("""COMPUTED_VALUE"""),"") | H73: =IFERROR(__xludf.DUMMYFUNCTION("""COMPUTED_VALUE"""),"") | I73: =IFERROR(__xludf.DUMMYFUNCTION("""COMPUTED_VALUE"""),"") | J73: =IFERROR(__xludf.DUMMYFUNCTION("""COMPUTED_VALUE"""),"") | K73: =IFERROR(__xludf.DUMMYFUNCTION("""COMPUTED_VALUE"""),"") | ... N73: =IFERROR(__xludf.DUMMYFUNCTION("""COMPUTED_VALUE"""),"")
A74: =IFERROR(__xludf.DUMMYFUNCTION("""COMPUTED_VALUE"""),2.21397E8) -> 221397000 | B74: =IFERROR(__xludf.DUMMYFUNCTION("""COMPUTED_VALUE"""),"DC25 & H25 Flange for 5/8"" shaft 6061-T6 AL") -> DC25 & H25 Flange for 5/8" shaft 6061-T6 AL | C74: =IFERROR(__xludf.DUMMYFUNCTION("""COMPUTED_VALUE"""),0.3315) -> 0.3315 | D74: =IFERROR(__xludf.DUMMYFUNCTION("""COMPUTED_VALUE"""),0.3315) -> 0.3315 | E74: =IFERROR(__xludf.DUMMYFUNCTION("""COMPUTED_VALUE"""),1.0) -> 1 | F74: =IFERROR(__xludf.DUMMYFUNCTION("""COMPUTED_VALUE"""),"") | G74: =IFERROR(__xludf.DUMMYFUNCTION("""COMPUTED_VALUE"""),"") | H74: =IFERROR(__xludf.DUMMYFUNCTION("""COMPUTED_VALUE"""),"") | I74: =IFERROR(__xludf.DUMMYFUNCTION("""COMPUTED_VALUE"""),"AL USA") -> AL USA | J74: =IFERROR(__xludf.DUMMYFUNCTION("""COMPUTED_VALUE"""),0.195) -> 0.195 | K74: =IFERROR(__xludf.DUMMYFUNCTION("""COMPUTED_VALUE"""),0.3315) -> 0.3315 | L74: =IFERROR(__xludf.DUMMYFUNCTION("""COMPUTED_VALUE"""),"") | M74: =IFERROR(__xludf.DUMMYFUNCTION("""COMPUTED_VALUE"""),"") | N74: =IFERROR(__xludf.DUMMYFUNCTION("""COMPUTED_VALUE"""),"")
A75: =IFERROR(__xludf.DUMMYFUNCTION("""COMPUTED_VALUE"""),"21110702D") -> 21110702D | B75: =IFERROR(__xludf.DUMMYFUNCTION("""COMPUTED_VALUE"""),"5/8"" S.S. shaft, w .250 end with keyway") -> 5/8" S.S. shaft, w .250 end with keyway | C75: =IFERROR(__xludf.DUMMYFUNCTION("""COMPUTED_VALUE"""),0.0) -> 0 | D75: =IFERROR(__xludf.DUMMYFUNCTION("""COMPUTED_VALUE"""),"") | E75: =IFERROR(__xludf.DUMMYFUNCTION("""COMPUTED_VALUE"""),"") | F75: =IFERROR(__xludf.DUMMYFUNCTION("""COMPUTED_VALUE"""),"") | G75: =IFERROR(__xludf.DUMMYFUNCTION("""COMPUTED_VALUE"""),"") | H75: =IFERROR(__xludf.DUMMYFUNCTION("""COMPUTED_VALUE"""),"") | I75: =IFERROR(__xludf.DUMMYFUNCTION("""COMPUTED_VALUE"""),"") | J75: =IFERROR(__xludf.DUMMYFUNCTION("""COMPUTED_VALUE"""),"") | K75: =IFERROR(__xludf.DUMMYFUNCTION("""COMPUTED_VALUE"""),"") | ... N75: =IFERROR(__xludf.DUMMYFUNCTION("""COMPUTED_VALUE"""),"")
A76: =IFERROR(__xludf.DUMMYFUNCTION("""COMPUTED_VALUE"""),"21129501B") -> 21129501B | B76: =IFERROR(__xludf.DUMMYFUNCTION("""COMPUTED_VALUE"""),"5/8"" Rotor Singleturn DC 25 Made from 200-91229 in BG Material SS-316") -> 5/8" Rotor Singleturn DC 25 Made from 200-91229 in BG Material SS-316 | C76: =IFERROR(__xludf.DUMMYFUNCTION("""COMPUTED_VALUE"""),0.0) -> 0 | D76: =IFERROR(__xludf.DUMMYFUNCTION("""COMPUTED_VALUE"""),"") | E76: =IFERROR(__xludf.DUMMYFUNCTION("""COMPUTED_VALUE"""),"") | F76: =IFERROR(__xludf.DUMMYFUNCTION("""COMPUTED_VALUE"""),"") | G76: =IFERROR(__xludf.DUMMYFUNCTION("""COMPUTED_VALUE"""),"") | H76: =IFERROR(__xludf.DUMMYFUNCTION("""COMPUTED_VALUE"""),"") | I76: =IFERROR(__xludf.DUMMYFUNCTION("""COMPUTED_VALUE"""),"") | J76: =IFERROR(__xludf.DUMMYFUNCTION("""COMPUTED_VALUE"""),"") | K76: =IFERROR(__xludf.DUMMYFUNCTION("""COMPUTED_VALUE"""),"") | ... N76: =IFERROR(__xludf.DUMMYFUNCTION("""COMPUTED_VALUE"""),"")
A77: =IFERROR(__xludf.DUMMYFUNCTION("""COMPUTED_VALUE"""),2.11137E8) -> 211137000 | B77: =IFERROR(__xludf.DUMMYFUNCTION("""COMPUTED_VALUE"""),"Transformer DC25 5 pin") -> Transformer DC25 5 pin | C77: =IFERROR(__xludf.DUMMYFUNCTION("""COMPUTED_VALUE"""),0.0) -> 0 | D77: =IFERROR(__xludf.DUMMYFUNCTION("""COMPUTED_VALUE"""),"") | E77: =IFERROR(__xludf.DUMMYFUNCTION("""COMPUTED_VALUE"""),"") | F77: =IFERROR(__xludf.DUMMYFUNCTION("""COMPUTED_VALUE"""),"") | G77: =IFERROR(__xludf.DUMMYFUNCTION("""COMPUTED_VALUE"""),"") | H77: =IFERROR(__xludf.DUMMYFUNCTION("""COMPUTED_VALUE"""),"") | I77: =IFERROR(__xludf.DUMMYFUNCTION("""COMPUTED_VALUE"""),"") | J77: =IFERROR(__xludf.DUMMYFUNCTION("""COMPUTED_VALUE"""),"") | K77: =IFERROR(__xludf.DUMMYFUNCTION("""COMPUTED_VALUE"""),"") | ... N77: =IFERROR(__xludf.DUMMYFUNCTION("""COMPUTED_VALUE"""),"")
A78: =IFERROR(__xludf.DUMMYFUNCTION("""COMPUTED_VALUE"""),"551-90002") -> 551-90002 | B78: =IFERROR(__xludf.DUMMYFUNCTION("""COMPUTED_VALUE"""),"Transformer Output 36150 Reference") -> Transformer Output 36150 Reference | C78: =IFERROR(__xludf.DUMMYFUNCTION("""COMPUTED_VALUE"""),0.0) -> 0 | D78: =IFERROR(__xludf.DUMMYFUNCTION("""COMPUTED_VALUE"""),"") | E78: =IFERROR(__xludf.DUMMYFUNCTION("""COMPUTED_VALUE"""),"") | F78: =IFERROR(__xludf.DUMMYFUNCTION("""COMPUTED_VALUE"""),"") | G78: =IFERROR(__xludf.DUMMYFUNCTION("""COMPUTED_VALUE"""),"") | H78: =IFERROR(__xludf.DUMMYFUNCTION("""COMPUTED_VALUE"""),"") | I78: =IFERROR(__xludf.DUMMYFUNCTION("""COMPUTED_VALUE"""),"") | J78: =IFERROR(__xludf.DUMMYFUNCTION("""COMPUTED_VALUE"""),"") | K78: =IFERROR(__xludf.DUMMYFUNCTION("""COMPUTED_VALUE"""),"") | ... N78: =IFERROR(__xludf.DUMMYFUNCTION("""COMPUTED_VALUE"""),"")
A79: =IFERROR(__xludf.DUMMYFUNCTION("""COMPUTED_VALUE"""),2.1129402E8) -> 211294020 | B79: =IFERROR(__xludf.DUMMYFUNCTION("""COMPUTED_VALUE"""),"IP67 R11 Rear Cover Length=17mm Hole Dia=18mm") -> IP67 R11 Rear Cover Length=17mm Hole Dia=18mm | C79: =IFERROR(__xludf.DUMMYFUNCTION("""COMPUTED_VALUE"""),0.0) -> 0 | D79: =IFERROR(__xludf.DUMMYFUNCTION("""COMPUTED_VALUE"""),"") | E79: =IFERROR(__xludf.DUMMYFUNCTION("""COMPUTED_VALUE"""),"") | F79: =IFERROR(__xludf.DUMMYFUNCTION("""COMPUTED_VALUE"""),"") | G79: =IFERROR(__xludf.DUMMYFUNCTION("""COMPUTED_VALUE"""),"") | H79: =IFERROR(__xludf.DUMMYFUNCTION("""COMPUTED_VALUE"""),"") | I79: =IFERROR(__xludf.DUMMYFUNCTION("""COMPUTED_VALUE"""),"") | J79: =IFERROR(__xludf.DUMMYFUNCTION("""COMPUTED_VALUE"""),"") | K79: =IFERROR(__xludf.DUMMYFUNCTION("""COMPUTED_VALUE"""),"") | L79: =IFERROR(__xludf.DUMMYFUNCTION("""COMPUTED_VALUE"""),"Ф28 S303") -> Ф28 S303 | M79: =IFERROR(__xludf.DUMMYFUNCTION("""COMPUTED_VALUE"""),0.0) -> 0 | N79: =IFERROR(__xludf.DUMMYFUNCTION("""COMPUTED_VALUE"""),"")
A80: =IFERROR(__xludf.DUMMYFUNCTION("""COMPUTED_VALUE"""),"21129405А") -> 21129405А | B80: =IFERROR(__xludf.DUMMYFUNCTION("""COMPUTED_VALUE"""),"IP67 R11 Rear Cover Length=12mm Hole Dia=15,3mm for R11X-F10B/7S3-52") -> IP67 R11 Rear Cover Length=12mm Hole Dia=15,3mm for R11X-F10B/7S3-52 | C80: =IFERROR(__xludf.DUMMYFUNCTION("""COMPUTED_VALUE"""),0.0) -> 0 | D80: =IFERROR(__xludf.DUMMYFUNCTION("""COMPUTED_VALUE"""),"") | E80: =IFERROR(__xludf.DUMMYFUNCTION("""COMPUTED_VALUE"""),"") | F80: =IFERROR(__xludf.DUMMYFUNCTION("""COMPUTED_VALUE"""),"") | G80: =IFERROR(__xludf.DUMMYFUNCTION("""COMPUTED_VALUE"""),"") | H80: =IFERROR(__xludf.DUMMYFUNCTION("""COMPUTED_VALUE"""),"") | I80: =IFERROR(__xludf.DUMMYFUNCTION("""COMPUTED_VALUE"""),"") | J80: =IFERROR(__xludf.DUMMYFUNCTION("""COMPUTED_VALUE"""),"") | K80: =IFERROR(__xludf.DUMMYFUNCTION("""COMPUTED_VALUE"""),"") | L80: =IFERROR(__xludf.DUMMYFUNCTION("""COMPUTED_VALUE"""),"Ф28 S303") -> Ф28 S303 | M80: =IFERROR(__xludf.DUMMYFUNCTION("""COMPUTED_VALUE"""),0.0) -> 0 | N80: =IFERROR(__xludf.DUMMYFUNCTION("""COMPUTED_VALUE"""),"")
A81: =IFERROR(__xludf.DUMMYFUNCTION("""COMPUTED_VALUE"""),2.11366E8) -> 211366000 | B81: =IFERROR(__xludf.DUMMYFUNCTION("""COMPUTED_VALUE"""),"NR25 Profibus Multiturn rear cover 3 end con., AL") -> NR25 Profibus Multiturn rear cover 3 end con., AL | C81: =IFERROR(__xludf.DUMMYFUNCTION("""COMPUTED_VALUE"""),0.95904) -> 0.95904 | D81: =IFERROR(__xludf.DUMMYFUNCTION("""COMPUTED_VALUE"""),0.95904) -> 0.95904 | E81: =IFERROR(__xludf.DUMMYFUNCTION("""COMPUTED_VALUE"""),1.0) -> 1 | F81: =IFERROR(__xludf.DUMMYFUNCTION("""COMPUTED_VALUE"""),"") | G81: =IFERROR(__xludf.DUMMYFUNCTION("""COMPUTED_VALUE"""),"") | H81: =IFERROR(__xludf.DUMMYFUNCTION("""COMPUTED_VALUE"""),"") | I81: =IFERROR(__xludf.DUMMYFUNCTION("""COMPUTED_VALUE"""),"") | J81: =IFERROR(__xludf.DUMMYFUNCTION("""COMPUTED_VALUE"""),"") | K81: =IFERROR(__xludf.DUMMYFUNCTION("""COMPUTED_VALUE"""),"") | L81: =IFERROR(__xludf.DUMMYFUNCTION("""COMPUTED_VALUE"""),"Ф65 AL 2017 Italy") -> Ф65 AL 2017 Italy | M81: =IFERROR(__xludf.DUMMYFUNCTION("""COMPUTED_VALUE"""),0.074) -> 0.074 | N81: =IFERROR(__xludf.DUMMYFUNCTION("""COMPUTED_VALUE"""),0.95904) -> 0.95904
A82: =IFERROR(__xludf.DUMMYFUNCTION("""COMPUTED_VALUE"""),"21137200A") -> 21137200A | B82: =IFERROR(__xludf.DUMMYFUNCTION("""COMPUTED_VALUE"""),"NR25 Profibus Multiturn rear cover singleturn end con.") -> NR25 Profibus Multiturn rear cover singleturn end con. | C82: =IFERROR(__xludf.DUMMYFUNCTION("""COMPUTED_VALUE"""),0.69984) -> 0.69984 | D82: =IFERROR(__xludf.DUMMYFUNCTION("""COMPUTED_VALUE"""),0.69984) -> 0.69984 | E82: =IFERROR(__xludf.DUMMYFUNCTION("""COMPUTED_VALUE"""),1.0) -> 1 | F82: =IFERROR(__xludf.DUMMYFUNCTION("""COMPUTED_VALUE"""),"") | G82: =IFERROR(__xludf.DUMMYFUNCTION("""COMPUTED_VALUE"""),"") | H82: =IFERROR(__xludf.DUMMYFUNCTION("""COMPUTED_VALUE"""),"") | I82: =IFERROR(__xludf.DUMMYFUNCTION("""COMPUTED_VALUE"""),"") | J82: =IFERROR(__xludf.DUMMYFUNCTION("""COMPUTED_VALUE"""),"") | K82: =IFERROR(__xludf.DUMMYFUNCTION("""COMPUTED_VALUE"""),"") | L82: =IFERROR(__xludf.DUMMYFUNCTION("""COMPUTED_VALUE"""),"Ф65 AL 2017 Italy") -> Ф65 AL 2017 Italy | M82: =IFERROR(__xludf.DUMMYFUNCTION("""COMPUTED_VALUE"""),0.054) -> 0.054 | N82: =IFERROR(__xludf.DUMMYFUNCTION("""COMPUTED_VALUE"""),0.69984) -> 0.69984
A83: =IFERROR(__xludf.DUMMYFUNCTION("""COMPUTED_VALUE"""),2.21466E8) -> 221466000 | B83: =IFERROR(__xludf.DUMMYFUNCTION("""COMPUTED_VALUE"""),"Metric servo nose for size 25 units; B.C.=48mm mounting holes") -> Metric servo nose for size 25 units; B.C.=48mm mounting holes | C83: =IFERROR(__xludf.DUMMYFUNCTION("""COMPUTED_VALUE"""),0.68688) -> 0.68688 | D83: =IFERROR(__xludf.DUMMYFUNCTION("""COMPUTED_VALUE"""),0.68688) -> 0.68688 | E83: =IFERROR(__xludf.DUMMYFUNCTION("""COMPUTED_VALUE"""),1.0) -> 1 | F83: =IFERROR(__xludf.DUMMYFUNCTION("""COMPUTED_VALUE"""),"") | G83: =IFERROR(__xludf.DUMMYFUNCTION("""COMPUTED_VALUE"""),"") | H83: =IFERROR(__xludf.DUMMYFUNCTION("""COMPUTED_VALUE"""),"") | I83: =IFERROR(__xludf.DUMMYFUNCTION("""COMPUTED_VALUE"""),"Ф65 AL 2017 Italy") -> Ф65 AL 2017 Italy | J83: =IFERROR(__xludf.DUMMYFUNCTION("""COMPUTED_VALUE"""),0.053) -> 0.053 | K83: =IFERROR(__xludf.DUMMYFUNCTION("""COMPUTED_VALUE"""),0.68688) -> 0.68688 | L83: =IFERROR(__xludf.DUMMYFUNCTION("""COMPUTED_VALUE"""),"") | M83: =IFERROR(__xludf.DUMMYFUNCTION("""COMPUTED_VALUE"""),"") | N83: =IFERROR(__xludf.DUMMYFUNCTION("""COMPUTED_VALUE"""),"")
A84: =IFERROR(__xludf.DUMMYFUNCTION("""COMPUTED_VALUE"""),"2216701A") -> 2216701A | B84: =IFERROR(__xludf.DUMMYFUNCTION("""COMPUTED_VALUE"""),"DC60 Rear cover w/o conn. Hole; LED pipe for Analog DC60") -> DC60 Rear cover w/o conn. Hole; LED pipe for Analog DC60 | C84: =IFERROR(__xludf.DUMMYFUNCTION("""COMPUTED_VALUE"""),0.0) -> 0 | D84: =IFERROR(__xludf.DUMMYFUNCTION("""COMPUTED_VALUE"""),"") | E84: =IFERROR(__xludf.DUMMYFUNCTION("""COMPUTED_VALUE"""),"") | F84: =IFERROR(__xludf.DUMMYFUNCTION("""COMPUTED_VALUE"""),"") | G84: =IFERROR(__xludf.DUMMYFUNCTION("""COMPUTED_VALUE"""),"") | H84: =IFERROR(__xludf.DUMMYFUNCTION("""COMPUTED_VALUE"""),"") | I84: =IFERROR(__xludf.DUMMYFUNCTION("""COMPUTED_VALUE"""),"") | J84: =IFERROR(__xludf.DUMMYFUNCTION("""COMPUTED_VALUE"""),"") | K84: =IFERROR(__xludf.DUMMYFUNCTION("""COMPUTED_VALUE"""),"") | M84: =IFERROR(__xludf.DUMMYFUNCTION("""COMPUTED_VALUE"""),0.0) -> 0 | N84: =IFERROR(__xludf.DUMMYFUNCTION("""COMPUTED_VALUE"""),"")
A85: =IFERROR(__xludf.DUMMYFUNCTION("""COMPUTED_VALUE"""),"21129500A") -> 21129500A | B85: =IFERROR(__xludf.DUMMYFUNCTION("""COMPUTED_VALUE"""),"5/8"" Rotor Assembly SS-303 used in DC25,H25, HT-20C singleturn,1-speed, J-type") -> 5/8" Rotor Assembly SS-303 used in DC25,H25, HT-20C singleturn,1-speed, J-type | C85: =IFERROR(__xludf.DUMMYFUNCTION("""COMPUTED_VALUE"""),0.0) -> 0 | D85: =IFERROR(__xludf.DUMMYFUNCTION("""COMPUTED_VALUE"""),"") | E85: =IFERROR(__xludf.DUMMYFUNCTION("""COMPUTED_VALUE"""),"") | F85: =IFERROR(__xludf.DUMMYFUNCTION("""COMPUTED_VALUE"""),"") | G85: =IFERROR(__xludf.DUMMYFUNCTION("""COMPUTED_VALUE"""),"") | H85: =IFERROR(__xludf.DUMMYFUNCTION("""COMPUTED_VALUE"""),"") | I85: =IFERROR(__xludf.DUMMYFUNCTION("""COMPUTED_VALUE"""),"") | J85: =IFERROR(__xludf.DUMMYFUNCTION("""COMPUTED_VALUE"""),"") | K85: =IFERROR(__xludf.DUMMYFUNCTION("""COMPUTED_VALUE"""),"") | ... N85: =IFERROR(__xludf.DUMMYFUNCTION("""COMPUTED_VALUE"""),"")
A86: =IFERROR(__xludf.DUMMYFUNCTION("""COMPUTED_VALUE"""),"21141300A") -> 21141300A | B86: =IFERROR(__xludf.DUMMYFUNCTION("""COMPUTED_VALUE"""),"1/4"" Multiturn Rotor for NR60 Encoders with flat") -> 1/4" Multiturn Rotor for NR60 Encoders with flat | C86: =IFERROR(__xludf.DUMMYFUNCTION("""COMPUTED_VALUE"""),0.0) -> 0 | D86: =IFERROR(__xludf.DUMMYFUNCTION("""COMPUTED_VALUE"""),"") | E86: =IFERROR(__xludf.DUMMYFUNCTION("""COMPUTED_VALUE"""),"") | F86: =IFERROR(__xludf.DUMMYFUNCTION("""COMPUTED_VALUE"""),"") | G86: =IFERROR(__xludf.DUMMYFUNCTION("""COMPUTED_VALUE"""),"") | H86: =IFERROR(__xludf.DUMMYFUNCTION("""COMPUTED_VALUE"""),"") | I86: =IFERROR(__xludf.DUMMYFUNCTION("""COMPUTED_VALUE"""),"") | J86: =IFERROR(__xludf.DUMMYFUNCTION("""COMPUTED_VALUE"""),"") | K86: =IFERROR(__xludf.DUMMYFUNCTION("""COMPUTED_VALUE"""),"") | ... N86: =IFERROR(__xludf.DUMMYFUNCTION("""COMPUTED_VALUE"""),"")
A87: =IFERROR(__xludf.DUMMYFUNCTION("""COMPUTED_VALUE"""),"575-01921-704") -> 575-01921-704 | B87: =IFERROR(__xludf.DUMMYFUNCTION("""COMPUTED_VALUE"""),"Resolver sie 11 /w seal 2,5KHz 0,5 TR 0,12"" shaft +/- 7 min 12"" side lead") -> Resolver sie 11 /w seal 2,5KHz 0,5 TR 0,12" shaft +/- 7 min 12" side lead | C87: =IFERROR(__xludf.DUMMYFUNCTION("""COMPUTED_VALUE"""),0.0) -> 0 | D87: =IFERROR(__xludf.DUMMYFUNCTION("""COMPUTED_VALUE"""),"") | E87: =IFERROR(__xludf.DUMMYFUNCTION("""COMPUTED_VALUE"""),"") | G87: =IFERROR(__xludf.DUMMYFUNCTION("""COMPUTED_VALUE"""),"") | H87: =IFERROR(__xludf.DUMMYFUNCTION("""COMPUTED_VALUE"""),"") | I87: =IFERROR(__xludf.DUMMYFUNCTION("""COMPUTED_VALUE"""),"") | J87: =IFERROR(__xludf.DUMMYFUNCTION("""COMPUTED_VALUE"""),"") | K87: =IFERROR(__xludf.DUMMYFUNCTION("""COMPUTED_VALUE"""),"") | L87: =IFERROR(__xludf.DUMMYFUNCTION("""COMPUTED_VALUE"""),"") | M87: =IFERROR(__xludf.DUMMYFUNCTION("""COMPUTED_VALUE"""),"") | N87: =IFERROR(__xludf.DUMMYFUNCTION("""COMPUTED_VALUE"""),"")
A88: =IFERROR(__xludf.DUMMYFUNCTION("""COMPUTED_VALUE"""),"575-01922-4") -> 575-01922-4 | B88: =IFERROR(__xludf.DUMMYFUNCTION("""COMPUTED_VALUE"""),"Res. Size 11, 1.75 TR 400Hz, control transformer w/18"" leads") -> Res. Size 11, 1.75 TR 400Hz, control transformer w/18" leads | C88: =IFERROR(__xludf.DUMMYFUNCTION("""COMPUTED_VALUE"""),0.0) -> 0 | D88: =IFERROR(__xludf.DUMMYFUNCTION("""COMPUTED_VALUE"""),"") | E88: =IFERROR(__xludf.DUMMYFUNCTION("""COMPUTED_VALUE"""),"") | G88: =IFERROR(__xludf.DUMMYFUNCTION("""COMPUTED_VALUE"""),"") | H88: =IFERROR(__xludf.DUMMYFUNCTION("""COMPUTED_VALUE"""),"") | I88: =IFERROR(__xludf.DUMMYFUNCTION("""COMPUTED_VALUE"""),"") | J88: =IFERROR(__xludf.DUMMYFUNCTION("""COMPUTED_VALUE"""),"") | K88: =IFERROR(__xludf.DUMMYFUNCTION("""COMPUTED_VALUE"""),"") | L88: =IFERROR(__xludf.DUMMYFUNCTION("""COMPUTED_VALUE"""),"") | M88: =IFERROR(__xludf.DUMMYFUNCTION("""COMPUTED_VALUE"""),"") | N88: =IFERROR(__xludf.DUMMYFUNCTION("""COMPUTED_VALUE"""),"")
A89: =IFERROR(__xludf.DUMMYFUNCTION("""COMPUTED_VALUE"""),2.11162E8) -> 211162000 | B89: =IFERROR(__xludf.DUMMYFUNCTION("""COMPUTED_VALUE"""),"HT-20 (K+L) Resolver Mod Dwg Shaft length .275") -> HT-20 (K+L) Resolver Mod Dwg Shaft length .275 | C89: =IFERROR(__xludf.DUMMYFUNCTION("""COMPUTED_VALUE"""),0.0) -> 0 | D89: =IFERROR(__xludf.DUMMYFUNCTION("""COMPUTED_VALUE"""),"") | E89: =IFERROR(__xludf.DUMMYFUNCTION("""COMPUTED_VALUE"""),"") | F89: =IFERROR(__xludf.DUMMYFUNCTION("""COMPUTED_VALUE"""),"Ф40 AL2017") -> Ф40 AL2017 | G89: =IFERROR(__xludf.DUMMYFUNCTION("""COMPUTED_VALUE"""),"") | H89: =IFERROR(__xludf.DUMMYFUNCTION("""COMPUTED_VALUE"""),"") | I89: =IFERROR(__xludf.DUMMYFUNCTION("""COMPUTED_VALUE"""),"") | J89: =IFERROR(__xludf.DUMMYFUNCTION("""COMPUTED_VALUE"""),"") | K89: =IFERROR(__xludf.DUMMYFUNCTION("""COMPUTED_VALUE"""),"") | L89: =IFERROR(__xludf.DUMMYFUNCTION("""COMPUTED_VALUE"""),"") | M89: =IFERROR(__xludf.DUMMYFUNCTION("""COMPUTED_VALUE"""),"") | N89: =IFERROR(__xludf.DUMMYFUNCTION("""COMPUTED_VALUE"""),"")
A90: =IFERROR(__xludf.DUMMYFUNCTION("""COMPUTED_VALUE"""),"21111200F") -> 21111200F | B90: =IFERROR(__xludf.DUMMYFUNCTION("""COMPUTED_VALUE"""),"DC-25 Rear Cover Blank") -> DC-25 Rear Cover Blank | C90: =IFERROR(__xludf.DUMMYFUNCTION("""COMPUTED_VALUE"""),0.69984) -> 0.69984 | D90: =IFERROR(__xludf.DUMMYFUNCTION("""COMPUTED_VALUE"""),0.69984) -> 0.69984 | E90: =IFERROR(__xludf.DUMMYFUNCTION("""COMPUTED_VALUE"""),1.0) -> 1 | F90: =IFERROR(__xludf.DUMMYFUNCTION("""COMPUTED_VALUE"""),"") | G90: =IFERROR(__xludf.DUMMYFUNCTION("""COMPUTED_VALUE"""),"") | H90: =IFERROR(__xludf.DUMMYFUNCTION("""COMPUTED_VALUE"""),"") | I90: =IFERROR(__xludf.DUMMYFUNCTION("""COMPUTED_VALUE"""),"") | J90: =IFERROR(__xludf.DUMMYFUNCTION("""COMPUTED_VALUE"""),"") | K90: =IFERROR(__xludf.DUMMYFUNCTION("""COMPUTED_VALUE"""),"") | L90: =IFERROR(__xludf.DUMMYFUNCTION("""COMPUTED_VALUE"""),"Ф65 AL 2017 Italy") -> Ф65 AL 2017 Italy | M90: =IFERROR(__xludf.DUMMYFUNCTION("""COMPUTED_VALUE"""),0.054) -> 0.054 | N90: =IFERROR(__xludf.DUMMYFUNCTION("""COMPUTED_VALUE"""),0.69984) -> 0.69984
A91: =IFERROR(__xludf.DUMMYFUNCTION("""COMPUTED_VALUE"""),"21129000B") -> 21129000B | B91: =IFERROR(__xludf.DUMMYFUNCTION("""COMPUTED_VALUE"""),"SSI Multiturn Cover For DC25FS") -> SSI Multiturn Cover For DC25FS | C91: =IFERROR(__xludf.DUMMYFUNCTION("""COMPUTED_VALUE"""),0.7257600000000001) -> 0.72576 | D91: =IFERROR(__xludf.DUMMYFUNCTION("""COMPUTED_VALUE"""),0.7257600000000001) -> 0.72576 | E91: =IFERROR(__xludf.DUMMYFUNCTION("""COMPUTED_VALUE"""),1.0) -> 1 | F91: =IFERROR(__xludf.DUMMYFUNCTION("""COMPUTED_VALUE"""),"") | G91: =IFERROR(__xludf.DUMMYFUNCTION("""COMPUTED_VALUE"""),"") | H91: =IFERROR(__xludf.DUMMYFUNCTION("""COMPUTED_VALUE"""),"") | I91: =IFERROR(__xludf.DUMMYFUNCTION("""COMPUTED_VALUE"""),"") | J91: =IFERROR(__xludf.DUMMYFUNCTION("""COMPUTED_VALUE"""),"") | K91: =IFERROR(__xludf.DUMMYFUNCTION("""COMPUTED_VALUE"""),"") | L91: =IFERROR(__xludf.DUMMYFUNCTION("""COMPUTED_VALUE"""),"Ф65 AL 2017 Italy") -> Ф65 AL 2017 Italy | M91: =IFERROR(__xludf.DUMMYFUNCTION("""COMPUTED_VALUE"""),0.056) -> 0.056 | N91: =IFERROR(__xludf.DUMMYFUNCTION("""COMPUTED_VALUE"""),0.7257600000000001) -> 0.72576
A92: =IFERROR(__xludf.DUMMYFUNCTION("""COMPUTED_VALUE"""),2.11279E8) -> 211279000 | B92: =IFERROR(__xludf.DUMMYFUNCTION("""COMPUTED_VALUE"""),"DC25 & H25 10mm shaft 303 SS new version") -> DC25 & H25 10mm shaft 303 SS new version | C92: =IFERROR(__xludf.DUMMYFUNCTION("""COMPUTED_VALUE"""),0.0) -> 0 | D92: =IFERROR(__xludf.DUMMYFUNCTION("""COMPUTED_VALUE"""),"") | E92: =IFERROR(__xludf.DUMMYFUNCTION("""COMPUTED_VALUE"""),"") | F92: =IFERROR(__xludf.DUMMYFUNCTION("""COMPUTED_VALUE"""),"") | G92: =IFERROR(__xludf.DUMMYFUNCTION("""COMPUTED_VALUE"""),"") | H92: =IFERROR(__xludf.DUMMYFUNCTION("""COMPUTED_VALUE"""),"") | I92: =IFERROR(__xludf.DUMMYFUNCTION("""COMPUTED_VALUE"""),"") | J92: =IFERROR(__xludf.DUMMYFUNCTION("""COMPUTED_VALUE"""),"") | K92: =IFERROR(__xludf.DUMMYFUNCTION("""COMPUTED_VALUE"""),"") | ... N92: =IFERROR(__xludf.DUMMYFUNCTION("""COMPUTED_VALUE"""),"")
A93: =IFERROR(__xludf.DUMMYFUNCTION("""COMPUTED_VALUE"""),"H25-FS-10") -> H25-FS-10 | B93: =IFERROR(__xludf.DUMMYFUNCTION("""COMPUTED_VALUE"""),"Transducer, 10 mm Shaft,Flange mount, side connector") -> Transducer, 10 mm Shaft,Flange mount, side connector | C93: =IFERROR(__xludf.DUMMYFUNCTION("""COMPUTED_VALUE"""),1.8503) -> 1.8503 | D93: =IFERROR(__xludf.DUMMYFUNCTION("""COMPUTED_VALUE"""),1.8503) -> 1.8503 | E93: =IFERROR(__xludf.DUMMYFUNCTION("""COMPUTED_VALUE"""),"") | F93: =IFERROR(__xludf.DUMMYFUNCTION("""COMPUTED_VALUE"""),"Cast AL Bulgaria (pc.)") -> Cast AL Bulgaria (pc.) | G93: =IFERROR(__xludf.DUMMYFUNCTION("""COMPUTED_VALUE"""),0.213) -> 0.213 | H93: =IFERROR(__xludf.DUMMYFUNCTION("""COMPUTED_VALUE"""),0.99258) -> 0.99258 | I93: =IFERROR(__xludf.DUMMYFUNCTION("""COMPUTED_VALUE"""),"AL USA (pc.)") -> AL USA (pc.) | J93: =IFERROR(__xludf.DUMMYFUNCTION("""COMPUTED_VALUE"""),0.07) -> 0.07 | K93: =IFERROR(__xludf.DUMMYFUNCTION("""COMPUTED_VALUE"""),0.11900000000000001) -> 0.119 | L93: =IFERROR(__xludf.DUMMYFUNCTION("""COMPUTED_VALUE"""),"Ф65 AL 2017 Italy") -> Ф65 AL 2017 Italy | M93: =IFERROR(__xludf.DUMMYFUNCTION("""COMPUTED_VALUE"""),0.057) -> 0.057 | N93: =IFERROR(__xludf.DUMMYFUNCTION("""COMPUTED_VALUE"""),0.73872) -> 0.73872
A94: =IFERROR(__xludf.DUMMYFUNCTION("""COMPUTED_VALUE"""),"575-91029") -> 575-91029 | B94: =IFERROR(__xludf.DUMMYFUNCTION("""COMPUTED_VALUE"""),"DC25-FE .50 TR/ 250Hz Ctrl. Transformer. Body only") -> DC25-FE .50 TR/ 250Hz Ctrl. Transformer. Body only | C94: =IFERROR(__xludf.DUMMYFUNCTION("""COMPUTED_VALUE"""),3.3849200000000006) -> 3.38492 | D94: =IFERROR(__xludf.DUMMYFUNCTION("""COMPUTED_VALUE"""),3.3849200000000006) -> 3.38492 | E94: =IFERROR(__xludf.DUMMYFUNCTION("""COMPUTED_VALUE"""),"") | F94: =IFERROR(__xludf.DUMMYFUNCTION("""COMPUTED_VALUE"""),"Ф65 AL 2017 Italy") -> Ф65 AL 2017 Italy | G94: =IFERROR(__xludf.DUMMYFUNCTION("""COMPUTED_VALUE"""),0.252) -> 0.252 | H94: =IFERROR(__xludf.DUMMYFUNCTION("""COMPUTED_VALUE"""),3.2659200000000004) -> 3.26592 | I94: =IFERROR(__xludf.DUMMYFUNCTION("""COMPUTED_VALUE"""),"AL USA (pc.)") -> AL USA (pc.) | J94: =IFERROR(__xludf.DUMMYFUNCTION("""COMPUTED_VALUE"""),0.07) -> 0.07 | K94: =IFERROR(__xludf.DUMMYFUNCTION("""COMPUTED_VALUE"""),0.11900000000000001) -> 0.119 | L94: =IFERROR(__xludf.DUMMYFUNCTION("""COMPUTED_VALUE"""),"") | M94: =IFERROR(__xludf.DUMMYFUNCTION("""COMPUTED_VALUE"""),"") | N94: =IFERROR(__xludf.DUMMYFUNCTION("""COMPUTED_VALUE"""),"")
A95: =IFERROR(__xludf.DUMMYFUNCTION("""COMPUTED_VALUE"""),2.11423E8) -> 211423000 | B95: =IFERROR(__xludf.DUMMYFUNCTION("""COMPUTED_VALUE"""),"1/2"" Hub rotor multiturn New collar-style shaft") -> 1/2" Hub rotor multiturn New collar-style shaft | C95: =IFERROR(__xludf.DUMMYFUNCTION("""COMPUTED_VALUE"""),0.0) -> 0 | D95: =IFERROR(__xludf.DUMMYFUNCTION("""COMPUTED_VALUE"""),"") | E95: =IFERROR(__xludf.DUMMYFUNCTION("""COMPUTED_VALUE"""),"") | F95: =IFERROR(__xludf.DUMMYFUNCTION("""COMPUTED_VALUE"""),"") | G95: =IFERROR(__xludf.DUMMYFUNCTION("""COMPUTED_VALUE"""),"") | H95: =IFERROR(__xludf.DUMMYFUNCTION("""COMPUTED_VALUE"""),"") | I95: =IFERROR(__xludf.DUMMYFUNCTION("""COMPUTED_VALUE"""),"") | J95: =IFERROR(__xludf.DUMMYFUNCTION("""COMPUTED_VALUE"""),"") | K95: =IFERROR(__xludf.DUMMYFUNCTION("""COMPUTED_VALUE"""),"") | ... N95: =IFERROR(__xludf.DUMMYFUNCTION("""COMPUTED_VALUE"""),"")
A96: =IFERROR(__xludf.DUMMYFUNCTION("""COMPUTED_VALUE"""),2.11426E8) -> 211426000 | B96: =IFERROR(__xludf.DUMMYFUNCTION("""COMPUTED_VALUE"""),"DC25 3/8"" SHAFT WITH FLAT & HOLE") -> DC25 3/8" SHAFT WITH FLAT & HOLE | D96: =IFERROR(__xludf.DUMMYFUNCTION("""COMPUTED_VALUE"""),"") | E96: =IFERROR(__xludf.DUMMYFUNCTION("""COMPUTED_VALUE"""),"") | G96: =IFERROR(__xludf.DUMMYFUNCTION("""COMPUTED_VALUE"""),"")
A97: =IFERROR(__xludf.DUMMYFUNCTION("""COMPUTED_VALUE"""),"21118100D") -> 21118100D | B97: =IFERROR(__xludf.DUMMYFUNCTION("""COMPUTED_VALUE"""),"DC25 & H25 1/4"" shaft 2007 version") -> DC25 & H25 1/4" shaft 2007 version | C97: =IFERROR(__xludf.DUMMYFUNCTION("""COMPUTED_VALUE"""),0.0) -> 0 | D97: =IFERROR(__xludf.DUMMYFUNCTION("""COMPUTED_VALUE"""),"") | E97: =IFERROR(__xludf.DUMMYFUNCTION("""COMPUTED_VALUE"""),"") | F97: =IFERROR(__xludf.DUMMYFUNCTION("""COMPUTED_VALUE"""),"") | G97: =IFERROR(__xludf.DUMMYFUNCTION("""COMPUTED_VALUE"""),"") | H97: =IFERROR(__xludf.DUMMYFUNCTION("""COMPUTED_VALUE"""),"") | I97: =IFERROR(__xludf.DUMMYFUNCTION("""COMPUTED_VALUE"""),"") | J97: =IFERROR(__xludf.DUMMYFUNCTION("""COMPUTED_VALUE"""),"") | K97: =IFERROR(__xludf.DUMMYFUNCTION("""COMPUTED_VALUE"""),"") | ... N97: =IFERROR(__xludf.DUMMYFUNCTION("""COMPUTED_VALUE"""),"")
A98: =IFERROR(__xludf.DUMMYFUNCTION("""COMPUTED_VALUE"""),"H25-FE-R3N") -> H25-FE-R3N | B98: =IFERROR(__xludf.DUMMYFUNCTION("""COMPUTED_VALUE"""),"Size 25 resolver 3/8 shaft 0,95 TR @ 5000Hz end mount w/ to pin conn.") -> Size 25 resolver 3/8 shaft 0,95 TR @ 5000Hz end mount w/ to pin conn. | C98: =IFERROR(__xludf.DUMMYFUNCTION("""COMPUTED_VALUE"""),4.007000000000001) -> 4.007 | D98: =IFERROR(__xludf.DUMMYFUNCTION("""COMPUTED_VALUE"""),4.007000000000001) -> 4.007 | E98: =IFERROR(__xludf.DUMMYFUNCTION("""COMPUTED_VALUE"""),"") | F98: =IFERROR(__xludf.DUMMYFUNCTION("""COMPUTED_VALUE"""),"Ф65 AL 2017 Italy") -> Ф65 AL 2017 Italy | G98: =IFERROR(__xludf.DUMMYFUNCTION("""COMPUTED_VALUE"""),0.252) -> 0.252 | H98: =IFERROR(__xludf.DUMMYFUNCTION("""COMPUTED_VALUE"""),3.2659200000000004) -> 3.26592 | I98: =IFERROR(__xludf.DUMMYFUNCTION("""COMPUTED_VALUE"""),"AL USA (pc.)") -> AL USA (pc.) | J98: =IFERROR(__xludf.DUMMYFUNCTION("""COMPUTED_VALUE"""),0.07) -> 0.07 | K98: =IFERROR(__xludf.DUMMYFUNCTION("""COMPUTED_VALUE"""),0.11900000000000001) -> 0.119 | L98: =IFERROR(__xludf.DUMMYFUNCTION("""COMPUTED_VALUE"""),"Ф65 AL 2017 Italy") -> Ф65 AL 2017 Italy | M98: =IFERROR(__xludf.DUMMYFUNCTION("""COMPUTED_VALUE"""),0.048) -> 0.048 | N98: =IFERROR(__xludf.DUMMYFUNCTION("""COMPUTED_VALUE"""),0.6220800000000001) -> 0.62208
A99: =IFERROR(__xludf.DUMMYFUNCTION("""COMPUTED_VALUE"""),"DC25-4FS(18)") -> DC25-4FS(18) | B99: =IFERROR(__xludf.DUMMYFUNCTION("""COMPUTED_VALUE"""),"DC25 housing 4 Speed Side Conn. 3/8"" shaft ") -> DC25 housing 4 Speed Side Conn. 3/8" shaft | C99: =IFERROR(__xludf.DUMMYFUNCTION("""COMPUTED_VALUE"""),1.13488) -> 1.13488 | D99: =IFERROR(__xludf.DUMMYFUNCTION("""COMPUTED_VALUE"""),1.13488) -> 1.13488 | E99: =IFERROR(__xludf.DUMMYFUNCTION("""COMPUTED_VALUE"""),"") | F99: =IFERROR(__xludf.DUMMYFUNCTION("""COMPUTED_VALUE"""),"Cast AL Bulgaria (pc.)") -> Cast AL Bulgaria (pc.) | G99: =IFERROR(__xludf.DUMMYFUNCTION("""COMPUTED_VALUE"""),0.218) -> 0.218 | H99: =IFERROR(__xludf.DUMMYFUNCTION("""COMPUTED_VALUE"""),1.0158800000000001) -> 1.01588 | I99: =IFERROR(__xludf.DUMMYFUNCTION("""COMPUTED_VALUE"""),"AL USA (pc.)") -> AL USA (pc.) | J99: =IFERROR(__xludf.DUMMYFUNCTION("""COMPUTED_VALUE"""),0.07) -> 0.07 | K99: =IFERROR(__xludf.DUMMYFUNCTION("""COMPUTED_VALUE"""),0.11900000000000001) -> 0.119 | L99: =IFERROR(__xludf.DUMMYFUNCTION("""COMPUTED_VALUE"""),"") | M99: =IFERROR(__xludf.DUMMYFUNCTION("""COMPUTED_VALUE"""),"") | N99: =IFERROR(__xludf.DUMMYFUNCTION("""COMPUTED_VALUE"""),"")
A100: =IFERROR(__xludf.DUMMYFUNCTION("""COMPUTED_VALUE"""),2.11406E8) -> 211406000 | B100: =IFERROR(__xludf.DUMMYFUNCTION("""COMPUTED_VALUE"""),"NR25 Prodibus Singleturn Rear Cover") -> NR25 Prodibus Singleturn Rear Cover | C100: =IFERROR(__xludf.DUMMYFUNCTION("""COMPUTED_VALUE"""),0.68688) -> 0.68688 | D100: =IFERROR(__xludf.DUMMYFUNCTION("""COMPUTED_VALUE"""),0.68688) -> 0.68688 | E100: =IFERROR(__xludf.DUMMYFUNCTION("""COMPUTED_VALUE"""),1.0) -> 1 | F100: =IFERROR(__xludf.DUMMYFUNCTION("""COMPUTED_VALUE"""),"") | G100: =IFERROR(__xludf.DUMMYFUNCTION("""COMPUTED_VALUE"""),"") | H100: =IFERROR(__xludf.DUMMYFUNCTION("""COMPUTED_VALUE"""),"") | I100: =IFERROR(__xludf.DUMMYFUNCTION("""COMPUTED_VALUE"""),"") | J100: =IFERROR(__xludf.DUMMYFUNCTION("""COMPUTED_VALUE"""),"") | K100: =IFERROR(__xludf.DUMMYFUNCTION("""COMPUTED_VALUE"""),"") | L100: =IFERROR(__xludf.DUMMYFUNCTION("""COMPUTED_VALUE"""),"Ф65 AL 2017 Italy") -> Ф65 AL 2017 Italy | M100: =IFERROR(__xludf.DUMMYFUNCTION("""COMPUTED_VALUE"""),0.053) -> 0.053 | N100: =IFERROR(__xludf.DUMMYFUNCTION("""COMPUTED_VALUE"""),0.68688) -> 0.68688
...

Sheet Данни
A1: Номер | B1: Описание | C1: Unit cost | D1: HTS Code
A2: ='Номенклатура'!A2 | B2: ='Номенклатура'!B2
A3: ='Номенклатура'!A3 -> 575-60044 | B3: ='Номенклатура'!B3 -> DC60 Multiturn Body 3/8'' shaft; Nitrile seal Sq. Flange Side PG9 conn | C3: 113 | D3: 8543.90.8885
A4: ='Номенклатура'!A4 -> 575-91001-9 | B4: ='Номенклатура'!B4 -> DC25FS </= 9 min IP69Kw hole on shaft no knurl M12 side conn. HARSCO | C4: 91 | D4: 8543.90.8885
A5: ='Номенклатура'!A5 -> 575-92015 | B5: ='Номенклатура'!B5 -> DC25FE, Multiturn Body 5/8" shaft flange end conn. | C5: 91 | D5: 8543.90.8885
A6: ='Номенклатура'!A6 -> 575-93001 | B6: ='Номенклатура'!B6 -> H25 Resolver Shaft 5/8" With MS-16 side conn. w/o seal Short body | C6: 91 | D6: 8543.90.8885
A7: ='Номенклатура'!A7 -> H25-FE-06 | B7: ='Номенклатура'!B7 -> Transducer 1 Turn Flange Mntaligned at zero degrees With 3mm Key Way, 3/8"shaft | C7: 91 | D7: 8543.70.4500
A8: ='Номенклатура'!A8 -> H25-FE | B8: ='Номенклатура'!B8 -> Size 25 resolver 3/8" shaft Flange mount End connector 0.95 TR @ 5000 Hz | C8: 91 | D8: 8543.70.4500
A9: ='Номенклатура'!A9 -> 575-60007 | B9: ='Номенклатура'!B9 -> NR-60 Multi Body 10mm shaft Nitrile seal Square flange End conn. | C9: 113 | D9: 8543.90.8885
A10: ='Номенклатура'!A10 -> 575-91001 | B10: ='Номенклатура'!B10 -> DC25FE </= 9 min 3/8" sahft flange end conn. | C10: 91 | D10: 8543.90.8885
A11: ='Номенклатура'!A11 -> 575-92000 | B11: ='Номенклатура'!B11 -> DC25FS Multiturn Body 3/8" shaft Flange Multiturn Body 3/8" shaft MS23 side conn | C11: 91 | D11: 8543.70.4500
A12: ='Номенклатура'!A12 -> 575-92006 | B12: ='Номенклатура'!B12 -> DC25FE </= 9 min 5/8" shaft flange end conn | C12: 91 | D12: 8543.70.4500
A13: ='Номенклатура'!A13 -> DC25-2FE | B13: ='Номенклатура'!B13 -> DC25 Housing 2Sp. End conn. 3/8" shaft | D13: 8543.70.4500
A14: ='Номенклатура'!A14 -> H25-F1E | B14: ='Номенклатура'!B14 -> Transducer 1 Turn C&A Flange TR=0/95; 5KHz end conn. | C14: 91 | D14: 8543.70.4500
A15: ='Номенклатура'!A15 -> H25-FS-06 | B15: ='Номенклатура'!B15 -> Size 25 resolver 3/8" shaft Flange mount Side connector w/3 mm keyway | C15: 91 | D15: 8543.70.4500
A16: ='Номенклатура'!A16 -> H25-SE | B16: ='Номенклатура'!B16 -> Size 25 resolver 3/8" shaft servo mount End connector 0.95 0.95 T.R. @5000 Hz | C16: 91 | D16: 8543.70.4500
A17: ='Номенклатура'!A17 -> 575-60021 | B17: ='Номенклатура'!B17 -> NR-60 Encoder Avago assembly,10 mm, multiturn shaft, servo mount, for SIDE CONNECTORS | C17: 113 | D17: 8543.90.8885
A18: ='Номенклатура'!A18 -> 575-91004 | B18: ='Номенклатура'!B18 -> DC25FS14 </= 9 min. 3/8" shaft flange side con | C18: 91 | D18: 8543.90.8885
A19: ='Номенклатура'!A19 -> 575-92002 | B19: ='Номенклатура'!B19 -> DC25FE multiturn body 3/8" shaft flange | C19: 91 | D19: 8543.90.8885
A20: ='Номенклатура'!A20 -> DC25-4FS(16) | B20: ='Номенклатура'!B20 -> DC25 housing 4 Speed Side Conn. 3/8" shaft | C20: 91 | D20: 8543.90.8885
A21: ='Номенклатура'!A21 -> H25-FS | B21: ='Номенклатура'!B21 -> Size 25 resolver 3/8 shaft Flange mount side connector 0.95 TR @5000Hz | C21: 91 | D21: 8543.70.4500
A22: ='Номенклатура'!A22 -> 575-93002 | B22: ='Номенклатура'!B22 -> H25 Resolver 5/8" shaft MS-16 end conn. w/o seal Short body | C22: 91 | D22: 8543.90.8885
A23: ='Номенклатура'!A23 -> 575-92011 | B23: ='Номенклатура'!B23 -> DC 25FS Singleturn body 5/8" shaft flange SSI Dura MS23 side conn </= 9min | C23: 91 | D23: 8543.90.8885
A24: ='Номенклатура'!A24 -> 575-91055 | B24: ='Номенклатура'!B24 -> H25-w/ Special servo nose Two flats on shaft TR=0.95 @ 5KHz | C24: 91 | D24: 8543.90.8885
A25: ='Номенклатура'!A25 -> 575-91009 | B25: ='Номенклатура'!B25 -> DC25FS18 </= 9 min 3/8" shaft flange side conn | C25: 91 | D25: 8543.90.8885
... A29: ='Номенклатура'!A29 -> H25-SE-10 | B29: ='Номенклатура'!B29 -> Transducer 1 Turn C&A Flange servo mount with 10mm shaft | C29: 91 | D29: 8543.70.4500
A30: ='Номенклатура'!A30 -> 22140701А | B30: ='Номенклатура'!B30 -> H25 Body with Shaft zeroed for HT-400x-L Single turn TR=1,4, 5KHz,2250Hz w/o conn
A31: ='Номенклатура'!A31 -> 575-91007 | B31: ='Номенклатура'!B31 -> DC25FS16 </=9 min. 3/8" shaft, flange , side conn | C31: 91 | D31: 8543.90.8885
A32: ='Номенклатура'!A32 -> H25-FE-10 | B32: ='Номенклатура'!B32 -> Transducer 1 Turn C&A Flange TR=0.95, 5KHz, w/o conn
A33: ='Номенклатура'!A33 -> H25-SS | B33: ='Номенклатура'!B33 -> Size 25 resolver servo with side connector 0.95 TR@5000Hz 3/8" shaft | C33: 91 | D33: 8543.70.4500
A34: ='Номенклатура'!A34 -> 575-01921 | B34: ='Номенклатура'!B34 -> Resolver size 11, TR=0.5 2500 Hz, Control Transmitter +/- 7min.; 0,12" shaft | C34: 76 | D34: 8543.70.4500
A35: ='Номенклатура'!A35 -> 575-01912-3 | B35: ='Номенклатура'!B35 -> Resolver size 11, TR=0,45 1000Hz, Acc. 3min. Transmitter; 0,12" shaft with flat | C35: 76 | D35: 8543.70.4500
A36: ='Номенклатура'!A36 -> 575-01902 | B36: ='Номенклатура'!B36 -> Resolver size 11, TR-0,95 Transmitter 5KHz; sorted into -1,-4,-8,-10 | C36: 76 | D36: 8543.70.4500
A37: ='Номенклатура'!A37 -> 575-01911-2 | B37: ='Номенклатура'!B37 -> Resolver size 11, TR=,50 2500Hz ACCUR.=<7 with .30" shaft lengt | C37: 76 | D37: 8543.70.4500
A38: ='Номенклатура'!A38 -> 575-01912 | B38: ='Номенклатура'!B38 -> Resolver size 11, TR=0,45 1000Hz, Transmitter Acc. Unsorted | C38: 76 | D38: 8543.70.4500
A39: ='Номенклатура'!A39 -> 575-01924 | B39: ='Номенклатура'!B39 -> Resolver size 11, TR=1,0 1000Hz, control Transmitter +/-7 min | C39: 76 | D39: 8543.70.4500
A40: ='Номенклатура'!A40 -> 575-01920-1 | B40: ='Номенклатура'!B40 -> Resolver size 11, TR=0.45 400Hz,Transmitter w/ flat; Acc.=<7 min. | C40: 76 | D40: 8543.70.4500
A41: ='Номенклатура'!A41 -> 575-01907 | B41: ='Номенклатура'!B41 -> Resolver size 11, TR=1,40 2250Hz | C41: 76 | D41: 8543.70.4500
A42: ='Номенклатура'!A42 -> 575-01909 | B42: ='Номенклатура'!B42 -> Resolver size 11,</=20min TR=0,95 5КHz 2speed | C42: 76 | D42: 8543.70.4500
A43: ='Номенклатура'!A43 -> 575-60025 | B43: ='Номенклатура'!B43 -> NR60 Multiturn Body 3/8" shaft; Nitrile seal Sq. Flange; End conn. | C43: 113 | D43: 8543.90.8885
A44: ='Номенклатура'!A44 -> H25V-FE-10 | B44: ='Номенклатура'!B44 -> H25 Flange mount, Viton Seal, End Connector w/10mm shaft 0.95 TR @ 5000Hz | C44: 91 | D44: 8543.70.4500
... A47: ='Номенклатура'!A47 -> 575-60001 | B47: ='Номенклатура'!B47 -> NR 60 Multiturn Body 6mm shaft; Nitrile seal; 58mm servo; End conn | C47: 113 | D47: 8543.90.8885
A48: ='Номенклатура'!A48 -> 575-60005 | B48: ='Номенклатура'!B48
A49: =#REF! -> #REF! | B49: =#REF! -> #REF!
A50: ='Номенклатура'!A50 -> 575-60027 | B50: ='Номенклатура'!B50
A51: ='Номенклатура'!A51 -> 575-60029 | B51: NR60 Multiturn Body 1/4 | C51: 113 | D51: 8543.90.8885
A52: ='Номенклатура'!A52 -> 575-01910 | B52: ='Номенклатура'!B52 -> Res. For HT-6 R11X-J 12/7 w/0,7"I. shaft | C52: 76 | D52: 8543.70.4500
A53: ='Номенклатура'!A53 -> 575-01911 | B53: ='Номенклатура'!B53 -> Res. Size 11 Freq.=2500 Hz, T.R.=.50, Acc=<7, control xfmr. | C53: 76 | D53: 8543.70.4500
A54: ='Номенклатура'!A54 -> 575-01913 | B54: ='Номенклатура'!B54 -> Res. Size 11 Freq.=2500 Hz, T.R.=.98, Acc<7
A55: ='Номенклатура'!A55 -> 575-01917 | B55: ='Номенклатура'!B55 -> Res. Size 11, T.R.=.50 Freq.=2.5k, Accur.=<10, Control Transfoemer , 2 Speed
A56: ='Номенклатура'!A56 -> 575-01918 | B56: ='Номенклатура'!B56 -> Res. Size 11 T.R.=0.54, Freq.= 4 k. ACCUR.=<7, Control Transmitter | C56: 76 | D56: 8543.70.4500
A57: ='Номенклатура'!A57 -> 575-01920 | B57: ='Номенклатура'!B57 -> Res. Size 11. T.R.=.45, FREQ.= 400 Hz, ACCUR. =<7
A58: ='Номенклатура'!A58 -> 575-01921-701 | B58: ='Номенклатура'!B58 -> Res. Size 11 Transmitter, T.R.=0.5, Freq.=2.5 КHz, Acc =+/- 7 min. With Conn. & seal
A59: ='Номенклатура'!A59 -> 575-01922 | B59: ='Номенклатура'!B59 -> Res. Size 11 T.R.=1.75, Freq.= 400 Hz, Control Transformer, w/ 18" leads
A60: ='Номенклатура'!A60 -> 575-01923 | B60: ='Номенклатура'!B60 -> Res. Size 11 T.R.=1.93, Freq.= 400 Hz, Control Transformer
A61: ='Номенклатура'!A61 -> 575-15903 | B61: ='Номенклатура'!B61 -> Res. Size 11 Transmitter, T.R.=0.95, Freq.=2.5 КHz, Acc =< 7 | C61: 76 | D61: 8543.70.4500
A62: ='Номенклатура'!A62 -> 211387000 | B62: 10 mm Multiturn Shaft for TURCK Encoders with flat | C62: 20 | D62: 8543.90.8885
A63: ='Номенклатура'!A63 -> 21108801A | B63: ='Номенклатура'!B63 -> Shaft DC-425.375 Dia .250End | C63: 20 | D63: 8543.90.8885
A64: ='Номенклатура'!A64 -> 21114201B | B64: ='Номенклатура'!B64 -> 5/8" Shaft w/o Keyway with Front slot Across Shaft for DC425 | C64: 20 | D64: 8543.90.8885
A65: ='Номенклатура'!A65 -> 22146700A | B65: ='Номенклатура'!B65 -> DC60 Rear Cover with PG9 hole and LED pipe for Analog DC60 | C65: 10 | D65: 8543.90.8885
A66: ='Номенклатура'!A66 -> 21130000B | B66: ='Номенклатура'!B66 -> Aluminium flange for size 25 Hub Shaft units for 26mm nitrile seal | C66: 10 | D66: 8543.90.8885
A67: ='Номенклатура'!A67 -> 21134200C | B67: ='Номенклатура'!B67 -> NR25 Ethernet Multiturn end conn. Rear cover | C67: 10 | D67: 8543.90.8885
A68: ='Номенклатура'!A68 -> RM-5 | B68: ='Номенклатура'!B68 -> Reference Module Harowe #11BRCX-300-C10 For 0.45 TR resolver | C68: 20 | D68: 8504.31.4035
A69: ='Номенклатура'!A69 -> 211174000 | B69: ='Номенклатура'!B69 -> Modified Size 11 resolver Made from 575-01902-1 machined flat on the body | C69: 76 | D69: 8543.70.4500
A70: ='Номенклатура'!A70 -> 21111202E | B70: ='Номенклатура'!B70 -> DC-25 Rear Cover Size 18 | C70: 10 | D70: 8543.90.8885
A71: ='Номенклатура'!A71 -> 22124400K | B71: ='Номенклатура'!B71 -> H25/DC25 Servo Nose in 6061 AL new stile | C71: 10 | D71: 8543.90.8885
A72: ='Номенклатура'!A72 -> 22903700B | B72: ='Номенклатура'!B72 -> AC Steppers Transformer Uses heavy wire 630-02228 for SD17060x, SD3045x | C72: 20 | D72: 8504.31.2000
A73: ='Номенклатура'!A73 -> 211389000 | B73: ='Номенклатура'!B73
A74: ='Номенклатура'!A74 -> 221397000 | B74: ='Номенклатура'!B74 -> DC25 & H25 Flange for 5/8" shaft 6061-T6 AL | C74: 10 | D74: 8543.90.8885
A75: ='Номенклатура'!A75 -> 21110702D | B75: ='Номенклатура'!B75 -> 5/8" S.S. shaft, w .250 end with keyway | C75: 20 | D75: 8543.90.8885
A76: ='Номенклатура'!A76 -> 21129501B | B76: ='Номенклатура'!B76 -> 5/8" Rotor Singleturn DC 25 Made from 200-91229 in BG Material SS-316 | C76: 20 | D76: 8543.90.8885
A77: ='Номенклатура'!A77 -> 211137000 | B77: ='Номенклатура'!B77 -> Transformer DC25 5 pin | C77: 20 | D77: 8543.90.8885
A78: ='Номенклатура'!A78 -> 551-90002 | B78: ='Номенклатура'!B78 -> Transformer Output 36150 Reference | C78: 20 | D78: 8543.70.4500
A79: ='Номенклатура'!A79 -> 211294020 | B79: ='Номенклатура'!B79 -> IP67 R11 Rear Cover Length=17mm Hole Dia=18mm
A80: ='Номенклатура'!A80 -> 21129405А | B80: ='Номенклатура'!B80 -> IP67 R11 Rear Cover Length=12mm Hole Dia=15,3mm for R11X-F10B/7S3-52
A81: ='Номенклатура'!A81 -> 211366000 | B81: ='Номенклатура'!B81 -> NR25 Profibus Multiturn rear cover 3 end con., AL | D81: 8543.90.8885
A82: ='Номенклатура'!A82 -> 21137200A | B82: ='Номенклатура'!B82 -> NR25 Profibus Multiturn rear cover singleturn end con. | C82: 10 | D82: 8543.90.8885
A83: ='Номенклатура'!A83 -> 221466000 | B83: ='Номенклатура'!B83 -> Metric servo nose for size 25 units; B.C.=48mm mounting holes
A84: ='Номенклатура'!A84 -> 2216701A | B84: ='Номенклатура'!B84 -> DC60 Rear cover w/o conn. Hole; LED pipe for Analog DC60 | D84: 8543.90.8885
A85: ='Номенклатура'!A85 -> 21129500A | B85: ='Номенклатура'!B85 -> 5/8" Rotor Assembly SS-303 used in DC25,H25, HT-20C singleturn,1-speed, J-type | C85: 20 | D85: 8543.90.8885
A86: ='Номенклатура'!A86 -> 21141300A | B86: ='Номенклатура'!B86 -> 1/4" Multiturn Rotor for NR60 Encoders with flat | C86: 20 | D86: 8543.90.8885
A87: ='Номенклатура'!A87 -> 575-01921-704 | B87: ='Номенклатура'!B87 -> Resolver sie 11 /w seal 2,5KHz 0,5 TR 0,12" shaft +/- 7 min 12" side lead | D87: 8543.70.4500
A88: ='Номенклатура'!A88 -> 575-01922-4 | B88: ='Номенклатура'!B88 -> Res. Size 11, 1.75 TR 400Hz, control transformer w/18" leads | C88: 76 | D88: 8543.70.4500
A89: ='Номенклатура'!A89 -> 211162000 | B89: ='Номенклатура'!B89 -> HT-20 (K+L) Resolver Mod Dwg Shaft length .275 | C89: 76 | D89: 8543.70.4500
A90: ='Номенклатура'!A90 -> 21111200F | B90: ='Номенклатура'!B90 -> DC-25 Rear Cover Blank | C90: 10 | D90: 8543.90.8885
A91: ='Номенклатура'!A91 -> 21129000B | B91: ='Номенклатура'!B91 -> SSI Multiturn Cover For DC25FS | C91: 10 | D91: 8543.90.8885
A92: ='Номенклатура'!A92 -> 211279000 | B92: ='Номенклатура'!B92 -> DC25 & H25 10mm shaft 303 SS new version | C92: 20 | D92: 8543.90.8885
A93: ='Номенклатура'!A93 -> H25-FS-10 | B93: ='Номенклатура'!B93 -> Transducer, 10 mm Shaft,Flange mount, side connector | C93: 91 | D93: 8543.70.4500
A94: ='Номенклатура'!A94 -> 575-91029 | B94: ='Номенклатура'!B94 -> DC25-FE .50 TR/ 250Hz Ctrl. Transformer. Body only
A95: ='Номенклатура'!A95 -> 211423000 | B95: ='Номенклатура'!B95 -> 1/2" Hub rotor multiturn New collar-style shaft | C95: 20 | D95: 8543.90.8885
A96: ='Номенклатура'!A96 -> 211426000 | B96: ='Номенклатура'!B96 -> DC25 3/8" SHAFT WITH FLAT & HOLE | C96: 20 | D96: 8543.90.8885
A97: ='Номенклатура'!A97 -> 21118100D | B97: ='Номенклатура'!B97 -> DC25 & H25 1/4" shaft 2007 version | C97: 20 | D97: 8543.90.8885
A98: ='Номенклатура'!A98 -> H25-FE-R3N | B98: ='Номенклатура'!B98 -> Size 25 resolver 3/8 shaft 0,95 TR @ 5000Hz end mount w/ to pin conn. | C98: 91 | D98: 8543.70.4500
A99: ='Номенклатура'!A99 -> DC25-4FS(18) | B99: ='Номенклатура'!B99 -> DC25 housing 4 Speed Side Conn. 3/8" shaft | D99: 8543.90.8885
A100: ='Номенклатура'!A100 -> 211406000 | B100: ='Номенклатура'!B100 -> NR25 Prodibus Singleturn Rear Cover | C100: 20 | D100: 8543.90.8885
A101: ='Номенклатура'!A101 -> 575-95002 | B101: ='Номенклатура'!B101 -> Transformer Assembly 1-speed for HT-20C/H25/THE/DC25/NR25 | C101: 20 | D101: 8543.90.8885
A102: ='Номенклатура'!A102 -> 575-95003 | B102: ='Номенклатура'!B102 -> Size25 Transformer Shell Part 1 with slot for wires Machined Powder metal | C102: 20 | D102: 8543.90.8885
A103: ='Номенклатура'!A103 -> 575-95004 | B103: ='Номенклатура'!B103 -> Size25 Transformer Shell Part 2 with slot for wires Machined Powder metal | C103: 20 | D103: 8543.90.8885
A104: ='Номенклатура'!A104 -> 575-95001 | B104: ='Номенклатура'!B104 -> Resolver Stator Assembly 1-speed for HT-20C/THE/H25/DC25/NR25 | C104: 20 | D104: 8543.90.8885
A105: ='Номенклатура'!A105 -> 097-90001 | B105: ='Номенклатура'!B105 -> H25&DC25 Shaft 3/8" Dia. for old flange 22133200A | D105: 8543.90.8885
...

Sheet План
A1: =IFERROR(__xludf.DUMMYFUNCTION("ARRAYFORMULA(IMPORTRANGE(""https://docs.google.com/spreadsheets/d/1iWfgTn_Pi02Cgzvv2hNxbn5R87Czwggoktc9asHRCjo/"",""Разбивка!A1:C1000""))"),"бр.") -> бр. | C1: =IFERROR(__xludf.DUMMYFUNCTION("""COMPUTED_VALUE"""),"Номер") -> Номер | Q1: ARRAYFORMULA(IMPORTRANGE("https://docs.google.com/spreadsheets/d/1iWfgTn_Pi02Cgzvv2hNxbn5R87Czwggoktc9asHRCjo/","Разбивка!A1:C1000"))
A2: =IFERROR(__xludf.DUMMYFUNCTION("""COMPUTED_VALUE"""),100.0) -> 100 | B2: =IFERROR(__xludf.DUMMYFUNCTION("""COMPUTED_VALUE"""),"21100202N") -> 21100202N | C2: =IFERROR(__xludf.DUMMYFUNCTION("""COMPUTED_VALUE"""),"21100202N") -> 21100202N
A3: =IFERROR(__xludf.DUMMYFUNCTION("""COMPUTED_VALUE"""),350.0) -> 350 | B3: =IFERROR(__xludf.DUMMYFUNCTION("""COMPUTED_VALUE"""),2.11137E8) -> 211137000 | C3: =IFERROR(__xludf.DUMMYFUNCTION("""COMPUTED_VALUE"""),2.11137E8) -> 211137000
A4: =IFERROR(__xludf.DUMMYFUNCTION("""COMPUTED_VALUE"""),10.0) -> 10 | B4: =IFERROR(__xludf.DUMMYFUNCTION("""COMPUTED_VALUE"""),2.11279E8) -> 211279000 | C4: =IFERROR(__xludf.DUMMYFUNCTION("""COMPUTED_VALUE"""),2.11279E8) -> 211279000
A5: =IFERROR(__xludf.DUMMYFUNCTION("""COMPUTED_VALUE"""),10.0) -> 10 | B5: =IFERROR(__xludf.DUMMYFUNCTION("""COMPUTED_VALUE"""),"21129500A") -> 21129500A | C5: =IFERROR(__xludf.DUMMYFUNCTION("""COMPUTED_VALUE"""),"21129500A") -> 21129500A
A6: =IFERROR(__xludf.DUMMYFUNCTION("""COMPUTED_VALUE"""),5.0) -> 5 | B6: =IFERROR(__xludf.DUMMYFUNCTION("""COMPUTED_VALUE"""),"21130002D") -> 21130002D | C6: =IFERROR(__xludf.DUMMYFUNCTION("""COMPUTED_VALUE"""),"21130002D") -> 21130002D
A7: =IFERROR(__xludf.DUMMYFUNCTION("""COMPUTED_VALUE"""),175.0) -> 175 | B7: =IFERROR(__xludf.DUMMYFUNCTION("""COMPUTED_VALUE"""),"21134801A") -> 21134801A | C7: =IFERROR(__xludf.DUMMYFUNCTION("""COMPUTED_VALUE"""),"21134801A") -> 21134801A
A8: =IFERROR(__xludf.DUMMYFUNCTION("""COMPUTED_VALUE"""),10.0) -> 10 | B8: =IFERROR(__xludf.DUMMYFUNCTION("""COMPUTED_VALUE"""),2.11361E8) -> 211361000 | C8: =IFERROR(__xludf.DUMMYFUNCTION("""COMPUTED_VALUE"""),2.11361E8) -> 211361000
A9: =IFERROR(__xludf.DUMMYFUNCTION("""COMPUTED_VALUE"""),70.0) -> 70 | B9: =IFERROR(__xludf.DUMMYFUNCTION("""COMPUTED_VALUE"""),"21137200A") -> 21137200A | C9: =IFERROR(__xludf.DUMMYFUNCTION("""COMPUTED_VALUE"""),"21137200A") -> 21137200A
A10: =IFERROR(__xludf.DUMMYFUNCTION("""COMPUTED_VALUE"""),120.0) -> 120 | B10: =IFERROR(__xludf.DUMMYFUNCTION("""COMPUTED_VALUE"""),"21139800A") -> 21139800A | C10: =IFERROR(__xludf.DUMMYFUNCTION("""COMPUTED_VALUE"""),"#N/A") -> #N/A
A11: =IFERROR(__xludf.DUMMYFUNCTION("""COMPUTED_VALUE"""),20.0) -> 20 | B11: =IFERROR(__xludf.DUMMYFUNCTION("""COMPUTED_VALUE"""),2.11404E8) -> 211404000 | C11: =IFERROR(__xludf.DUMMYFUNCTION("""COMPUTED_VALUE"""),2.11404E8) -> 211404000
A12: =IFERROR(__xludf.DUMMYFUNCTION("""COMPUTED_VALUE"""),15.0) -> 15 | B12: =IFERROR(__xludf.DUMMYFUNCTION("""COMPUTED_VALUE"""),"22146701A") -> 22146701A | C12: =IFERROR(__xludf.DUMMYFUNCTION("""COMPUTED_VALUE"""),"22146701A") -> 22146701A
A13: =IFERROR(__xludf.DUMMYFUNCTION("""COMPUTED_VALUE"""),30.0) -> 30 | B13: =IFERROR(__xludf.DUMMYFUNCTION("""COMPUTED_VALUE"""),"575-01902-750") -> 575-01902-750 | C13: =IFERROR(__xludf.DUMMYFUNCTION("""COMPUTED_VALUE"""),"575-01902-750") -> 575-01902-750
A14: =IFERROR(__xludf.DUMMYFUNCTION("""COMPUTED_VALUE"""),120.0) -> 120 | B14: =IFERROR(__xludf.DUMMYFUNCTION("""COMPUTED_VALUE"""),"575-01921") -> 575-01921 | C14: =IFERROR(__xludf.DUMMYFUNCTION("""COMPUTED_VALUE"""),"575-01921") -> 575-01921
A15: =IFERROR(__xludf.DUMMYFUNCTION("""COMPUTED_VALUE"""),35.0) -> 35 | B15: =IFERROR(__xludf.DUMMYFUNCTION("""COMPUTED_VALUE"""),"575-91001") -> 575-91001 | C15: =IFERROR(__xludf.DUMMYFUNCTION("""COMPUTED_VALUE"""),"575-91001") -> 575-91001
A16: =IFERROR(__xludf.DUMMYFUNCTION("""COMPUTED_VALUE"""),20.0) -> 20 | B16: =IFERROR(__xludf.DUMMYFUNCTION("""COMPUTED_VALUE"""),"575-91009") -> 575-91009 | C16: =IFERROR(__xludf.DUMMYFUNCTION("""COMPUTED_VALUE"""),"575-91009") -> 575-91009
A17: =IFERROR(__xludf.DUMMYFUNCTION("""COMPUTED_VALUE"""),10.0) -> 10 | B17: =IFERROR(__xludf.DUMMYFUNCTION("""COMPUTED_VALUE"""),"575-92003") -> 575-92003 | C17: =IFERROR(__xludf.DUMMYFUNCTION("""COMPUTED_VALUE"""),"575-92003") -> 575-92003
A18: =IFERROR(__xludf.DUMMYFUNCTION("""COMPUTED_VALUE"""),20.0) -> 20 | B18: =IFERROR(__xludf.DUMMYFUNCTION("""COMPUTED_VALUE"""),"575-92006") -> 575-92006 | C18: =IFERROR(__xludf.DUMMYFUNCTION("""COMPUTED_VALUE"""),"575-92006") -> 575-92006
A19: =IFERROR(__xludf.DUMMYFUNCTION("""COMPUTED_VALUE"""),10.0) -> 10 | B19: =IFERROR(__xludf.DUMMYFUNCTION("""COMPUTED_VALUE"""),"575-92011") -> 575-92011 | C19: =IFERROR(__xludf.DUMMYFUNCTION("""COMPUTED_VALUE"""),"575-92011") -> 575-92011
A20: =IFERROR(__xludf.DUMMYFUNCTION("""COMPUTED_VALUE"""),100.0) -> 100 | B20: =IFERROR(__xludf.DUMMYFUNCTION("""COMPUTED_VALUE"""),"575-95001") -> 575-95001 | C20: =IFERROR(__xludf.DUMMYFUNCTION("""COMPUTED_VALUE"""),"575-95001") -> 575-95001
A21: =IFERROR(__xludf.DUMMYFUNCTION("""COMPUTED_VALUE"""),100.0) -> 100 | B21: =IFERROR(__xludf.DUMMYFUNCTION("""COMPUTED_VALUE"""),"575-95002") -> 575-95002 | C21: =IFERROR(__xludf.DUMMYFUNCTION("""COMPUTED_VALUE"""),"575-95002") -> 575-95002
A22: =IFERROR(__xludf.DUMMYFUNCTION("""COMPUTED_VALUE"""),100.0) -> 100 | B22: =IFERROR(__xludf.DUMMYFUNCTION("""COMPUTED_VALUE"""),"575-95003") -> 575-95003 | C22: =IFERROR(__xludf.DUMMYFUNCTION("""COMPUTED_VALUE"""),"575-95003") -> 575-95003
A23: =IFERROR(__xludf.DUMMYFUNCTION("""COMPUTED_VALUE"""),100.0) -> 100 | B23: =IFERROR(__xludf.DUMMYFUNCTION("""COMPUTED_VALUE"""),"575-95004") -> 575-95004 | C23: =IFERROR(__xludf.DUMMYFUNCTION("""COMPUTED_VALUE"""),"575-95004") -> 575-95004
A24: =IFERROR(__xludf.DUMMYFUNCTION("""COMPUTED_VALUE"""),2.0) -> 2 | B24: =IFERROR(__xludf.DUMMYFUNCTION("""COMPUTED_VALUE"""),"H25-FS-R2C") -> H25-FS-R2C | C24: =IFERROR(__xludf.DUMMYFUNCTION("""COMPUTED_VALUE"""),"H25-FS-R2C") -> H25-FS-R2C
A25: =IFERROR(__xludf.DUMMYFUNCTION("""COMPUTED_VALUE"""),10.0) -> 10 | B25: =IFERROR(__xludf.DUMMYFUNCTION("""COMPUTED_VALUE"""),"H25-FS-R3N") -> H25-FS-R3N | C25: =IFERROR(__xludf.DUMMYFUNCTION("""COMPUTED_VALUE"""),"H25-FS-R3N") -> H25-FS-R3N
A26: =IFERROR(__xludf.DUMMYFUNCTION("""COMPUTED_VALUE"""),15.0) -> 15 | B26: =IFERROR(__xludf.DUMMYFUNCTION("""COMPUTED_VALUE"""),"H25-SE") -> H25-SE | C26: =IFERROR(__xludf.DUMMYFUNCTION("""COMPUTED_VALUE"""),"H25-SE") -> H25-SE
A27: =IFERROR(__xludf.DUMMYFUNCTION("""COMPUTED_VALUE"""),2.0) -> 2 | B27: =IFERROR(__xludf.DUMMYFUNCTION("""COMPUTED_VALUE"""),"H25V-FE-10") -> H25V-FE-10 | C27: =IFERROR(__xludf.DUMMYFUNCTION("""COMPUTED_VALUE"""),"H25V-FE-10") -> H25V-FE-10
A28: =IFERROR(__xludf.DUMMYFUNCTION("""COMPUTED_VALUE"""),20.0) -> 20 | B28: =IFERROR(__xludf.DUMMYFUNCTION("""COMPUTED_VALUE"""),"575-01910") -> 575-01910 | C28: =IFERROR(__xludf.DUMMYFUNCTION("""COMPUTED_VALUE"""),"575-01910") -> 575-01910
C29: =IFERROR(__xludf.DUMMYFUNCTION("""COMPUTED_VALUE"""),"")
C30: =IFERROR(__xludf.DUMMYFUNCTION("""COMPUTED_VALUE"""),"")
C31: =IFERROR(__xludf.DUMMYFUNCTION("""COMPUTED_VALUE"""),"")
C32: =IFERROR(__xludf.DUMMYFUNCTION("""COMPUTED_VALUE"""),"")
C33: =IFERROR(__xludf.DUMMYFUNCTION("""COMPUTED_VALUE"""),"")
C34: =IFERROR(__xludf.DUMMYFUNCTION("""COMPUTED_VALUE"""),"")
C35: =IFERROR(__xludf.DUMMYFUNCTION("""COMPUTED_VALUE"""),"")
C36: =IFERROR(__xludf.DUMMYFUNCTION("""COMPUTED_VALUE"""),"")
C37: =IFERROR(__xludf.DUMMYFUNCTION("""COMPUTED_VALUE"""),"")
C38: =IFERROR(__xludf.DUMMYFUNCTION("""COMPUTED_VALUE"""),"")
C39: =IFERROR(__xludf.DUMMYFUNCTION("""COMPUTED_VALUE"""),"")
C40: =IFERROR(__xludf.DUMMYFUNCTION("""COMPUTED_VALUE"""),"")
... C351: =IFERROR(__xludf.DUMMYFUNCTION("""COMPUTED_VALUE"""),"")

Sheet INVOICE BGN
C1: INVOICE
C3: No.0000000501/29.05.2025
B5: Custumer: | D5: Seller:
D6: AMCI AD
B7: Advanced Micro Controls Incorporated | D7: 14 Lubata str.
B8: 20 Gear Drive, Plymouth Industrial Park | D8: Sofia 1407,Bulgaria
B9: CT 06786-24, Terryville , USA | D9: BG130316090
A12: # | B12: Item No | C12: Description | D12: Qty | E12: HTS Code | F12: Unit cost | G12: Amount | H12: Aluminum Content Value | I12: Aluminum Content weight percentage | J12: Country of Smelt &Cast of Aluminum
J13: AL type 1 | K13: Weight | L13: Price | M13: AL type 1 | N13: Weight | O13: Price | P13: AL type 1 | Q13: Weight | R13: Price
A14: 1 | C14: =if(B14="","", VLOOKUP(B14,'Номенклатура'!A$3:B997,2,false)) | D14: 75 | E14: =if(B14="","", VLOOKUP(B14,'Данни'!A:D,4,false)) | F14: =if(B14="","", VLOOKUP(B14,'Данни'!A:D,3,false)) | G14: =D14*F14 -> 0 | H14: =IFerror(VLOOKUP(B14,'Номенклатура'!A:F,4,0),"") | I14: =iferror(VLOOKUP(B14,'Номенклатура'!A:F,5,0),"") | J14: =iferror(VLOOKUP(B14,'Номенклатура'!A:N,6,0),"") | K14: =iferror(VLOOKUP(B14,'Номенклатура'!A:N,7,0),"") | L14: =IFERROR(VLOOKUP(B14,'Номенклатура'!A:N,8,0),"") | M14: =IFERROR(VLOOKUP(B14,'Номенклатура'!A:N,9,0),"") | N14: =IFERROR(VLOOKUP(B15,'Номенклатура'!A:N,10,0),"") | O14: =IFERROR(VLOOKUP(B14,'Номенклатура'!A:N,11,0),"") | P14: =IFERROR(VLOOKUP(B14,'Номенклатура'!A:N,12,0),"") | Q14: =IFERROR(VLOOKUP(B14,'Номенклатура'!A:N,13,0),"") | R14: =IFERROR(VLOOKUP(B14,'Номенклатура'!A:N,14,0),"")
A15: 2 | B15: 211447000 | C15: =if(B15="","", VLOOKUP(B15,'Номенклатура'!A$3:B997,2,false)) -> #N/A | D15: 15 | E15: =if(B15="","", VLOOKUP(B15,'Данни'!A:D,4,false)) -> #N/A | F15: =if(B15="","", VLOOKUP(B15,'Данни'!A:D,3,false)) -> #N/A | G15: =D15*F15 -> #N/A | H15: =IFerror(VLOOKUP(B15,'Номенклатура'!A:F,4,0),"") | I15: =iferror(VLOOKUP(B15,'Номенклатура'!A:F,5,0),"") | J15: =iferror(VLOOKUP(B15,'Номенклатура'!A:N,6,0),"") | K15: =iferror(VLOOKUP(B15,'Номенклатура'!A:N,7,0),"") | L15: =IFERROR(VLOOKUP(B15,'Номенклатура'!A:N,8,0),"") | M15: =IFERROR(VLOOKUP(B15,'Номенклатура'!A:N,9,0),"") | N15: =IFERROR(VLOOKUP(B16,'Номенклатура'!A:N,10,0),"") | O15: =IFERROR(VLOOKUP(B15,'Номенклатура'!A:N,11,0),"") | P15: =IFERROR(VLOOKUP(B15,'Номенклатура'!A:N,12,0),"") | Q15: =IFERROR(VLOOKUP(B15,'Номенклатура'!A:N,13,0),"") | R15: =IFERROR(VLOOKUP(B15,'Номенклатура'!A:N,14,0),"")
A16: 3 | C16: =if(B16="","", VLOOKUP(B16,'Номенклатура'!A$3:B997,2,false)) | D16: 20 | E16: =if(B16="","", VLOOKUP(B16,'Данни'!A:D,4,false)) | F16: =if(B16="","", VLOOKUP(B16,'Данни'!A:D,3,false)) | G16: =D16*F16 -> 0 | H16: =IFerror(VLOOKUP(B16,'Номенклатура'!A:F,4,0),"") | I16: =iferror(VLOOKUP(B16,'Номенклатура'!A:F,5,0),"") | J16: =iferror(VLOOKUP(B16,'Номенклатура'!A:N,6,0),"") | K16: =iferror(VLOOKUP(B16,'Номенклатура'!A:N,7,0),"") | L16: =IFERROR(VLOOKUP(B16,'Номенклатура'!A:N,8,0),"") | M16: =IFERROR(VLOOKUP(B16,'Номенклатура'!A:N,9,0),"") | N16: =IFERROR(VLOOKUP(B17,'Номенклатура'!A:N,10,0),"") | O16: =IFERROR(VLOOKUP(B16,'Номенклатура'!A:N,11,0),"") | P16: =IFERROR(VLOOKUP(B16,'Номенклатура'!A:N,12,0),"") | Q16: =IFERROR(VLOOKUP(B16,'Номенклатура'!A:N,13,0),"") | R16: =IFERROR(VLOOKUP(B16,'Номенклатура'!A:N,14,0),"")
A17: 4 | C17: =if(B17="","", VLOOKUP(B17,'Номенклатура'!A$3:B997,2,false)) | D17: 25 | E17: =if(B17="","", VLOOKUP(B17,'Данни'!A:D,4,false)) | F17: =if(B17="","", VLOOKUP(B17,'Данни'!A:D,3,false)) | G17: =D17*F17 -> 0 | H17: =IFerror(VLOOKUP(B17,'Номенклатура'!A:F,4,0),"") | I17: =iferror(VLOOKUP(B17,'Номенклатура'!A:F,5,0),"") | J17: =iferror(VLOOKUP(B17,'Номенклатура'!A:N,6,0),"") | K17: =iferror(VLOOKUP(B17,'Номенклатура'!A:N,7,0),"") | L17: =IFERROR(VLOOKUP(B17,'Номенклатура'!A:N,8,0),"") | M17: =IFERROR(VLOOKUP(B17,'Номенклатура'!A:N,9,0),"") | N17: =IFERROR(VLOOKUP(B18,'Номенклатура'!A:N,10,0),"") | O17: =IFERROR(VLOOKUP(B17,'Номенклатура'!A:N,11,0),"") | P17: =IFERROR(VLOOKUP(B17,'Номенклатура'!A:N,12,0),"") | Q17: =IFERROR(VLOOKUP(B17,'Номенклатура'!A:N,13,0),"") | R17: =IFERROR(VLOOKUP(B17,'Номенклатура'!A:N,14,0),"")
A18: 5 | C18: =if(B18="","", VLOOKUP(B18,'Номенклатура'!A$3:B997,2,false)) | D18: 25 | E18: =if(B18="","", VLOOKUP(B18,'Данни'!A:D,4,false)) | F18: =if(B18="","", VLOOKUP(B18,'Данни'!A:D,3,false)) | G18: =D18*F18 -> 0 | H18: =IFerror(VLOOKUP(B18,'Номенклатура'!A:F,4,0),"") | I18: =iferror(VLOOKUP(B18,'Номенклатура'!A:F,5,0),"") | J18: =iferror(VLOOKUP(B18,'Номенклатура'!A:N,6,0),"") | K18: =iferror(VLOOKUP(B18,'Номенклатура'!A:N,7,0),"") | L18: =IFERROR(VLOOKUP(B18,'Номенклатура'!A:N,8,0),"") | M18: =IFERROR(VLOOKUP(B18,'Номенклатура'!A:N,9,0),"") | N18: =IFERROR(VLOOKUP(B19,'Номенклатура'!A:N,10,0),"") | O18: =IFERROR(VLOOKUP(B18,'Номенклатура'!A:N,11,0),"") | P18: =IFERROR(VLOOKUP(B18,'Номенклатура'!A:N,12,0),"") | Q18: =IFERROR(VLOOKUP(B18,'Номенклатура'!A:N,13,0),"") | R18: =IFERROR(VLOOKUP(B18,'Номенклатура'!A:N,14,0),"")
A19: 6 | C19: =if(B19="","", VLOOKUP(B19,'Номенклатура'!A$3:B997,2,false)) | D19: 25 | E19: =if(B19="","", VLOOKUP(B19,'Данни'!A:D,4,false)) | F19: =if(B19="","", VLOOKUP(B19,'Данни'!A:D,3,false)) | G19: =D19*F19 -> 0 | H19: =IFerror(VLOOKUP(B19,'Номенклатура'!A:F,4,0),"") | I19: =iferror(VLOOKUP(B19,'Номенклатура'!A:F,5,0),"") | J19: =iferror(VLOOKUP(B19,'Номенклатура'!A:N,6,0),"") | K19: =iferror(VLOOKUP(B19,'Номенклатура'!A:N,7,0),"") | L19: =IFERROR(VLOOKUP(B19,'Номенклатура'!A:N,8,0),"") | M19: =IFERROR(VLOOKUP(B19,'Номенклатура'!A:N,9,0),"") | N19: =IFERROR(VLOOKUP(B20,'Номенклатура'!A:N,10,0),"") | O19: =IFERROR(VLOOKUP(B19,'Номенклатура'!A:N,11,0),"") | P19: =IFERROR(VLOOKUP(B19,'Номенклатура'!A:N,12,0),"") | Q19: =IFERROR(VLOOKUP(B19,'Номенклатура'!A:N,13,0),"") | R19: =IFERROR(VLOOKUP(B19,'Номенклатура'!A:N,14,0),"")
A20: 7 | C20: =if(B20="","", VLOOKUP(B20,'Номенклатура'!A$3:B997,2,false)) | D20: 25 | E20: =if(B20="","", VLOOKUP(B20,'Данни'!A:D,4,false)) | F20: =if(B20="","", VLOOKUP(B20,'Данни'!A:D,3,false)) | G20: =D20*F20 -> 0 | H20: =IFerror(VLOOKUP(B20,'Номенклатура'!A:F,4,0),"") | I20: =iferror(VLOOKUP(B20,'Номенклатура'!A:F,5,0),"") | J20: =iferror(VLOOKUP(B20,'Номенклатура'!A:N,6,0),"") | K20: =iferror(VLOOKUP(B20,'Номенклатура'!A:N,7,0),"") | L20: =IFERROR(VLOOKUP(B20,'Номенклатура'!A:N,8,0),"") | M20: =IFERROR(VLOOKUP(B20,'Номенклатура'!A:N,9,0),"") | N20: =IFERROR(VLOOKUP(B21,'Номенклатура'!A:N,10,0),"") | O20: =IFERROR(VLOOKUP(B20,'Номенклатура'!A:N,11,0),"") | P20: =IFERROR(VLOOKUP(B20,'Номенклатура'!A:N,12,0),"") | Q20: =IFERROR(VLOOKUP(B20,'Номенклатура'!A:N,13,0),"") | R20: =IFERROR(VLOOKUP(B20,'Номенклатура'!A:N,14,0),"")
A21: 8 | C21: =if(B21="","", VLOOKUP(B21,'Номенклатура'!A$3:B997,2,false)) | D21: 60 | E21: =if(B21="","", VLOOKUP(B21,'Данни'!A:D,4,false)) | F21: =if(B21="","", VLOOKUP(B21,'Данни'!A:D,3,false)) | G21: =D21*F21 -> 0 | H21: =IFerror(VLOOKUP(B21,'Номенклатура'!A:F,4,0),"") | I21: =iferror(VLOOKUP(B21,'Номенклатура'!A:F,5,0),"") | J21: =iferror(VLOOKUP(B21,'Номенклатура'!A:N,6,0),"") | K21: =iferror(VLOOKUP(B21,'Номенклатура'!A:N,7,0),"") | L21: =IFERROR(VLOOKUP(B21,'Номенклатура'!A:N,8,0),"") | M21: =IFERROR(VLOOKUP(B21,'Номенклатура'!A:N,9,0),"") | N21: =IFERROR(VLOOKUP(B22,'Номенклатура'!A:N,10,0),"") | O21: =IFERROR(VLOOKUP(B21,'Номенклатура'!A:N,11,0),"") | P21: =IFERROR(VLOOKUP(B21,'Номенклатура'!A:N,12,0),"") | Q21: =IFERROR(VLOOKUP(B21,'Номенклатура'!A:N,13,0),"") | R21: =IFERROR(VLOOKUP(B21,'Номенклатура'!A:N,14,0),"")
A22: 9 | C22: =if(B22="","", VLOOKUP(B22,'Номенклатура'!A$3:B997,2,false)) | D22: 120 | E22: =if(B22="","", VLOOKUP(B22,'Данни'!A:D,4,false)) | F22: =if(B22="","", VLOOKUP(B22,'Данни'!A:D,3,false)) | G22: =D22*F22 -> 0 | H22: =IFerror(VLOOKUP(B22,'Номенклатура'!A:F,4,0),"") | I22: =iferror(VLOOKUP(B22,'Номенклатура'!A:F,5,0),"") | J22: =iferror(VLOOKUP(B22,'Номенклатура'!A:N,6,0),"") | K22: =iferror(VLOOKUP(B22,'Номенклатура'!A:N,7,0),"") | L22: =IFERROR(VLOOKUP(B22,'Номенклатура'!A:N,8,0),"") | M22: =IFERROR(VLOOKUP(B22,'Номенклатура'!A:N,9,0),"") | N22: =IFERROR(VLOOKUP(B23,'Номенклатура'!A:N,10,0),"") | O22: =IFERROR(VLOOKUP(B22,'Номенклатура'!A:N,11,0),"") | P22: =IFERROR(VLOOKUP(B22,'Номенклатура'!A:N,12,0),"") | Q22: =IFERROR(VLOOKUP(B22,'Номенклатура'!A:N,13,0),"") | R22: =IFERROR(VLOOKUP(B22,'Номенклатура'!A:N,14,0),"")
A23: 10 | C23: =if(B23="","", VLOOKUP(B23,'Номенклатура'!A$3:B997,2,false)) | D23: 90 | E23: =if(B23="","", VLOOKUP(B23,'Данни'!A:D,4,false)) | F23: =if(B23="","", VLOOKUP(B23,'Данни'!A:D,3,false)) | G23: =D23*F23 -> 0 | H23: =IFerror(VLOOKUP(B23,'Номенклатура'!A:F,4,0),"") | I23: =iferror(VLOOKUP(B23,'Номенклатура'!A:F,5,0),"") | J23: =iferror(VLOOKUP(B23,'Номенклатура'!A:N,6,0),"") | K23: =iferror(VLOOKUP(B23,'Номенклатура'!A:N,7,0),"") | L23: =IFERROR(VLOOKUP(B23,'Номенклатура'!A:N,8,0),"") | M23: =IFERROR(VLOOKUP(B23,'Номенклатура'!A:N,9,0),"") | N23: =IFERROR(VLOOKUP(B24,'Номенклатура'!A:N,10,0),"") | O23: =IFERROR(VLOOKUP(B23,'Номенклатура'!A:N,11,0),"") | P23: =IFERROR(VLOOKUP(B23,'Номенклатура'!A:N,12,0),"") | Q23: =IFERROR(VLOOKUP(B23,'Номенклатура'!A:N,13,0),"") | R23: =IFERROR(VLOOKUP(B23,'Номенклатура'!A:N,14,0),"")
A24: 11 | C24: =if(B24="","", VLOOKUP(B24,'Номенклатура'!A$3:B997,2,false)) | D24: 25 | E24: =if(B24="","", VLOOKUP(B24,'Данни'!A:D,4,false)) | F24: =if(B24="","", VLOOKUP(B24,'Данни'!A:D,3,false)) | G24: =D24*F24 -> 0 | H24: =IFerror(VLOOKUP(B24,'Номенклатура'!A:F,4,0),"") | I24: =iferror(VLOOKUP(B24,'Номенклатура'!A:F,5,0),"") | J24: =iferror(VLOOKUP(B24,'Номенклатура'!A:N,6,0),"") | K24: =iferror(VLOOKUP(B24,'Номенклатура'!A:N,7,0),"") | L24: =IFERROR(VLOOKUP(B24,'Номенклатура'!A:N,8,0),"") | M24: =IFERROR(VLOOKUP(B24,'Номенклатура'!A:N,9,0),"") | N24: =IFERROR(VLOOKUP(B25,'Номенклатура'!A:N,10,0),"") | O24: =IFERROR(VLOOKUP(B24,'Номенклатура'!A:N,11,0),"") | P24: =IFERROR(VLOOKUP(B24,'Номенклатура'!A:N,12,0),"") | Q24: =IFERROR(VLOOKUP(B24,'Номенклатура'!A:N,13,0),"") | R24: =IFERROR(VLOOKUP(B24,'Номенклатура'!A:N,14,0),"")
A25: 12 | C25: =if(B25="","", VLOOKUP(B25,'Номенклатура'!A$3:B997,2,false)) | D25: 35 | E25: =if(B25="","", VLOOKUP(B25,'Данни'!A:D,4,false)) | F25: =if(B25="","", VLOOKUP(B25,'Данни'!A:D,3,false)) | G25: =D25*F25 -> 0 | H25: =IFerror(VLOOKUP(B25,'Номенклатура'!A:F,4,0),"") | I25: =iferror(VLOOKUP(B25,'Номенклатура'!A:F,5,0),"") | J25: =iferror(VLOOKUP(B25,'Номенклатура'!A:N,6,0),"") | K25: =iferror(VLOOKUP(B25,'Номенклатура'!A:N,7,0),"") | L25: =IFERROR(VLOOKUP(B25,'Номенклатура'!A:N,8,0),"") | M25: =IFERROR(VLOOKUP(B25,'Номенклатура'!A:N,9,0),"") | N25: =IFERROR(VLOOKUP(B26,'Номенклатура'!A:N,10,0),"") | O25: =IFERROR(VLOOKUP(B25,'Номенклатура'!A:N,11,0),"") | P25: =IFERROR(VLOOKUP(B25,'Номенклатура'!A:N,12,0),"") | Q25: =IFERROR(VLOOKUP(B25,'Номенклатура'!A:N,13,0),"") | R25: =IFERROR(VLOOKUP(B25,'Номенклатура'!A:N,14,0),"")
A26: 13 | C26: =if(B26="","", VLOOKUP(B26,'Номенклатура'!A$3:B997,2,false)) | D26: 25 | E26: =if(B26="","", VLOOKUP(B26,'Данни'!A:D,4,false)) | F26: =if(B26="","", VLOOKUP(B26,'Данни'!A:D,3,false)) | G26: =D26*F26 -> 0 | H26: =IFerror(VLOOKUP(B26,'Номенклатура'!A:F,4,0),"") | I26: =iferror(VLOOKUP(B26,'Номенклатура'!A:F,5,0),"") | J26: =iferror(VLOOKUP(B26,'Номенклатура'!A:N,6,0),"") | K26: =iferror(VLOOKUP(B26,'Номенклатура'!A:N,7,0),"") | L26: =IFERROR(VLOOKUP(B26,'Номенклатура'!A:N,8,0),"") | M26: =IFERROR(VLOOKUP(B26,'Номенклатура'!A:N,9,0),"") | N26: =IFERROR(VLOOKUP(B27,'Номенклатура'!A:N,10,0),"") | O26: =IFERROR(VLOOKUP(B26,'Номенклатура'!A:N,11,0),"") | P26: =IFERROR(VLOOKUP(B26,'Номенклатура'!A:N,12,0),"") | Q26: =IFERROR(VLOOKUP(B26,'Номенклатура'!A:N,13,0),"") | R26: =IFERROR(VLOOKUP(B26,'Номенклатура'!A:N,14,0),"")
A27: 14 | C27: =if(B27="","", VLOOKUP(B27,'Номенклатура'!A$3:B997,2,false)) | D27: 20 | E27: =if(B27="","", VLOOKUP(B27,'Данни'!A:D,4,false)) | F27: =if(B27="","", VLOOKUP(B27,'Данни'!A:D,3,false)) | G27: =D27*F27 -> 0 | H27: =IFerror(VLOOKUP(B27,'Номенклатура'!A:F,4,0),"") | I27: =iferror(VLOOKUP(B27,'Номенклатура'!A:F,5,0),"") | J27: =iferror(VLOOKUP(B27,'Номенклатура'!A:N,6,0),"") | K27: =iferror(VLOOKUP(B27,'Номенклатура'!A:N,7,0),"") | L27: =IFERROR(VLOOKUP(B27,'Номенклатура'!A:N,8,0),"") | M27: =IFERROR(VLOOKUP(B27,'Номенклатура'!A:N,9,0),"") | N27: =IFERROR(VLOOKUP(B28,'Номенклатура'!A:N,10,0),"") | O27: =IFERROR(VLOOKUP(B27,'Номенклатура'!A:N,11,0),"") | P27: =IFERROR(VLOOKUP(B27,'Номенклатура'!A:N,12,0),"") | Q27: =IFERROR(VLOOKUP(B27,'Номенклатура'!A:N,13,0),"") | R27: =IFERROR(VLOOKUP(B27,'Номенклатура'!A:N,14,0),"")
A28: 15 | C28: =if(B28="","", VLOOKUP(B28,'Номенклатура'!A$3:B997,2,false)) | D28: 20 | E28: =if(B28="","", VLOOKUP(B28,'Данни'!A:D,4,false)) | F28: =if(B28="","", VLOOKUP(B28,'Данни'!A:D,3,false)) | G28: =D28*F28 -> 0 | H28: =IFerror(VLOOKUP(B28,'Номенклатура'!A:F,4,0),"") | I28: =iferror(VLOOKUP(B28,'Номенклатура'!A:F,5,0),"") | J28: =iferror(VLOOKUP(B28,'Номенклатура'!A:N,6,0),"") | K28: =iferror(VLOOKUP(B28,'Номенклатура'!A:N,7,0),"") | L28: =IFERROR(VLOOKUP(B28,'Номенклатура'!A:N,8,0),"") | M28: =IFERROR(VLOOKUP(B28,'Номенклатура'!A:N,9,0),"") | N28: =IFERROR(VLOOKUP(B29,'Номенклатура'!A:N,10,0),"") | O28: =IFERROR(VLOOKUP(B28,'Номенклатура'!A:N,11,0),"") | P28: =IFERROR(VLOOKUP(B28,'Номенклатура'!A:N,12,0),"") | Q28: =IFERROR(VLOOKUP(B28,'Номенклатура'!A:N,13,0),"") | R28: =IFERROR(VLOOKUP(B28,'Номенклатура'!A:N,14,0),"")
A29: 16 | C29: =if(B29="","", VLOOKUP(B29,'Номенклатура'!A$3:B997,2,false)) | D29: 15 | E29: =if(B29="","", VLOOKUP(B29,'Данни'!A:D,4,false)) | F29: =if(B29="","", VLOOKUP(B29,'Данни'!A:D,3,false)) | G29: =D29*F29 -> 0 | H29: =IFerror(VLOOKUP(B29,'Номенклатура'!A:F,4,0),"") | I29: =iferror(VLOOKUP(B29,'Номенклатура'!A:F,5,0),"") | J29: =iferror(VLOOKUP(B29,'Номенклатура'!A:N,6,0),"") | K29: =iferror(VLOOKUP(B29,'Номенклатура'!A:N,7,0),"") | L29: =IFERROR(VLOOKUP(B29,'Номенклатура'!A:N,8,0),"") | M29: =IFERROR(VLOOKUP(B29,'Номенклатура'!A:N,9,0),"") | N29: =IFERROR(VLOOKUP(B30,'Номенклатура'!A:N,10,0),"") | O29: =IFERROR(VLOOKUP(B29,'Номенклатура'!A:N,11,0),"") | P29: =IFERROR(VLOOKUP(B29,'Номенклатура'!A:N,12,0),"") | Q29: =IFERROR(VLOOKUP(B29,'Номенклатура'!A:N,13,0),"") | R29: =IFERROR(VLOOKUP(B29,'Номенклатура'!A:N,14,0),"")
A30: 17 | C30: =if(B30="","", VLOOKUP(B30,'Номенклатура'!A$3:B997,2,false)) | E30: =if(B30="","", VLOOKUP(B30,'Данни'!A:D,4,false)) | F30: =if(B30="","", VLOOKUP(B30,'Данни'!A:D,3,false)) | G30: =D30*F30 -> 0 | H30: =IFerror(VLOOKUP(B30,'Номенклатура'!A:F,4,0),"") | I30: =iferror(VLOOKUP(B30,'Номенклатура'!A:F,5,0),"") | J30: =iferror(VLOOKUP(B30,'Номенклатура'!A:N,6,0),"") | K30: =iferror(VLOOKUP(B30,'Номенклатура'!A:N,7,0),"") | L30: =IFERROR(VLOOKUP(B30,'Номенклатура'!A:N,8,0),"") | M30: =IFERROR(VLOOKUP(B30,'Номенклатура'!A:N,9,0),"") | N30: =IFERROR(VLOOKUP(B31,'Номенклатура'!A:N,10,0),"") | O30: =IFERROR(VLOOKUP(B30,'Номенклатура'!A:N,11,0),"") | P30: =IFERROR(VLOOKUP(B30,'Номенклатура'!A:N,12,0),"") | Q30: =IFERROR(VLOOKUP(B30,'Номенклатура'!A:N,13,0),"") | R30: =IFERROR(VLOOKUP(B30,'Номенклатура'!A:N,14,0),"")
A31: 18 | C31: =if(B31="","", VLOOKUP(B31,'Номенклатура'!A$3:B997,2,false)) | E31: =if(B31="","", VLOOKUP(B31,'Данни'!A:D,4,false)) | F31: =if(B31="","", VLOOKUP(B31,'Данни'!A:D,3,false)) | G31: =D31*F31 -> 0 | H31: =IFerror(VLOOKUP(B31,'Номенклатура'!A:F,4,0),"") | I31: =iferror(VLOOKUP(B31,'Номенклатура'!A:F,5,0),"") | J31: =iferror(VLOOKUP(B31,'Номенклатура'!A:N,6,0),"") | K31: =iferror(VLOOKUP(B31,'Номенклатура'!A:N,7,0),"") | L31: =IFERROR(VLOOKUP(B31,'Номенклатура'!A:N,8,0),"") | M31: =IFERROR(VLOOKUP(B31,'Номенклатура'!A:N,9,0),"") | N31: =IFERROR(VLOOKUP(B32,'Номенклатура'!A:N,10,0),"") | O31: =IFERROR(VLOOKUP(B31,'Номенклатура'!A:N,11,0),"") | P31: =IFERROR(VLOOKUP(B31,'Номенклатура'!A:N,12,0),"") | Q31: =IFERROR(VLOOKUP(B31,'Номенклатура'!A:N,13,0),"") | R31: =IFERROR(VLOOKUP(B31,'Номенклатура'!A:N,14,0),"")
A32: 19 | C32: =if(B32="","", VLOOKUP(B32,'Номенклатура'!A$3:B997,2,false)) | E32: =if(B32="","", VLOOKUP(B32,'Данни'!A:D,4,false)) | F32: =if(B32="","", VLOOKUP(B32,'Данни'!A:D,3,false)) | G32: =D32*F32 -> 0 | H32: =IFerror(VLOOKUP(B32,'Номенклатура'!A:F,4,0),"") | I32: =iferror(VLOOKUP(B32,'Номенклатура'!A:F,5,0),"") | J32: =iferror(VLOOKUP(B32,'Номенклатура'!A:N,6,0),"") | K32: =iferror(VLOOKUP(B32,'Номенклатура'!A:N,7,0),"") | L32: =IFERROR(VLOOKUP(B32,'Номенклатура'!A:N,8,0),"") | M32: =IFERROR(VLOOKUP(B32,'Номенклатура'!A:N,9,0),"") | N32: =IFERROR(VLOOKUP(B33,'Номенклатура'!A:N,10,0),"") | O32: =IFERROR(VLOOKUP(B32,'Номенклатура'!A:N,11,0),"") | P32: =IFERROR(VLOOKUP(B32,'Номенклатура'!A:N,12,0),"") | Q32: =IFERROR(VLOOKUP(B32,'Номенклатура'!A:N,13,0),"") | R32: =IFERROR(VLOOKUP(B32,'Номенклатура'!A:N,14,0),"")
A33: 20 | C33: =if(B33="","", VLOOKUP(B33,'Номенклатура'!A$3:B997,2,false)) | E33: =if(B33="","", VLOOKUP(B33,'Данни'!A:D,4,false)) | F33: =if(B33="","", VLOOKUP(B33,'Данни'!A:D,3,false)) | G33: =D33*F33 -> 0 | H33: =IFerror(VLOOKUP(B33,'Номенклатура'!A:F,4,0),"") | I33: =iferror(VLOOKUP(B33,'Номенклатура'!A:F,5,0),"") | J33: =iferror(VLOOKUP(B33,'Номенклатура'!A:N,6,0),"") | K33: =iferror(VLOOKUP(B33,'Номенклатура'!A:N,7,0),"") | L33: =IFERROR(VLOOKUP(B33,'Номенклатура'!A:N,8,0),"") | M33: =IFERROR(VLOOKUP(B33,'Номенклатура'!A:N,9,0),"") | N33: =IFERROR(VLOOKUP(B34,'Номенклатура'!A:N,10,0),"") | O33: =IFERROR(VLOOKUP(B33,'Номенклатура'!A:N,11,0),"") | P33: =IFERROR(VLOOKUP(B33,'Номенклатура'!A:N,12,0),"") | Q33: =IFERROR(VLOOKUP(B33,'Номенклатура'!A:N,13,0),"") | R33: =IFERROR(VLOOKUP(B33,'Номенклатура'!A:N,14,0),"")
A34: 21 | F34: =if(B34="","", VLOOKUP(B34,'Данни'!A:D,3,false)) | G34: =D34*F34 -> 0 | H34: =IFerror(VLOOKUP(B34,'Номенклатура'!A:F,4,0),"") | I34: =iferror(VLOOKUP(B34,'Номенклатура'!A:F,5,0),"") | J34: =iferror(VLOOKUP(B34,'Номенклатура'!A:N,6,0),"") | K34: =iferror(VLOOKUP(B34,'Номенклатура'!A:N,7,0),"") | L34: =IFERROR(VLOOKUP(B34,'Номенклатура'!A:N,8,0),"") | M34: =IFERROR(VLOOKUP(B34,'Номенклатура'!A:N,9,0),"") | N34: =IFERROR(VLOOKUP(B35,'Номенклатура'!A:N,10,0),"") | O34: =IFERROR(VLOOKUP(B34,'Номенклатура'!A:N,11,0),"") | P34: =IFERROR(VLOOKUP(B34,'Номенклатура'!A:N,12,0),"") | Q34: =IFERROR(VLOOKUP(B34,'Номенклатура'!A:N,13,0),"") | R34: =IFERROR(VLOOKUP(B34,'Номенклатура'!A:N,14,0),"")
A35: 22 | E35: =if(B35="","", VLOOKUP(B35,'Данни'!A:D,4,false)) | F35: =if(B35="","", VLOOKUP(B35,'Данни'!A:D,3,false)) | G35: =D35*F35 -> 0 | H35: =IFerror(VLOOKUP(B35,'Номенклатура'!A:F,4,0),"") | I35: =iferror(VLOOKUP(B35,'Номенклатура'!A:F,5,0),"") | J35: =iferror(VLOOKUP(B35,'Номенклатура'!A:N,6,0),"") | K35: =iferror(VLOOKUP(B35,'Номенклатура'!A:N,7,0),"") | L35: =IFERROR(VLOOKUP(B35,'Номенклатура'!A:N,8,0),"") | M35: =IFERROR(VLOOKUP(B35,'Номенклатура'!A:N,9,0),"") | N35: =IFERROR(VLOOKUP(B36,'Номенклатура'!A:N,10,0),"") | O35: =IFERROR(VLOOKUP(B35,'Номенклатура'!A:N,11,0),"") | P35: =IFERROR(VLOOKUP(B35,'Номенклатура'!A:N,12,0),"") | Q35: =IFERROR(VLOOKUP(B35,'Номенклатура'!A:N,13,0),"") | R35: =IFERROR(VLOOKUP(B35,'Номенклатура'!A:N,14,0),"")
A36: 23 | E36: =if(B36="","", VLOOKUP(B36,'Данни'!A:D,4,false)) | F36: =if(B36="","", VLOOKUP(B36,'Данни'!A:D,3,false)) | G36: =D36*F36 -> 0 | H36: =IFerror(VLOOKUP(B36,'Номенклатура'!A:F,4,0),"") | I36: =iferror(VLOOKUP(B36,'Номенклатура'!A:F,5,0),"") | J36: =iferror(VLOOKUP(B36,'Номенклатура'!A:N,6,0),"") | K36: =iferror(VLOOKUP(B36,'Номенклатура'!A:N,7,0),"") | L36: =IFERROR(VLOOKUP(B36,'Номенклатура'!A:N,8,0),"") | M36: =IFERROR(VLOOKUP(B36,'Номенклатура'!A:N,9,0),"") | N36: =IFERROR(VLOOKUP(B39,'Номенклатура'!A:N,10,0),"") | O36: =IFERROR(VLOOKUP(B36,'Номенклатура'!A:N,11,0),"") | P36: =IFERROR(VLOOKUP(B36,'Номенклатура'!A:N,12,0),"") | Q36: =IFERROR(VLOOKUP(B36,'Номенклатура'!A:N,13,0),"") | R36: =IFERROR(VLOOKUP(B36,'Номенклатура'!A:N,14,0),"")
A37: 24 | E37: =if(B39="","", VLOOKUP(B39,'Данни'!A:D,4,false)) | F37: =if(B39="","", VLOOKUP(B39,'Данни'!A:D,3,false)) | G37: =D37*F37 -> 0 | H37: =IFerror(VLOOKUP(B39,'Номенклатура'!A:F,4,0),"") | I37: =iferror(VLOOKUP(B39,'Номенклатура'!A:F,5,0),"") | J37: =iferror(VLOOKUP(B39,'Номенклатура'!A:N,6,0),"") | K37: =iferror(VLOOKUP(B39,'Номенклатура'!A:N,7,0),"") | L37: =IFERROR(VLOOKUP(B39,'Номенклатура'!A:N,8,0),"") | M37: =IFERROR(VLOOKUP(B39,'Номенклатура'!A:N,9,0),"") | N37: =IFERROR(VLOOKUP(B40,'Номенклатура'!A:N,10,0),"") | O37: =IFERROR(VLOOKUP(B39,'Номенклатура'!A:N,11,0),"") | P37: =IFERROR(VLOOKUP(B39,'Номенклатура'!A:N,12,0),"") | Q37: =IFERROR(VLOOKUP(B39,'Номенклатура'!A:N,13,0),"") | R37: =IFERROR(VLOOKUP(B39,'Номенклатура'!A:N,14,0),"")
E38: =if(B40="","", VLOOKUP(B40,'Данни'!A:D,4,false)) | F38: =if(B40="","", VLOOKUP(B40,'Данни'!A:D,3,false)) | G38: =D38*F38 -> 0 | H38: =IFerror(VLOOKUP(B40,'Номенклатура'!A:F,4,0),"") | I38: =iferror(VLOOKUP(B40,'Номенклатура'!A:F,5,0),"") | J38: =iferror(VLOOKUP(B40,'Номенклатура'!A:N,6,0),"") | K38: =iferror(VLOOKUP(B40,'Номенклатура'!A:N,7,0),"") | L38: =IFERROR(VLOOKUP(B40,'Номенклатура'!A:N,8,0),"") | M38: =IFERROR(VLOOKUP(B40,'Номенклатура'!A:N,9,0),"") | N38: =IFERROR(VLOOKUP(B41,'Номенклатура'!A:N,10,0),"") | O38: =IFERROR(VLOOKUP(B40,'Номенклатура'!A:N,11,0),"") | P38: =IFERROR(VLOOKUP(B40,'Номенклатура'!A:N,12,0),"") | Q38: =IFERROR(VLOOKUP(B40,'Номенклатура'!A:N,13,0),"") | R38: =IFERROR(VLOOKUP(B40,'Номенклатура'!A:N,14,0),"")
E39: =if(B41="","", VLOOKUP(B41,'Данни'!A:D,4,false)) | F39: =if(B41="","", VLOOKUP(B41,'Данни'!A:D,3,false)) | G39: =D39*F39 -> 0 | H39: =IFerror(VLOOKUP(B41,'Номенклатура'!A:F,4,0),"") | I39: =iferror(VLOOKUP(B41,'Номенклатура'!A:F,5,0),"") | J39: =iferror(VLOOKUP(B41,'Номенклатура'!A:N,6,0),"") | K39: =iferror(VLOOKUP(B41,'Номенклатура'!A:N,7,0),"") | L39: =IFERROR(VLOOKUP(B41,'Номенклатура'!A:N,8,0),"") | M39: =IFERROR(VLOOKUP(B41,'Номенклатура'!A:N,9,0),"") | N39: =IFERROR(VLOOKUP(B42,'Номенклатура'!A:N,10,0),"") | O39: =IFERROR(VLOOKUP(B41,'Номенклатура'!A:N,11,0),"") | P39: =IFERROR(VLOOKUP(B41,'Номенклатура'!A:N,12,0),"") | Q39: =IFERROR(VLOOKUP(B41,'Номенклатура'!A:N,13,0),"") | R39: =IFERROR(VLOOKUP(B41,'Номенклатура'!A:N,14,0),"")
A40: 27 | H40: =IFerror(VLOOKUP(B42,'Номенклатура'!A:F,4,0),"") | I40: =iferror(VLOOKUP(B42,'Номенклатура'!A:F,5,0),"") | J40: =iferror(VLOOKUP(B42,'Номенклатура'!A:N,6,0),"") | K40: =iferror(VLOOKUP(B42,'Номенклатура'!A:N,7,0),"") | L40: =IFERROR(VLOOKUP(B42,'Номенклатура'!A:N,8,0),"") | M40: =IFERROR(VLOOKUP(B42,'Номенклатура'!A:N,9,0),"") | N40: =IFERROR(VLOOKUP(B43,'Номенклатура'!A:N,10,0),"") | O40: =IFERROR(VLOOKUP(B42,'Номенклатура'!A:N,11,0),"") | P40: =IFERROR(VLOOKUP(B42,'Номенклатура'!A:N,12,0),"") | Q40: =IFERROR(VLOOKUP(B42,'Номенклатура'!A:N,13,0),"") | R40: =IFERROR(VLOOKUP(B42,'Номенклатура'!A:N,14,0),"")
A41: 28 | H41: =IFerror(VLOOKUP(B43,'Номенклатура'!A:F,4,0),"") | I41: =iferror(VLOOKUP(B43,'Номенклатура'!A:F,5,0),"") | J41: =iferror(VLOOKUP(B43,'Номенклатура'!A:N,6,0),"") | K41: =iferror(VLOOKUP(B43,'Номенклатура'!A:N,7,0),"") | L41: =IFERROR(VLOOKUP(B43,'Номенклатура'!A:N,8,0),"") | M41: =IFERROR(VLOOKUP(B43,'Номенклатура'!A:N,9,0),"") | N41: =IFERROR(VLOOKUP(B44,'Номенклатура'!A:N,10,0),"") | O41: =IFERROR(VLOOKUP(B43,'Номенклатура'!A:N,11,0),"") | P41: =IFERROR(VLOOKUP(B43,'Номенклатура'!A:N,12,0),"") | Q41: =IFERROR(VLOOKUP(B43,'Номенклатура'!A:N,13,0),"") | R41: =IFERROR(VLOOKUP(B43,'Номенклатура'!A:N,14,0),"")
A42: 29 | H42: =IFerror(VLOOKUP(B44,'Номенклатура'!A:F,4,0),"") | I42: =iferror(VLOOKUP(B44,'Номенклатура'!A:F,5,0),"") | J42: =iferror(VLOOKUP(B44,'Номенклатура'!A:N,6,0),"") | K42: =iferror(VLOOKUP(B44,'Номенклатура'!A:N,7,0),"") | L42: =IFERROR(VLOOKUP(B44,'Номенклатура'!A:N,8,0),"") | M42: =IFERROR(VLOOKUP(B44,'Номенклатура'!A:N,9,0),"") | N42: =IFERROR(VLOOKUP(B45,'Номенклатура'!A:N,10,0),"") | O42: =IFERROR(VLOOKUP(B44,'Номенклатура'!A:N,11,0),"") | P42: =IFERROR(VLOOKUP(B44,'Номенклатура'!A:N,12,0),"") | Q42: =IFERROR(VLOOKUP(B44,'Номенклатура'!A:N,13,0),"") | R42: =IFERROR(VLOOKUP(B44,'Номенклатура'!A:N,14,0),"")
A43: 30 | H43: =IFerror(VLOOKUP(B45,'Номенклатура'!A:F,4,0),"") | I43: =iferror(VLOOKUP(B45,'Номенклатура'!A:F,5,0),"") | J43: =iferror(VLOOKUP(B45,'Номенклатура'!A:N,6,0),"") | K43: =iferror(VLOOKUP(B45,'Номенклатура'!A:N,7,0),"") | L43: =IFERROR(VLOOKUP(B45,'Номенклатура'!A:N,8,0),"") | M43: =IFERROR(VLOOKUP(B45,'Номенклатура'!A:N,9,0),"") | N43: =IFERROR(VLOOKUP(B46,'Номенклатура'!A:N,10,0),"") | O43: =IFERROR(VLOOKUP(B45,'Номенклатура'!A:N,11,0),"") | P43: =IFERROR(VLOOKUP(B45,'Номенклатура'!A:N,12,0),"") | Q43: =IFERROR(VLOOKUP(B45,'Номенклатура'!A:N,13,0),"") | R43: =IFERROR(VLOOKUP(B45,'Номенклатура'!A:N,14,0),"")
A44: 31 | H44: =IFerror(VLOOKUP(B46,'Номенклатура'!A:F,4,0),"") | I44: =iferror(VLOOKUP(B46,'Номенклатура'!A:F,5,0),"") | J44: =iferror(VLOOKUP(B46,'Номенклатура'!A:N,6,0),"") | K44: =iferror(VLOOKUP(B46,'Номенклатура'!A:N,7,0),"") | L44: =IFERROR(VLOOKUP(B46,'Номенклатура'!A:N,8,0),"") | M44: =IFERROR(VLOOKUP(B46,'Номенклатура'!A:N,9,0),"") | N44: =IFERROR(VLOOKUP(B47,'Номенклатура'!A:N,10,0),"") | O44: =IFERROR(VLOOKUP(B46,'Номенклатура'!A:N,11,0),"") | P44: =IFERROR(VLOOKUP(B46,'Номенклатура'!A:N,12,0),"") | Q44: =IFERROR(VLOOKUP(B46,'Номенклатура'!A:N,13,0),"") | R44: =IFERROR(VLOOKUP(B46,'Номенклатура'!A:N,14,0),"")
A45: 32 | H45: =IFerror(VLOOKUP(B47,'Номенклатура'!A:F,4,0),"") | I45: =iferror(VLOOKUP(B47,'Номенклатура'!A:F,5,0),"") | J45: =iferror(VLOOKUP(B47,'Номенклатура'!A:N,6,0),"") | K45: =iferror(VLOOKUP(B47,'Номенклатура'!A:N,7,0),"") | L45: =IFERROR(VLOOKUP(B47,'Номенклатура'!A:N,8,0),"") | M45: =IFERROR(VLOOKUP(B47,'Номенклатура'!A:N,9,0),"") | N45: =IFERROR(VLOOKUP(B48,'Номенклатура'!A:N,10,0),"") | O45: =IFERROR(VLOOKUP(B47,'Номенклатура'!A:N,11,0),"") | P45: =IFERROR(VLOOKUP(B47,'Номенклатура'!A:N,12,0),"") | Q45: =IFERROR(VLOOKUP(B47,'Номенклатура'!A:N,13,0),"") | R45: =IFERROR(VLOOKUP(B47,'Номенклатура'!A:N,14,0),"")
A46: 33 | H46: =IFerror(VLOOKUP(B48,'Номенклатура'!A:F,4,0),"") | I46: =iferror(VLOOKUP(B48,'Номенклатура'!A:F,5,0),"") | J46: =iferror(VLOOKUP(B48,'Номенклатура'!A:N,6,0),"") | K46: =iferror(VLOOKUP(B48,'Номенклатура'!A:N,7,0),"") | L46: =IFERROR(VLOOKUP(B48,'Номенклатура'!A:N,8,0),"") | M46: =IFERROR(VLOOKUP(B48,'Номенклатура'!A:N,9,0),"") | N46: =IFERROR(VLOOKUP(B49,'Номенклатура'!A:N,10,0),"") | O46: =IFERROR(VLOOKUP(B48,'Номенклатура'!A:N,11,0),"") | P46: =IFERROR(VLOOKUP(B48,'Номенклатура'!A:N,12,0),"") | Q46: =IFERROR(VLOOKUP(B48,'Номенклатура'!A:N,13,0),"") | R46: =IFERROR(VLOOKUP(B48,'Номенклатура'!A:N,14,0),"")
A47: 34 | H47: =IFerror(VLOOKUP(B49,'Номенклатура'!A:F,4,0),"") | I47: =iferror(VLOOKUP(B49,'Номенклатура'!A:F,5,0),"") | J47: =iferror(VLOOKUP(B49,'Номенклатура'!A:N,6,0),"") | K47: =iferror(VLOOKUP(B49,'Номенклатура'!A:N,7,0),"") | L47: =IFERROR(VLOOKUP(B49,'Номенклатура'!A:N,8,0),"") | M47: =IFERROR(VLOOKUP(B49,'Номенклатура'!A:N,9,0),"") | N47: =IFERROR(VLOOKUP(#REF!,'Номенклатура'!A:N,10,0),"") | O47: =IFERROR(VLOOKUP(B49,'Номенклатура'!A:N,11,0),"") | P47: =IFERROR(VLOOKUP(B49,'Номенклатура'!A:N,12,0),"") | Q47: =IFERROR(VLOOKUP(B49,'Номенклатура'!A:N,13,0),"") | R47: =IFERROR(VLOOKUP(B49,'Номенклатура'!A:N,14,0),"")
A48: 35 | H48: =IFerror(VLOOKUP(#REF!,'Номенклатура'!A:F,4,0),"") | I48: =iferror(VLOOKUP(#REF!,'Номенклатура'!A:F,5,0),"") | J48: =iferror(VLOOKUP(#REF!,'Номенклатура'!A:N,6,0),"") | K48: =iferror(VLOOKUP(#REF!,'Номенклатура'!A:N,7,0),"") | L48: =IFERROR(VLOOKUP(#REF!,'Номенклатура'!A:N,8,0),"") | M48: =IFERROR(VLOOKUP(#REF!,'Номенклатура'!A:N,9,0),"") | N48: =IFERROR(VLOOKUP(#REF!,'Номенклатура'!A:N,10,0),"") | O48: =IFERROR(VLOOKUP(#REF!,'Номенклатура'!A:N,11,0),"") | P48: =IFERROR(VLOOKUP(#REF!,'Номенклатура'!A:N,12,0),"") | Q48: =IFERROR(VLOOKUP(#REF!,'Номенклатура'!A:N,13,0),"") | R48: =IFERROR(VLOOKUP(#REF!,'Номенклатура'!A:N,14,0),"")
A49: 36 | H49: =IFerror(VLOOKUP(#REF!,'Номенклатура'!A:F,4,0),"") | I49: =iferror(VLOOKUP(#REF!,'Номенклатура'!A:F,5,0),"") | J49: =iferror(VLOOKUP(#REF!,'Номенклатура'!A:N,6,0),"") | K49: =iferror(VLOOKUP(#REF!,'Номенклатура'!A:N,7,0),"") | L49: =IFERROR(VLOOKUP(#REF!,'Номенклатура'!A:N,8,0),"") | M49: =IFERROR(VLOOKUP(#REF!,'Номенклатура'!A:N,9,0),"") | N49: =IFERROR(VLOOKUP(B50,'Номенклатура'!A:N,10,0),"") | O49: =IFERROR(VLOOKUP(#REF!,'Номенклатура'!A:N,11,0),"") | P49: =IFERROR(VLOOKUP(#REF!,'Номенклатура'!A:N,12,0),"") | Q49: =IFERROR(VLOOKUP(#REF!,'Номенклатура'!A:N,13,0),"") | R49: =IFERROR(VLOOKUP(#REF!,'Номенклатура'!A:N,14,0),"")
A50: 37 | H50: =IFerror(VLOOKUP(B50,'Номенклатура'!A:F,4,0),"") | I50: =iferror(VLOOKUP(B50,'Номенклатура'!A:F,5,0),"") | J50: =iferror(VLOOKUP(B50,'Номенклатура'!A:N,6,0),"") | K50: =iferror(VLOOKUP(B50,'Номенклатура'!A:N,7,0),"") | L50: =IFERROR(VLOOKUP(B50,'Номенклатура'!A:N,8,0),"") | M50: =IFERROR(VLOOKUP(B50,'Номенклатура'!A:N,9,0),"") | N50: =IFERROR(VLOOKUP(B51,'Номенклатура'!A:N,10,0),"") | O50: =IFERROR(VLOOKUP(B50,'Номенклатура'!A:N,11,0),"") | P50: =IFERROR(VLOOKUP(B50,'Номенклатура'!A:N,12,0),"") | Q50: =IFERROR(VLOOKUP(B50,'Номенклатура'!A:N,13,0),"") | R50: =IFERROR(VLOOKUP(B50,'Номенклатура'!A:N,14,0),"")
A51: 38 | H51: =IFerror(VLOOKUP(B51,'Номенклатура'!A:F,4,0),"") | I51: =iferror(VLOOKUP(B51,'Номенклатура'!A:F,5,0),"") | J51: =iferror(VLOOKUP(B51,'Номенклатура'!A:N,6,0),"") | K51: =iferror(VLOOKUP(B51,'Номенклатура'!A:N,7,0),"") | L51: =IFERROR(VLOOKUP(B51,'Номенклатура'!A:N,8,0),"") | M51: =IFERROR(VLOOKUP(B51,'Номенклатура'!A:N,9,0),"") | N51: =IFERROR(VLOOKUP(B52,'Номенклатура'!A:N,10,0),"") | O51: =IFERROR(VLOOKUP(B51,'Номенклатура'!A:N,11,0),"") | P51: =IFERROR(VLOOKUP(B51,'Номенклатура'!A:N,12,0),"") | Q51: =IFERROR(VLOOKUP(B51,'Номенклатура'!A:N,13,0),"") | R51: =IFERROR(VLOOKUP(B51,'Номенклатура'!A:N,14,0),"")
A52: 39 | H52: =IFerror(VLOOKUP(B52,'Номенклатура'!A:F,4,0),"") | I52: =iferror(VLOOKUP(B52,'Номенклатура'!A:F,5,0),"") | J52: =iferror(VLOOKUP(B52,'Номенклатура'!A:N,6,0),"") | K52: =iferror(VLOOKUP(B52,'Номенклатура'!A:N,7,0),"") | L52: =IFERROR(VLOOKUP(B52,'Номенклатура'!A:N,8,0),"") | M52: =IFERROR(VLOOKUP(B52,'Номенклатура'!A:N,9,0),"") | N52: =IFERROR(VLOOKUP(B53,'Номенклатура'!A:N,10,0),"") | O52: =IFERROR(VLOOKUP(B52,'Номенклатура'!A:N,11,0),"") | P52: =IFERROR(VLOOKUP(B52,'Номенклатура'!A:N,12,0),"") | Q52: =IFERROR(VLOOKUP(B52,'Номенклатура'!A:N,13,0),"") | R52: =IFERROR(VLOOKUP(B52,'Номенклатура'!A:N,14,0),"")
A53: 40 | E53: =if(B53="","", VLOOKUP(B53,'Данни'!A:D,4,false)) | F53: =if(B53="","", VLOOKUP(B53,'Данни'!A:D,3,false)) | G53: =D53*F53 -> 0 | H53: =IFerror(VLOOKUP(B53,'Номенклатура'!A:F,4,0),"") | I53: =iferror(VLOOKUP(B53,'Номенклатура'!A:F,5,0),"") | J53: =iferror(VLOOKUP(B53,'Номенклатура'!A:N,6,0),"") | K53: =iferror(VLOOKUP(B53,'Номенклатура'!A:N,7,0),"") | L53: =IFERROR(VLOOKUP(B53,'Номенклатура'!A:N,8,0),"") | M53: =IFERROR(VLOOKUP(B53,'Номенклатура'!A:N,9,0),"") | N53: =IFERROR(VLOOKUP(B54,'Номенклатура'!A:N,10,0),"") | O53: =IFERROR(VLOOKUP(B53,'Номенклатура'!A:N,11,0),"") | P53: =IFERROR(VLOOKUP(B53,'Номенклатура'!A:N,12,0),"") | Q53: =IFERROR(VLOOKUP(B53,'Номенклатура'!A:N,13,0),"") | R53: =IFERROR(VLOOKUP(B53,'Номенклатура'!A:N,14,0),"")
A54: 41 | E54: =if(B54="","", VLOOKUP(B54,'Данни'!A:D,4,false)) | F54: =if(B54="","", VLOOKUP(B54,'Данни'!A:D,3,false)) | G54: =D54*F54 -> 0 | H54: =IFerror(VLOOKUP(B54,'Номенклатура'!A:F,4,0),"") | I54: =iferror(VLOOKUP(B54,'Номенклатура'!A:F,5,0),"") | J54: =iferror(VLOOKUP(B54,'Номенклатура'!A:N,6,0),"") | K54: =iferror(VLOOKUP(B54,'Номенклатура'!A:N,7,0),"") | L54: =IFERROR(VLOOKUP(B54,'Номенклатура'!A:N,8,0),"") | M54: =IFERROR(VLOOKUP(B54,'Номенклатура'!A:N,9,0),"") | N54: =IFERROR(VLOOKUP(B55,'Номенклатура'!A:N,10,0),"") | O54: =IFERROR(VLOOKUP(B54,'Номенклатура'!A:N,11,0),"") | P54: =IFERROR(VLOOKUP(B54,'Номенклатура'!A:N,12,0),"") | Q54: =IFERROR(VLOOKUP(B54,'Номенклатура'!A:N,13,0),"") | R54: =IFERROR(VLOOKUP(B54,'Номенклатура'!A:N,14,0),"")
A55: 42 | E55: =if(B55="","", VLOOKUP(B55,'Данни'!A:D,4,false)) | F55: =if(B55="","", VLOOKUP(B55,'Данни'!A:D,3,false)) | G55: =D55*F55 -> 0 | H55: =IFerror(VLOOKUP(B55,'Номенклатура'!A:F,4,0),"") | I55: =iferror(VLOOKUP(B55,'Номенклатура'!A:F,5,0),"") | J55: =iferror(VLOOKUP(B55,'Номенклатура'!A:N,6,0),"") | K55: =iferror(VLOOKUP(B55,'Номенклатура'!A:N,7,0),"") | L55: =IFERROR(VLOOKUP(B55,'Номенклатура'!A:N,8,0),"") | M55: =IFERROR(VLOOKUP(B55,'Номенклатура'!A:N,9,0),"") | N55: =IFERROR(VLOOKUP(B56,'Номенклатура'!A:N,10,0),"") | O55: =IFERROR(VLOOKUP(B55,'Номенклатура'!A:N,11,0),"") | P55: =IFERROR(VLOOKUP(B55,'Номенклатура'!A:N,12,0),"") | Q55: =IFERROR(VLOOKUP(B55,'Номенклатура'!A:N,13,0),"") | R55: =IFERROR(VLOOKUP(B55,'Номенклатура'!A:N,14,0),"")
A56: 43 | E56: =if(B56="","", VLOOKUP(B56,'Данни'!A:D,4,false)) | F56: =if(B56="","", VLOOKUP(B56,'Данни'!A:D,3,false)) | G56: =D56*F56 -> 0 | H56: =IFerror(VLOOKUP(B56,'Номенклатура'!A:F,4,0),"") | I56: =iferror(VLOOKUP(B56,'Номенклатура'!A:F,5,0),"") | J56: =iferror(VLOOKUP(B56,'Номенклатура'!A:N,6,0),"") | K56: =iferror(VLOOKUP(B56,'Номенклатура'!A:N,7,0),"") | L56: =IFERROR(VLOOKUP(B56,'Номенклатура'!A:N,8,0),"") | M56: =IFERROR(VLOOKUP(B56,'Номенклатура'!A:N,9,0),"") | N56: =IFERROR(VLOOKUP(B57,'Номенклатура'!A:N,10,0),"") | O56: =IFERROR(VLOOKUP(B56,'Номенклатура'!A:N,11,0),"") | P56: =IFERROR(VLOOKUP(B56,'Номенклатура'!A:N,12,0),"") | Q56: =IFERROR(VLOOKUP(B56,'Номенклатура'!A:N,13,0),"") | R56: =IFERROR(VLOOKUP(B56,'Номенклатура'!A:N,14,0),"")
A57: 44 | B57: ='План'!C45 | E57: =if(B57="","", VLOOKUP(B57,'Данни'!A:D,4,false)) | F57: =if(B57="","", VLOOKUP(B57,'Данни'!A:D,3,false)) | G57: =D57*F57 -> 0 | H57: =IFerror(VLOOKUP(B57,'Номенклатура'!A:F,4,0),"") | I57: =iferror(VLOOKUP(B57,'Номенклатура'!A:F,5,0),"") | J57: =iferror(VLOOKUP(B57,'Номенклатура'!A:N,6,0),"") | K57: =iferror(VLOOKUP(B57,'Номенклатура'!A:N,7,0),"") | L57: =IFERROR(VLOOKUP(B57,'Номенклатура'!A:N,8,0),"") | M57: =IFERROR(VLOOKUP(B57,'Номенклатура'!A:N,9,0),"") | N57: =IFERROR(VLOOKUP(B58,'Номенклатура'!A:N,10,0),"") | O57: =IFERROR(VLOOKUP(B57,'Номенклатура'!A:N,11,0),"") | P57: =IFERROR(VLOOKUP(B57,'Номенклатура'!A:N,12,0),"") | Q57: =IFERROR(VLOOKUP(B57,'Номенклатура'!A:N,13,0),"") | R57: =IFERROR(VLOOKUP(B57,'Номенклатура'!A:N,14,0),"")
A58: 45 | B58: ='План'!C46 | E58: =if(B58="","", VLOOKUP(B58,'Данни'!A:D,4,false)) | F58: =if(B58="","", VLOOKUP(B58,'Данни'!A:D,3,false)) | G58: =D58*F58 -> 0 | H58: =IFerror(VLOOKUP(B58,'Номенклатура'!A:F,4,0),"") | I58: =iferror(VLOOKUP(B58,'Номенклатура'!A:F,5,0),"") | J58: =iferror(VLOOKUP(B58,'Номенклатура'!A:N,6,0),"") | K58: =iferror(VLOOKUP(B58,'Номенклатура'!A:N,7,0),"") | L58: =IFERROR(VLOOKUP(B58,'Номенклатура'!A:N,8,0),"") | M58: =IFERROR(VLOOKUP(B58,'Номенклатура'!A:N,9,0),"") | N58: =IFERROR(VLOOKUP(B59,'Номенклатура'!A:N,10,0),"") | O58: =IFERROR(VLOOKUP(B58,'Номенклатура'!A:N,11,0),"") | P58: =IFERROR(VLOOKUP(B58,'Номенклатура'!A:N,12,0),"") | Q58: =IFERROR(VLOOKUP(B58,'Номенклатура'!A:N,13,0),"") | R58: =IFERROR(VLOOKUP(B58,'Номенклатура'!A:N,14,0),"")
A59: 46 | B59: ='План'!C47 | C59: =if(B59="","", VLOOKUP(B59,'Номенклатура'!A$3:B997,2,false)) | D59: ='План'!A47 | E59: =if(B59="","", VLOOKUP(B59,'Данни'!A:D,4,false)) | F59: =if(B59="","", VLOOKUP(B59,'Данни'!A:D,3,false)) | G59: =D59*F59 -> 0 | H59: =IFerror(VLOOKUP(B59,'Номенклатура'!A:F,4,0),"") | I59: =iferror(VLOOKUP(B59,'Номенклатура'!A:F,5,0),"") | J59: =iferror(VLOOKUP(B59,'Номенклатура'!A:N,6,0),"") | K59: =iferror(VLOOKUP(B59,'Номенклатура'!A:N,7,0),"") | L59: =IFERROR(VLOOKUP(B59,'Номенклатура'!A:N,8,0),"") | M59: =IFERROR(VLOOKUP(B59,'Номенклатура'!A:N,9,0),"") | N59: =IFERROR(VLOOKUP(B60,'Номенклатура'!A:N,10,0),"") | O59: =IFERROR(VLOOKUP(B59,'Номенклатура'!A:N,11,0),"") | P59: =IFERROR(VLOOKUP(B59,'Номенклатура'!A:N,12,0),"") | Q59: =IFERROR(VLOOKUP(B59,'Номенклатура'!A:N,13,0),"") | R59: =IFERROR(VLOOKUP(B59,'Номенклатура'!A:N,14,0),"")
A60: 47 | B60: ='План'!C48 | C60: =if(B60="","", VLOOKUP(B60,'Номенклатура'!A$3:B997,2,false)) | D60: ='План'!A48 | E60: =if(B60="","", VLOOKUP(B60,'Данни'!A:D,4,false)) | F60: =if(B60="","", VLOOKUP(B60,'Данни'!A:D,3,false)) | G60: =D60*F60 -> 0 | H60: =IFerror(VLOOKUP(B60,'Номенклатура'!A:F,4,0),"") | I60: =iferror(VLOOKUP(B60,'Номенклатура'!A:F,5,0),"") | J60: =iferror(VLOOKUP(B60,'Номенклатура'!A:N,6,0),"") | K60: =iferror(VLOOKUP(B60,'Номенклатура'!A:N,7,0),"") | L60: =IFERROR(VLOOKUP(B60,'Номенклатура'!A:N,8,0),"") | M60: =IFERROR(VLOOKUP(B60,'Номенклатура'!A:N,9,0),"") | N60: =IFERROR(VLOOKUP(B61,'Номенклатура'!A:N,10,0),"") | O60: =IFERROR(VLOOKUP(B60,'Номенклатура'!A:N,11,0),"") | P60: =IFERROR(VLOOKUP(B60,'Номенклатура'!A:N,12,0),"") | Q60: =IFERROR(VLOOKUP(B60,'Номенклатура'!A:N,13,0),"") | R60: =IFERROR(VLOOKUP(B60,'Номенклатура'!A:N,14,0),"")
A61: 48 | B61: ='План'!C49 | C61: =if(B61="","", VLOOKUP(B61,'Номенклатура'!A$3:B997,2,false)) | D61: ='План'!A49 | E61: =if(B61="","", VLOOKUP(B61,'Данни'!A:D,4,false)) | F61: =if(B61="","", VLOOKUP(B61,'Данни'!A:D,3,false)) | G61: =D61*F61 -> 0 | H61: =IFerror(VLOOKUP(B61,'Номенклатура'!A:F,4,0),"") | I61: =iferror(VLOOKUP(B61,'Номенклатура'!A:F,5,0),"") | J61: =iferror(VLOOKUP(B61,'Номенклатура'!A:N,6,0),"") | K61: =iferror(VLOOKUP(B61,'Номенклатура'!A:N,7,0),"") | L61: =IFERROR(VLOOKUP(B61,'Номенклатура'!A:N,8,0),"") | M61: =IFERROR(VLOOKUP(B61,'Номенклатура'!A:N,9,0),"") | N61: =IFERROR(VLOOKUP(B62,'Номенклатура'!A:N,10,0),"") | O61: =IFERROR(VLOOKUP(B61,'Номенклатура'!A:N,11,0),"") | P61: =IFERROR(VLOOKUP(B61,'Номенклатура'!A:N,12,0),"") | Q61: =IFERROR(VLOOKUP(B61,'Номенклатура'!A:N,13,0),"") | R61: =IFERROR(VLOOKUP(B61,'Номенклатура'!A:N,14,0),"")
A62: 49 | B62: ='План'!C50 | C62: =if(B62="","", VLOOKUP(B62,'Номенклатура'!A$3:B997,2,false)) | D62: ='План'!A50 | E62: =if(B62="","", VLOOKUP(B62,'Данни'!A:D,4,false)) | F62: =if(B62="","", VLOOKUP(B62,'Данни'!A:D,3,false)) | G62: =D62*F62 -> 0 | H62: =IFerror(VLOOKUP(B62,'Номенклатура'!A:F,4,0),"") | I62: =iferror(VLOOKUP(B62,'Номенклатура'!A:F,5,0),"") | J62: =iferror(VLOOKUP(B62,'Номенклатура'!A:N,6,0),"") | K62: =iferror(VLOOKUP(B62,'Номенклатура'!A:N,7,0),"") | L62: =IFERROR(VLOOKUP(B62,'Номенклатура'!A:N,8,0),"") | M62: =IFERROR(VLOOKUP(B62,'Номенклатура'!A:N,9,0),"") | N62: =IFERROR(VLOOKUP(B63,'Номенклатура'!A:N,10,0),"") | O62: =IFERROR(VLOOKUP(B62,'Номенклатура'!A:N,11,0),"") | P62: =IFERROR(VLOOKUP(B62,'Номенклатура'!A:N,12,0),"") | Q62: =IFERROR(VLOOKUP(B62,'Номенклатура'!A:N,13,0),"") | R62: =IFERROR(VLOOKUP(B62,'Номенклатура'!A:N,14,0),"")
A63: 50 | B63: ='План'!C51 | C63: =if(B63="","", VLOOKUP(B63,'Номенклатура'!A$3:B997,2,false)) | D63: ='План'!A51 | E63: =if(B63="","", VLOOKUP(B63,'Данни'!A:D,4,false)) | F63: =if(B63="","", VLOOKUP(B63,'Данни'!A:D,3,false)) | G63: =D63*F63 -> 0 | H63: =IFerror(VLOOKUP(B63,'Номенклатура'!A:F,4,0),"") | I63: =iferror(VLOOKUP(B63,'Номенклатура'!A:F,5,0),"") | J63: =iferror(VLOOKUP(B63,'Номенклатура'!A:N,6,0),"") | K63: =iferror(VLOOKUP(B63,'Номенклатура'!A:N,7,0),"") | L63: =IFERROR(VLOOKUP(B63,'Номенклатура'!A:N,8,0),"") | M63: =IFERROR(VLOOKUP(B63,'Номенклатура'!A:N,9,0),"") | N63: =IFERROR(VLOOKUP(B64,'Номенклатура'!A:N,10,0),"") | O63: =IFERROR(VLOOKUP(B63,'Номенклатура'!A:N,11,0),"") | P63: =IFERROR(VLOOKUP(B63,'Номенклатура'!A:N,12,0),"") | Q63: =IFERROR(VLOOKUP(B63,'Номенклатура'!A:N,13,0),"") | R63: =IFERROR(VLOOKUP(B63,'Номенклатура'!A:N,14,0),"")
A64: 51 | B64: ='План'!C52 | C64: =if(B64="","", VLOOKUP(B64,'Номенклатура'!A$3:B997,2,false)) | D64: ='План'!A52 | E64: =if(B64="","", VLOOKUP(B64,'Данни'!A:D,4,false)) | F64: =if(B64="","", VLOOKUP(B64,'Данни'!A:D,3,false)) | G64: =D64*F64 -> 0 | H64: =IFerror(VLOOKUP(B64,'Номенклатура'!A:F,4,0),"") | I64: =iferror(VLOOKUP(B64,'Номенклатура'!A:F,5,0),"") | J64: =iferror(VLOOKUP(B64,'Номенклатура'!A:N,6,0),"") | K64: =iferror(VLOOKUP(B64,'Номенклатура'!A:N,7,0),"") | L64: =IFERROR(VLOOKUP(B64,'Номенклатура'!A:N,8,0),"") | M64: =IFERROR(VLOOKUP(B64,'Номенклатура'!A:N,9,0),"") | N64: =IFERROR(VLOOKUP(B65,'Номенклатура'!A:N,10,0),"") | O64: =IFERROR(VLOOKUP(B64,'Номенклатура'!A:N,11,0),"") | P64: =IFERROR(VLOOKUP(B64,'Номенклатура'!A:N,12,0),"") | Q64: =IFERROR(VLOOKUP(B64,'Номенклатура'!A:N,13,0),"") | R64: =IFERROR(VLOOKUP(B64,'Номенклатура'!A:N,14,0),"")
A65: 52 | B65: ='План'!C53 | C65: =if(B65="","", VLOOKUP(B65,'Номенклатура'!A$3:B997,2,false)) | D65: ='План'!A53 | E65: =if(B65="","", VLOOKUP(B65,'Данни'!A:D,4,false)) | F65: =if(B65="","", VLOOKUP(B65,'Данни'!A:D,3,false)) | G65: =D65*F65 -> 0 | H65: =IFerror(VLOOKUP(B65,'Номенклатура'!A:F,4,0),"") | I65: =iferror(VLOOKUP(B65,'Номенклатура'!A:F,5,0),"") | J65: =iferror(VLOOKUP(B65,'Номенклатура'!A:N,6,0),"") | K65: =iferror(VLOOKUP(B65,'Номенклатура'!A:N,7,0),"") | L65: =IFERROR(VLOOKUP(B65,'Номенклатура'!A:N,8,0),"") | M65: =IFERROR(VLOOKUP(B65,'Номенклатура'!A:N,9,0),"") | N65: =IFERROR(VLOOKUP(B66,'Номенклатура'!A:N,10,0),"") | O65: =IFERROR(VLOOKUP(B65,'Номенклатура'!A:N,11,0),"") | P65: =IFERROR(VLOOKUP(B65,'Номенклатура'!A:N,12,0),"") | Q65: =IFERROR(VLOOKUP(B65,'Номенклатура'!A:N,13,0),"") | R65: =IFERROR(VLOOKUP(B65,'Номенклатура'!A:N,14,0),"")
A66: 53 | B66: ='План'!C54 | C66: =if(B66="","", VLOOKUP(B66,'Номенклатура'!A$3:B997,2,false)) | D66: ='План'!A54 | E66: =if(B66="","", VLOOKUP(B66,'Данни'!A:D,4,false)) | F66: =if(B66="","", VLOOKUP(B66,'Данни'!A:D,3,false)) | G66: =D66*F66 -> 0 | H66: =IFerror(VLOOKUP(B66,'Номенклатура'!A:F,4,0),"") | I66: =iferror(VLOOKUP(B66,'Номенклатура'!A:F,5,0),"") | J66: =iferror(VLOOKUP(B66,'Номенклатура'!A:N,6,0),"") | K66: =iferror(VLOOKUP(B66,'Номенклатура'!A:N,7,0),"") | L66: =IFERROR(VLOOKUP(B66,'Номенклатура'!A:N,8,0),"") | M66: =IFERROR(VLOOKUP(B66,'Номенклатура'!A:N,9,0),"") | N66: =IFERROR(VLOOKUP(B67,'Номенклатура'!A:N,10,0),"") | O66: =IFERROR(VLOOKUP(B66,'Номенклатура'!A:N,11,0),"") | P66: =IFERROR(VLOOKUP(B66,'Номенклатура'!A:N,12,0),"") | Q66: =IFERROR(VLOOKUP(B66,'Номенклатура'!A:N,13,0),"") | R66: =IFERROR(VLOOKUP(B66,'Номенклатура'!A:N,14,0),"")
A67: 54 | B67: ='План'!C55 | C67: =if(B67="","", VLOOKUP(B67,'Номенклатура'!A$3:B997,2,false)) | D67: ='План'!A55 | E67: =if(B67="","", VLOOKUP(B67,'Данни'!A:D,4,false)) | F67: =if(B67="","", VLOOKUP(B67,'Данни'!A:D,3,false)) | G67: =D67*F67 -> 0 | H67: =IFerror(VLOOKUP(B67,'Номенклатура'!A:F,4,0),"") | I67: =iferror(VLOOKUP(B67,'Номенклатура'!A:F,5,0),"") | J67: =iferror(VLOOKUP(B67,'Номенклатура'!A:N,6,0),"") | K67: =iferror(VLOOKUP(B67,'Номенклатура'!A:N,7,0),"") | L67: =IFERROR(VLOOKUP(B67,'Номенклатура'!A:N,8,0),"") | M67: =IFERROR(VLOOKUP(B67,'Номенклатура'!A:N,9,0),"") | N67: =IFERROR(VLOOKUP(B68,'Номенклатура'!A:N,10,0),"") | O67: =IFERROR(VLOOKUP(B67,'Номенклатура'!A:N,11,0),"") | P67: =IFERROR(VLOOKUP(B67,'Номенклатура'!A:N,12,0),"") | Q67: =IFERROR(VLOOKUP(B67,'Номенклатура'!A:N,13,0),"") | R67: =IFERROR(VLOOKUP(B67,'Номенклатура'!A:N,14,0),"")
A68: 55 | B68: ='План'!C56 | C68: =if(B68="","", VLOOKUP(B68,'Номенклатура'!A$3:B997,2,false)) | D68: ='План'!A56 | E68: =if(B68="","", VLOOKUP(B68,'Данни'!A:D,4,false)) | F68: =if(B68="","", VLOOKUP(B68,'Данни'!A:D,3,false)) | G68: =D68*F68 -> 0 | H68: =IFerror(VLOOKUP(B68,'Номенклатура'!A:F,4,0),"") | I68: =iferror(VLOOKUP(B68,'Номенклатура'!A:F,5,0),"") | J68: =iferror(VLOOKUP(B68,'Номенклатура'!A:N,6,0),"") | K68: =iferror(VLOOKUP(B68,'Номенклатура'!A:N,7,0),"") | L68: =IFERROR(VLOOKUP(B68,'Номенклатура'!A:N,8,0),"") | M68: =IFERROR(VLOOKUP(B68,'Номенклатура'!A:N,9,0),"") | N68: =IFERROR(VLOOKUP(B69,'Номенклатура'!A:N,10,0),"") | O68: =IFERROR(VLOOKUP(B68,'Номенклатура'!A:N,11,0),"") | P68: =IFERROR(VLOOKUP(B68,'Номенклатура'!A:N,12,0),"") | Q68: =IFERROR(VLOOKUP(B68,'Номенклатура'!A:N,13,0),"") | R68: =IFERROR(VLOOKUP(B68,'Номенклатура'!A:N,14,0),"")
A69: 56 | B69: ='План'!C57 | C69: =if(B69="","", VLOOKUP(B69,'Номенклатура'!A$3:B997,2,false)) | D69: ='План'!A57 | E69: =if(B69="","", VLOOKUP(B69,'Данни'!A:D,4,false)) | F69: =if(B69="","", VLOOKUP(B69,'Данни'!A:D,3,false)) | G69: =D69*F69 -> 0 | H69: =IFerror(VLOOKUP(B69,'Номенклатура'!A:F,4,0),"") | I69: =iferror(VLOOKUP(B69,'Номенклатура'!A:F,5,0),"") | J69: =iferror(VLOOKUP(B69,'Номенклатура'!A:N,6,0),"") | K69: =iferror(VLOOKUP(B69,'Номенклатура'!A:N,7,0),"") | L69: =IFERROR(VLOOKUP(B69,'Номенклатура'!A:N,8,0),"") | M69: =IFERROR(VLOOKUP(B69,'Номенклатура'!A:N,9,0),"") | N69: =IFERROR(VLOOKUP(B70,'Номенклатура'!A:N,10,0),"") | O69: =IFERROR(VLOOKUP(B69,'Номенклатура'!A:N,11,0),"") | P69: =IFERROR(VLOOKUP(B69,'Номенклатура'!A:N,12,0),"") | Q69: =IFERROR(VLOOKUP(B69,'Номенклатура'!A:N,13,0),"") | R69: =IFERROR(VLOOKUP(B69,'Номенклатура'!A:N,14,0),"")
A70: 57 | B70: ='План'!C58 | C70: =if(B70="","", VLOOKUP(B70,'Номенклатура'!A$3:B997,2,false)) | D70: ='План'!A58 | E70: =if(B70="","", VLOOKUP(B70,'Данни'!A:D,4,false)) | F70: =if(B70="","", VLOOKUP(B70,'Данни'!A:D,3,false)) | G70: =D70*F70 -> 0 | H70: =IFerror(VLOOKUP(B70,'Номенклатура'!A:F,4,0),"") | I70: =iferror(VLOOKUP(B70,'Номенклатура'!A:F,5,0),"") | J70: =iferror(VLOOKUP(B70,'Номенклатура'!A:N,6,0),"") | K70: =iferror(VLOOKUP(B70,'Номенклатура'!A:N,7,0),"") | L70: =IFERROR(VLOOKUP(B70,'Номенклатура'!A:N,8,0),"") | M70: =IFERROR(VLOOKUP(B70,'Номенклатура'!A:N,9,0),"") | N70: =IFERROR(VLOOKUP(B71,'Номенклатура'!A:N,10,0),"") | O70: =IFERROR(VLOOKUP(B70,'Номенклатура'!A:N,11,0),"") | P70: =IFERROR(VLOOKUP(B70,'Номенклатура'!A:N,12,0),"") | Q70: =IFERROR(VLOOKUP(B70,'Номенклатура'!A:N,13,0),"") | R70: =IFERROR(VLOOKUP(B70,'Номенклатура'!A:N,14,0),"")
A71: 58 | B71: ='План'!C59 | C71: =if(B71="","", VLOOKUP(B71,'Номенклатура'!A$3:B997,2,false)) | D71: ='План'!A59 | E71: =if(B71="","", VLOOKUP(B71,'Данни'!A:D,4,false)) | F71: =if(B71="","", VLOOKUP(B71,'Данни'!A:D,3,false)) | G71: =D71*F71 -> 0 | H71: =IFerror(VLOOKUP(B71,'Номенклатура'!A:F,4,0),"") | I71: =iferror(VLOOKUP(B71,'Номенклатура'!A:F,5,0),"") | J71: =iferror(VLOOKUP(B71,'Номенклатура'!A:N,6,0),"") | K71: =iferror(VLOOKUP(B71,'Номенклатура'!A:N,7,0),"") | L71: =IFERROR(VLOOKUP(B71,'Номенклатура'!A:N,8,0),"") | M71: =IFERROR(VLOOKUP(B71,'Номенклатура'!A:N,9,0),"") | N71: =IFERROR(VLOOKUP(B72,'Номенклатура'!A:N,10,0),"") | O71: =IFERROR(VLOOKUP(B71,'Номенклатура'!A:N,11,0),"") | P71: =IFERROR(VLOOKUP(B71,'Номенклатура'!A:N,12,0),"") | Q71: =IFERROR(VLOOKUP(B71,'Номенклатура'!A:N,13,0),"") | R71: =IFERROR(VLOOKUP(B71,'Номенклатура'!A:N,14,0),"")
A72: 59 | B72: ='План'!C60 | C72: =if(B72="","", VLOOKUP(B72,'Номенклатура'!A$3:B997,2,false)) | D72: ='План'!A60 | E72: =if(B72="","", VLOOKUP(B72,'Данни'!A:D,4,false)) | F72: =if(B72="","", VLOOKUP(B72,'Данни'!A:D,3,false)) | G72: =D72*F72 -> 0 | H72: =IFerror(VLOOKUP(B72,'Номенклатура'!A:F,4,0),"") | I72: =iferror(VLOOKUP(B72,'Номенклатура'!A:F,5,0),"") | J72: =iferror(VLOOKUP(B72,'Номенклатура'!A:N,6,0),"") | K72: =iferror(VLOOKUP(B72,'Номенклатура'!A:N,7,0),"") | L72: =IFERROR(VLOOKUP(B72,'Номенклатура'!A:N,8,0),"") | M72: =IFERROR(VLOOKUP(B72,'Номенклатура'!A:N,9,0),"") | N72: =IFERROR(VLOOKUP(B73,'Номенклатура'!A:N,10,0),"") | O72: =IFERROR(VLOOKUP(B72,'Номенклатура'!A:N,11,0),"") | P72: =IFERROR(VLOOKUP(B72,'Номенклатура'!A:N,12,0),"") | Q72: =IFERROR(VLOOKUP(B72,'Номенклатура'!A:N,13,0),"") | R72: =IFERROR(VLOOKUP(B72,'Номенклатура'!A:N,14,0),"")
A73: 60 | B73: ='План'!C61 | C73: =if(B73="","", VLOOKUP(B73,'Номенклатура'!A$3:B997,2,false)) | D73: ='План'!A61 | E73: =if(B73="","", VLOOKUP(B73,'Данни'!A:D,4,false)) | F73: =if(B73="","", VLOOKUP(B73,'Данни'!A:D,3,false)) | G73: =D73*F73 -> 0 | H73: =IFerror(VLOOKUP(B73,'Номенклатура'!A:F,4,0),"") | I73: =iferror(VLOOKUP(B73,'Номенклатура'!A:F,5,0),"") | J73: =iferror(VLOOKUP(B73,'Номенклатура'!A:N,6,0),"") | K73: =iferror(VLOOKUP(B73,'Номенклатура'!A:N,7,0),"") | L73: =IFERROR(VLOOKUP(B73,'Номенклатура'!A:N,8,0),"") | M73: =IFERROR(VLOOKUP(B73,'Номенклатура'!A:N,9,0),"") | N73: =IFERROR(VLOOKUP(B74,'Номенклатура'!A:N,10,0),"") | O73: =IFERROR(VLOOKUP(B73,'Номенклатура'!A:N,11,0),"") | P73: =IFERROR(VLOOKUP(B73,'Номенклатура'!A:N,12,0),"") | Q73: =IFERROR(VLOOKUP(B73,'Номенклатура'!A:N,13,0),"") | R73: =IFERROR(VLOOKUP(B73,'Номенклатура'!A:N,14,0),"")
A74: 61 | B74: ='План'!C62 | C74: =if(B74="","", VLOOKUP(B74,'Номенклатура'!A$3:B997,2,false)) | D74: ='План'!A62 | E74: =if(B74="","", VLOOKUP(B74,'Данни'!A:D,4,false)) | F74: =if(B74="","", VLOOKUP(B74,'Данни'!A:D,3,false)) | G74: =D74*F74 -> 0 | H74: =IFerror(VLOOKUP(B74,'Номенклатура'!A:F,4,0),"") | I74: =iferror(VLOOKUP(B74,'Номенклатура'!A:F,5,0),"") | J74: =iferror(VLOOKUP(B74,'Номенклатура'!A:N,6,0),"") | K74: =iferror(VLOOKUP(B74,'Номенклатура'!A:N,7,0),"") | L74: =IFERROR(VLOOKUP(B74,'Номенклатура'!A:N,8,0),"") | M74: =IFERROR(VLOOKUP(B74,'Номенклатура'!A:N,9,0),"") | N74: =IFERROR(VLOOKUP(B75,'Номенклатура'!A:N,10,0),"") | O74: =IFERROR(VLOOKUP(B74,'Номенклатура'!A:N,11,0),"") | P74: =IFERROR(VLOOKUP(B74,'Номенклатура'!A:N,12,0),"") | Q74: =IFERROR(VLOOKUP(B74,'Номенклатура'!A:N,13,0),"") | R74: =IFERROR(VLOOKUP(B74,'Номенклатура'!A:N,14,0),"")
A75: 62 | B75: ='План'!C63 | C75: =if(B75="","", VLOOKUP(B75,'Номенклатура'!A$3:B997,2,false)) | D75: ='План'!A63 | E75: =if(B75="","", VLOOKUP(B75,'Данни'!A:D,4,false)) | F75: =if(B75="","", VLOOKUP(B75,'Данни'!A:D,3,false)) | G75: =D75*F75 -> 0 | H75: =IFerror(VLOOKUP(B75,'Номенклатура'!A:F,4,0),"") | I75: =iferror(VLOOKUP(B75,'Номенклатура'!A:F,5,0),"") | J75: =iferror(VLOOKUP(B75,'Номенклатура'!A:N,6,0),"") | K75: =iferror(VLOOKUP(B75,'Номенклатура'!A:N,7,0),"") | L75: =IFERROR(VLOOKUP(B75,'Номенклатура'!A:N,8,0),"") | M75: =IFERROR(VLOOKUP(B75,'Номенклатура'!A:N,9,0),"") | N75: =IFERROR(VLOOKUP(B76,'Номенклатура'!A:N,10,0),"") | O75: =IFERROR(VLOOKUP(B75,'Номенклатура'!A:N,11,0),"") | P75: =IFERROR(VLOOKUP(B75,'Номенклатура'!A:N,12,0),"") | Q75: =IFERROR(VLOOKUP(B75,'Номенклатура'!A:N,13,0),"") | R75: =IFERROR(VLOOKUP(B75,'Номенклатура'!A:N,14,0),"")
A76: 63 | B76: ='План'!C64 | C76: =if(B76="","", VLOOKUP(B76,'Номенклатура'!A$3:B997,2,false)) | D76: ='План'!A64 | E76: =if(B76="","", VLOOKUP(B76,'Данни'!A:D,4,false)) | F76: =if(B76="","", VLOOKUP(B76,'Данни'!A:D,3,false)) | G76: =D76*F76 -> 0 | H76: =IFerror(VLOOKUP(B76,'Номенклатура'!A:F,4,0),"") | I76: =iferror(VLOOKUP(B76,'Номенклатура'!A:F,5,0),"") | J76: =iferror(VLOOKUP(B76,'Номенклатура'!A:N,6,0),"") | K76: =iferror(VLOOKUP(B76,'Номенклатура'!A:N,7,0),"") | L76: =IFERROR(VLOOKUP(B76,'Номенклатура'!A:N,8,0),"") | M76: =IFERROR(VLOOKUP(B76,'Номенклатура'!A:N,9,0),"") | N76: =IFERROR(VLOOKUP(B77,'Номенклатура'!A:N,10,0),"") | O76: =IFERROR(VLOOKUP(B76,'Номенклатура'!A:N,11,0),"") | P76: =IFERROR(VLOOKUP(B76,'Номенклатура'!A:N,12,0),"") | Q76: =IFERROR(VLOOKUP(B76,'Номенклатура'!A:N,13,0),"") | R76: =IFERROR(VLOOKUP(B76,'Номенклатура'!A:N,14,0),"")
A77: 64 | B77: ='План'!C65 | C77: =if(B77="","", VLOOKUP(B77,'Номенклатура'!A$3:B997,2,false)) | D77: ='План'!A65 | E77: =if(B77="","", VLOOKUP(B77,'Данни'!A:D,4,false)) | F77: =if(B77="","", VLOOKUP(B77,'Данни'!A:D,3,false)) | G77: =D77*F77 -> 0 | H77: =IFerror(VLOOKUP(B77,'Номенклатура'!A:F,4,0),"") | I77: =iferror(VLOOKUP(B77,'Номенклатура'!A:F,5,0),"") | J77: =iferror(VLOOKUP(B77,'Номенклатура'!A:N,6,0),"") | K77: =iferror(VLOOKUP(B77,'Номенклатура'!A:N,7,0),"") | L77: =IFERROR(VLOOKUP(B77,'Номенклатура'!A:N,8,0),"") | M77: =IFERROR(VLOOKUP(B77,'Номенклатура'!A:N,9,0),"") | N77: =IFERROR(VLOOKUP(B78,'Номенклатура'!A:N,10,0),"") | O77: =IFERROR(VLOOKUP(B77,'Номенклатура'!A:N,11,0),"") | P77: =IFERROR(VLOOKUP(B77,'Номенклатура'!A:N,12,0),"") | Q77: =IFERROR(VLOOKUP(B77,'Номенклатура'!A:N,13,0),"") | R77: =IFERROR(VLOOKUP(B77,'Номенклатура'!A:N,14,0),"")
A78: 65 | B78: ='План'!C66 | C78: =if(B78="","", VLOOKUP(B78,'Номенклатура'!A$3:B997,2,false)) | D78: ='План'!A66 | E78: =if(B78="","", VLOOKUP(B78,'Данни'!A:D,4,false)) | F78: =if(B78="","", VLOOKUP(B78,'Данни'!A:D,3,false)) | G78: =D78*F78 -> 0 | H78: =IFerror(VLOOKUP(B78,'Номенклатура'!A:F,4,0),"") | I78: =iferror(VLOOKUP(B78,'Номенклатура'!A:F,5,0),"") | J78: =iferror(VLOOKUP(B78,'Номенклатура'!A:N,6,0),"") | K78: =iferror(VLOOKUP(B78,'Номенклатура'!A:N,7,0),"") | L78: =IFERROR(VLOOKUP(B78,'Номенклатура'!A:N,8,0),"") | M78: =IFERROR(VLOOKUP(B78,'Номенклатура'!A:N,9,0),"") | N78: =IFERROR(VLOOKUP(B79,'Номенклатура'!A:N,10,0),"") | O78: =IFERROR(VLOOKUP(B78,'Номенклатура'!A:N,11,0),"") | P78: =IFERROR(VLOOKUP(B78,'Номенклатура'!A:N,12,0),"") | Q78: =IFERROR(VLOOKUP(B78,'Номенклатура'!A:N,13,0),"") | R78: =IFERROR(VLOOKUP(B78,'Номенклатура'!A:N,14,0),"")
A79: 66 | B79: ='План'!C67 | C79: =if(B79="","", VLOOKUP(B79,'Номенклатура'!A$3:B997,2,false)) | D79: ='План'!A67 | E79: =if(B79="","", VLOOKUP(B79,'Данни'!A:D,4,false)) | F79: =if(B79="","", VLOOKUP(B79,'Данни'!A:D,3,false)) | G79: =D79*F79 -> 0 | H79: =IFerror(VLOOKUP(B79,'Номенклатура'!A:F,4,0),"") | I79: =iferror(VLOOKUP(B79,'Номенклатура'!A:F,5,0),"") | J79: =iferror(VLOOKUP(B79,'Номенклатура'!A:N,6,0),"") | K79: =iferror(VLOOKUP(B79,'Номенклатура'!A:N,7,0),"") | L79: =IFERROR(VLOOKUP(B79,'Номенклатура'!A:N,8,0),"") | M79: =IFERROR(VLOOKUP(B79,'Номенклатура'!A:N,9,0),"") | N79: =IFERROR(VLOOKUP(B80,'Номенклатура'!A:N,10,0),"") | O79: =IFERROR(VLOOKUP(B79,'Номенклатура'!A:N,11,0),"") | P79: =IFERROR(VLOOKUP(B79,'Номенклатура'!A:N,12,0),"") | Q79: =IFERROR(VLOOKUP(B79,'Номенклатура'!A:N,13,0),"") | R79: =IFERROR(VLOOKUP(B79,'Номенклатура'!A:N,14,0),"")
A80: 67 | B80: ='План'!C68 | C80: =if(B80="","", VLOOKUP(B80,'Номенклатура'!A$3:B997,2,false)) | D80: ='План'!A68 | E80: =if(B80="","", VLOOKUP(B80,'Данни'!A:D,4,false)) | F80: =if(B80="","", VLOOKUP(B80,'Данни'!A:D,3,false)) | G80: =D80*F80 -> 0 | H80: =IFerror(VLOOKUP(B80,'Номенклатура'!A:F,4,0),"") | I80: =iferror(VLOOKUP(B80,'Номенклатура'!A:F,5,0),"") | J80: =iferror(VLOOKUP(B80,'Номенклатура'!A:N,6,0),"") | K80: =iferror(VLOOKUP(B80,'Номенклатура'!A:N,7,0),"") | L80: =IFERROR(VLOOKUP(B80,'Номенклатура'!A:N,8,0),"") | M80: =IFERROR(VLOOKUP(B80,'Номенклатура'!A:N,9,0),"") | N80: =IFERROR(VLOOKUP(B81,'Номенклатура'!A:N,10,0),"") | O80: =IFERROR(VLOOKUP(B80,'Номенклатура'!A:N,11,0),"") | P80: =IFERROR(VLOOKUP(B80,'Номенклатура'!A:N,12,0),"") | Q80: =IFERROR(VLOOKUP(B80,'Номенклатура'!A:N,13,0),"") | R80: =IFERROR(VLOOKUP(B80,'Номенклатура'!A:N,14,0),"")
A81: 68 | B81: ='План'!C69 | C81: =if(B81="","", VLOOKUP(B81,'Номенклатура'!A$3:B997,2,false)) | D81: ='План'!A69 | E81: =if(B81="","", VLOOKUP(B81,'Данни'!A:D,4,false)) | F81: =if(B81="","", VLOOKUP(B81,'Данни'!A:D,3,false)) | G81: =D81*F81 -> 0 | H81: =IFerror(VLOOKUP(B81,'Номенклатура'!A:F,4,0),"") | I81: =iferror(VLOOKUP(B81,'Номенклатура'!A:F,5,0),"") | J81: =iferror(VLOOKUP(B81,'Номенклатура'!A:N,6,0),"") | K81: =iferror(VLOOKUP(B81,'Номенклатура'!A:N,7,0),"") | L81: =IFERROR(VLOOKUP(B81,'Номенклатура'!A:N,8,0),"") | M81: =IFERROR(VLOOKUP(B81,'Номенклатура'!A:N,9,0),"") | N81: =IFERROR(VLOOKUP(B82,'Номенклатура'!A:N,10,0),"") | O81: =IFERROR(VLOOKUP(B81,'Номенклатура'!A:N,11,0),"") | P81: =IFERROR(VLOOKUP(B81,'Номенклатура'!A:N,12,0),"") | Q81: =IFERROR(VLOOKUP(B81,'Номенклатура'!A:N,13,0),"") | R81: =IFERROR(VLOOKUP(B81,'Номенклатура'!A:N,14,0),"")
A82: 69 | B82: ='План'!C70 | C82: =if(B82="","", VLOOKUP(B82,'Номенклатура'!A$3:B997,2,false)) | D82: ='План'!A70 | E82: =if(B82="","", VLOOKUP(B82,'Данни'!A:D,4,false)) | F82: =if(B82="","", VLOOKUP(B82,'Данни'!A:D,3,false)) | G82: =D82*F82 -> 0 | H82: =IFerror(VLOOKUP(B82,'Номенклатура'!A:F,4,0),"") | I82: =iferror(VLOOKUP(B82,'Номенклатура'!A:F,5,0),"") | J82: =iferror(VLOOKUP(B82,'Номенклатура'!A:N,6,0),"") | K82: =iferror(VLOOKUP(B82,'Номенклатура'!A:N,7,0),"") | L82: =IFERROR(VLOOKUP(B82,'Номенклатура'!A:N,8,0),"") | M82: =IFERROR(VLOOKUP(B82,'Номенклатура'!A:N,9,0),"") | N82: =IFERROR(VLOOKUP(B83,'Номенклатура'!A:N,10,0),"") | O82: =IFERROR(VLOOKUP(B82,'Номенклатура'!A:N,11,0),"") | P82: =IFERROR(VLOOKUP(B82,'Номенклатура'!A:N,12,0),"") | Q82: =IFERROR(VLOOKUP(B82,'Номенклатура'!A:N,13,0),"") | R82: =IFERROR(VLOOKUP(B82,'Номенклатура'!A:N,14,0),"")
A83: 70 | B83: ='План'!C71 | C83: =if(B83="","", VLOOKUP(B83,'Номенклатура'!A$3:B997,2,false)) | D83: ='План'!A71 | E83: =if(B83="","", VLOOKUP(B83,'Данни'!A:D,4,false)) | F83: =if(B83="","", VLOOKUP(B83,'Данни'!A:D,3,false)) | G83: =D83*F83 -> 0 | H83: =IFerror(VLOOKUP(B83,'Номенклатура'!A:F,4,0),"") | I83: =iferror(VLOOKUP(B83,'Номенклатура'!A:F,5,0),"") | J83: =iferror(VLOOKUP(B83,'Номенклатура'!A:N,6,0),"") | K83: =iferror(VLOOKUP(B83,'Номенклатура'!A:N,7,0),"") | L83: =IFERROR(VLOOKUP(B83,'Номенклатура'!A:N,8,0),"") | M83: =IFERROR(VLOOKUP(B83,'Номенклатура'!A:N,9,0),"") | N83: =IFERROR(VLOOKUP(B84,'Номенклатура'!A:N,10,0),"") | O83: =IFERROR(VLOOKUP(B83,'Номенклатура'!A:N,11,0),"") | P83: =IFERROR(VLOOKUP(B83,'Номенклатура'!A:N,12,0),"") | Q83: =IFERROR(VLOOKUP(B83,'Номенклатура'!A:N,13,0),"") | R83: =IFERROR(VLOOKUP(B83,'Номенклатура'!A:N,14,0),"")
A84: 71 | B84: ='План'!C72 | C84: =if(B84="","", VLOOKUP(B84,'Номенклатура'!A$3:B997,2,false)) | D84: ='План'!A72 | E84: =if(B84="","", VLOOKUP(B84,'Данни'!A:D,4,false)) | F84: =if(B84="","", VLOOKUP(B84,'Данни'!A:D,3,false)) | G84: =D84*F84 -> 0 | H84: =IFerror(VLOOKUP(B84,'Номенклатура'!A:F,4,0),"") | I84: =iferror(VLOOKUP(B84,'Номенклатура'!A:F,5,0),"") | J84: =iferror(VLOOKUP(B84,'Номенклатура'!A:N,6,0),"") | K84: =iferror(VLOOKUP(B84,'Номенклатура'!A:N,7,0),"") | L84: =IFERROR(VLOOKUP(B84,'Номенклатура'!A:N,8,0),"") | M84: =IFERROR(VLOOKUP(B84,'Номенклатура'!A:N,9,0),"") | N84: =IFERROR(VLOOKUP(B85,'Номенклатура'!A:N,10,0),"") | O84: =IFERROR(VLOOKUP(B84,'Номенклатура'!A:N,11,0),"") | P84: =IFERROR(VLOOKUP(B84,'Номенклатура'!A:N,12,0),"") | Q84: =IFERROR(VLOOKUP(B84,'Номенклатура'!A:N,13,0),"") | R84: =IFERROR(VLOOKUP(B84,'Номенклатура'!A:N,14,0),"")
A85: 72 | B85: ='План'!C73 | C85: =if(B85="","", VLOOKUP(B85,'Номенклатура'!A$3:B997,2,false)) | D85: ='План'!A73 | E85: =if(B85="","", VLOOKUP(B85,'Данни'!A:D,4,false)) | F85: =if(B85="","", VLOOKUP(B85,'Данни'!A:D,3,false)) | G85: =D85*F85 -> 0 | H85: =IFerror(VLOOKUP(B85,'Номенклатура'!A:F,4,0),"") | I85: =iferror(VLOOKUP(B85,'Номенклатура'!A:F,5,0),"") | J85: =iferror(VLOOKUP(B85,'Номенклатура'!A:N,6,0),"") | K85: =iferror(VLOOKUP(B85,'Номенклатура'!A:N,7,0),"") | L85: =IFERROR(VLOOKUP(B85,'Номенклатура'!A:N,8,0),"") | M85: =IFERROR(VLOOKUP(B85,'Номенклатура'!A:N,9,0),"") | N85: =IFERROR(VLOOKUP(B86,'Номенклатура'!A:N,10,0),"") | O85: =IFERROR(VLOOKUP(B85,'Номенклатура'!A:N,11,0),"") | P85: =IFERROR(VLOOKUP(B85,'Номенклатура'!A:N,12,0),"") | Q85: =IFERROR(VLOOKUP(B85,'Номенклатура'!A:N,13,0),"") | R85: =IFERROR(VLOOKUP(B85,'Номенклатура'!A:N,14,0),"")
A86: 73 | B86: ='План'!C74 | C86: =if(B86="","", VLOOKUP(B86,'Номенклатура'!A$3:B997,2,false)) | D86: ='План'!A74 | E86: =if(B86="","", VLOOKUP(B86,'Данни'!A:D,4,false)) | F86: =if(B86="","", VLOOKUP(B86,'Данни'!A:D,3,false)) | G86: =D86*F86 -> 0 | H86: =IFerror(VLOOKUP(B86,'Номенклатура'!A:F,4,0),"") | I86: =iferror(VLOOKUP(B86,'Номенклатура'!A:F,5,0),"") | J86: =iferror(VLOOKUP(B86,'Номенклатура'!A:N,6,0),"") | K86: =iferror(VLOOKUP(B86,'Номенклатура'!A:N,7,0),"") | L86: =IFERROR(VLOOKUP(B86,'Номенклатура'!A:N,8,0),"") | M86: =IFERROR(VLOOKUP(B86,'Номенклатура'!A:N,9,0),"") | N86: =IFERROR(VLOOKUP(B87,'Номенклатура'!A:N,10,0),"") | O86: =IFERROR(VLOOKUP(B86,'Номенклатура'!A:N,11,0),"") | P86: =IFERROR(VLOOKUP(B86,'Номенклатура'!A:N,12,0),"") | Q86: =IFERROR(VLOOKUP(B86,'Номенклатура'!A:N,13,0),"") | R86: =IFERROR(VLOOKUP(B86,'Номенклатура'!A:N,14,0),"")
A87: 74 | B87: ='План'!C75 | C87: =if(B87="","", VLOOKUP(B87,'Номенклатура'!A$3:B997,2,false)) | D87: ='План'!A75 | E87: =if(B87="","", VLOOKUP(B87,'Данни'!A:D,4,false)) | F87: =if(B87="","", VLOOKUP(B87,'Данни'!A:D,3,false)) | G87: =D87*F87 -> 0 | H87: =IFerror(VLOOKUP(B87,'Номенклатура'!A:F,4,0),"") | I87: =iferror(VLOOKUP(B87,'Номенклатура'!A:F,5,0),"") | J87: =iferror(VLOOKUP(B87,'Номенклатура'!A:N,6,0),"") | K87: =iferror(VLOOKUP(B87,'Номенклатура'!A:N,7,0),"") | L87: =IFERROR(VLOOKUP(B87,'Номенклатура'!A:N,8,0),"") | M87: =IFERROR(VLOOKUP(B87,'Номенклатура'!A:N,9,0),"") | N87: =IFERROR(VLOOKUP(B88,'Номенклатура'!A:N,10,0),"") | O87: =IFERROR(VLOOKUP(B87,'Номенклатура'!A:N,11,0),"") | P87: =IFERROR(VLOOKUP(B87,'Номенклатура'!A:N,12,0),"") | Q87: =IFERROR(VLOOKUP(B87,'Номенклатура'!A:N,13,0),"") | R87: =IFERROR(VLOOKUP(B87,'Номенклатура'!A:N,14,0),"")
A88: 75 | B88: ='План'!C76 | C88: =if(B88="","", VLOOKUP(B88,'Номенклатура'!A$3:B997,2,false)) | D88: ='План'!A76 | E88: =if(B88="","", VLOOKUP(B88,'Данни'!A:D,4,false)) | F88: =if(B88="","", VLOOKUP(B88,'Данни'!A:D,3,false)) | G88: =D88*F88 -> 0 | H88: =IFerror(VLOOKUP(B88,'Номенклатура'!A:F,4,0),"") | I88: =iferror(VLOOKUP(B88,'Номенклатура'!A:F,5,0),"") | J88: =iferror(VLOOKUP(B88,'Номенклатура'!A:N,6,0),"") | K88: =iferror(VLOOKUP(B88,'Номенклатура'!A:N,7,0),"") | L88: =IFERROR(VLOOKUP(B88,'Номенклатура'!A:N,8,0),"") | M88: =IFERROR(VLOOKUP(B88,'Номенклатура'!A:N,9,0),"") | N88: =IFERROR(VLOOKUP(B89,'Номенклатура'!A:N,10,0),"") | O88: =IFERROR(VLOOKUP(B88,'Номенклатура'!A:N,11,0),"") | P88: =IFERROR(VLOOKUP(B88,'Номенклатура'!A:N,12,0),"") | Q88: =IFERROR(VLOOKUP(B88,'Номенклатура'!A:N,13,0),"") | R88: =IFERROR(VLOOKUP(B88,'Номенклатура'!A:N,14,0),"")
A89: 76 | B89: ='План'!C77 | C89: =if(B89="","", VLOOKUP(B89,'Номенклатура'!A$3:B997,2,false)) | D89: ='План'!A77 | E89: =if(B89="","", VLOOKUP(B89,'Данни'!A:D,4,false)) | F89: =if(B89="","", VLOOKUP(B89,'Данни'!A:D,3,false)) | G89: =D89*F89 -> 0 | H89: =IFerror(VLOOKUP(B89,'Номенклатура'!A:F,4,0),"") | I89: =iferror(VLOOKUP(B89,'Номенклатура'!A:F,5,0),"") | J89: =iferror(VLOOKUP(B89,'Номенклатура'!A:N,6,0),"") | K89: =iferror(VLOOKUP(B89,'Номенклатура'!A:N,7,0),"") | L89: =IFERROR(VLOOKUP(B89,'Номенклатура'!A:N,8,0),"") | M89: =IFERROR(VLOOKUP(B89,'Номенклатура'!A:N,9,0),"") | N89: =IFERROR(VLOOKUP(B90,'Номенклатура'!A:N,10,0),"") | O89: =IFERROR(VLOOKUP(B89,'Номенклатура'!A:N,11,0),"") | P89: =IFERROR(VLOOKUP(B89,'Номенклатура'!A:N,12,0),"") | Q89: =IFERROR(VLOOKUP(B89,'Номенклатура'!A:N,13,0),"") | R89: =IFERROR(VLOOKUP(B89,'Номенклатура'!A:N,14,0),"")
A90: 77 | B90: ='План'!C78 | C90: =if(B90="","", VLOOKUP(B90,'Номенклатура'!A$3:B997,2,false)) | D90: ='План'!A78 | E90: =if(B90="","", VLOOKUP(B90,'Данни'!A:D,4,false)) | F90: =if(B90="","", VLOOKUP(B90,'Данни'!A:D,3,false)) | G90: =D90*F90 -> 0 | H90: =IFerror(VLOOKUP(B90,'Номенклатура'!A:F,4,0),"") | I90: =iferror(VLOOKUP(B90,'Номенклатура'!A:F,5,0),"") | J90: =iferror(VLOOKUP(B90,'Номенклатура'!A:N,6,0),"") | K90: =iferror(VLOOKUP(B90,'Номенклатура'!A:N,7,0),"") | L90: =IFERROR(VLOOKUP(B90,'Номенклатура'!A:N,8,0),"") | M90: =IFERROR(VLOOKUP(B90,'Номенклатура'!A:N,9,0),"") | N90: =IFERROR(VLOOKUP(B91,'Номенклатура'!A:N,10,0),"") | O90: =IFERROR(VLOOKUP(B90,'Номенклатура'!A:N,11,0),"") | P90: =IFERROR(VLOOKUP(B90,'Номенклатура'!A:N,12,0),"") | Q90: =IFERROR(VLOOKUP(B90,'Номенклатура'!A:N,13,0),"") | R90: =IFERROR(VLOOKUP(B90,'Номенклатура'!A:N,14,0),"")
A91: 78 | B91: ='План'!C79 | C91: =if(B91="","", VLOOKUP(B91,'Номенклатура'!A$3:B997,2,false)) | D91: ='План'!A79 | E91: =if(B91="","", VLOOKUP(B91,'Данни'!A:D,4,false)) | F91: =if(B91="","", VLOOKUP(B91,'Данни'!A:D,3,false)) | G91: =D91*F91 -> 0 | H91: =IFerror(VLOOKUP(B91,'Номенклатура'!A:F,4,0),"") | I91: =iferror(VLOOKUP(B91,'Номенклатура'!A:F,5,0),"") | J91: =iferror(VLOOKUP(B91,'Номенклатура'!A:N,6,0),"") | K91: =iferror(VLOOKUP(B91,'Номенклатура'!A:N,7,0),"") | L91: =IFERROR(VLOOKUP(B91,'Номенклатура'!A:N,8,0),"") | M91: =IFERROR(VLOOKUP(B91,'Номенклатура'!A:N,9,0),"") | N91: =IFERROR(VLOOKUP(B92,'Номенклатура'!A:N,10,0),"") | O91: =IFERROR(VLOOKUP(B91,'Номенклатура'!A:N,11,0),"") | P91: =IFERROR(VLOOKUP(B91,'Номенклатура'!A:N,12,0),"") | Q91: =IFERROR(VLOOKUP(B91,'Номенклатура'!A:N,13,0),"") | R91: =IFERROR(VLOOKUP(B91,'Номенклатура'!A:N,14,0),"")
A92: 79 | B92: ='План'!C80 | C92: =if(B92="","", VLOOKUP(B92,'Номенклатура'!A$3:B997,2,false)) | D92: ='План'!A80 | E92: =if(B92="","", VLOOKUP(B92,'Данни'!A:D,4,false)) | F92: =if(B92="","", VLOOKUP(B92,'Данни'!A:D,3,false)) | G92: =D92*F92 -> 0 | H92: =IFerror(VLOOKUP(B92,'Номенклатура'!A:F,4,0),"") | I92: =iferror(VLOOKUP(B92,'Номенклатура'!A:F,5,0),"") | J92: =iferror(VLOOKUP(B92,'Номенклатура'!A:N,6,0),"") | K92: =iferror(VLOOKUP(B92,'Номенклатура'!A:N,7,0),"") | L92: =IFERROR(VLOOKUP(B92,'Номенклатура'!A:N,8,0),"") | M92: =IFERROR(VLOOKUP(B92,'Номенклатура'!A:N,9,0),"") | N92: =IFERROR(VLOOKUP(B93,'Номенклатура'!A:N,10,0),"") | O92: =IFERROR(VLOOKUP(B92,'Номенклатура'!A:N,11,0),"") | P92: =IFERROR(VLOOKUP(B92,'Номенклатура'!A:N,12,0),"") | Q92: =IFERROR(VLOOKUP(B92,'Номенклатура'!A:N,13,0),"") | R92: =IFERROR(VLOOKUP(B92,'Номенклатура'!A:N,14,0),"")
A93: 80 | B93: ='План'!C81 | C93: =if(B93="","", VLOOKUP(B93,'Номенклатура'!A$3:B997,2,false)) | D93: ='План'!A81 | E93: =if(B93="","", VLOOKUP(B93,'Данни'!A:D,4,false)) | F93: =if(B93="","", VLOOKUP(B93,'Данни'!A:D,3,false)) | G93: =D93*F93 -> 0 | H93: =IFerror(VLOOKUP(B93,'Номенклатура'!A:F,4,0),"") | I93: =iferror(VLOOKUP(B93,'Номенклатура'!A:F,5,0),"") | J93: =iferror(VLOOKUP(B93,'Номенклатура'!A:N,6,0),"") | K93: =iferror(VLOOKUP(B93,'Номенклатура'!A:N,7,0),"") | L93: =IFERROR(VLOOKUP(B93,'Номенклатура'!A:N,8,0),"") | M93: =IFERROR(VLOOKUP(B93,'Номенклатура'!A:N,9,0),"") | N93: =IFERROR(VLOOKUP(B94,'Номенклатура'!A:N,10,0),"") | O93: =IFERROR(VLOOKUP(B93,'Номенклатура'!A:N,11,0),"") | P93: =IFERROR(VLOOKUP(B93,'Номенклатура'!A:N,12,0),"") | Q93: =IFERROR(VLOOKUP(B93,'Номенклатура'!A:N,13,0),"") | R93: =IFERROR(VLOOKUP(B93,'Номенклатура'!A:N,14,0),"")
A94: 81 | B94: ='План'!C82 | C94: =if(B94="","", VLOOKUP(B94,'Номенклатура'!A$3:B997,2,false)) | D94: ='План'!A82 | E94: =if(B94="","", VLOOKUP(B94,'Данни'!A:D,4,false)) | F94: =if(B94="","", VLOOKUP(B94,'Данни'!A:D,3,false)) | G94: =D94*F94 -> 0 | H94: =IFerror(VLOOKUP(B94,'Номенклатура'!A:F,4,0),"") | I94: =iferror(VLOOKUP(B94,'Номенклатура'!A:F,5,0),"") | J94: =iferror(VLOOKUP(B94,'Номенклатура'!A:N,6,0),"") | K94: =iferror(VLOOKUP(B94,'Номенклатура'!A:N,7,0),"") | L94: =IFERROR(VLOOKUP(B94,'Номенклатура'!A:N,8,0),"") | M94: =IFERROR(VLOOKUP(B94,'Номенклатура'!A:N,9,0),"") | N94: =IFERROR(VLOOKUP(B95,'Номенклатура'!A:N,10,0),"") | O94: =IFERROR(VLOOKUP(B94,'Номенклатура'!A:N,11,0),"") | P94: =IFERROR(VLOOKUP(B94,'Номенклатура'!A:N,12,0),"") | Q94: =IFERROR(VLOOKUP(B94,'Номенклатура'!A:N,13,0),"") | R94: =IFERROR(VLOOKUP(B94,'Номенклатура'!A:N,14,0),"")
A95: 82 | B95: ='План'!C83 | C95: =if(B95="","", VLOOKUP(B95,'Номенклатура'!A$3:B997,2,false)) | D95: ='План'!A83 | E95: =if(B95="","", VLOOKUP(B95,'Данни'!A:D,4,false)) | F95: =if(B95="","", VLOOKUP(B95,'Данни'!A:D,3,false)) | G95: =D95*F95 -> 0 | H95: =IFerror(VLOOKUP(B95,'Номенклатура'!A:F,4,0),"") | I95: =iferror(VLOOKUP(B95,'Номенклатура'!A:F,5,0),"") | J95: =iferror(VLOOKUP(B95,'Номенклатура'!A:N,6,0),"") | K95: =iferror(VLOOKUP(B95,'Номенклатура'!A:N,7,0),"") | L95: =IFERROR(VLOOKUP(B95,'Номенклатура'!A:N,8,0),"") | M95: =IFERROR(VLOOKUP(B95,'Номенклатура'!A:N,9,0),"") | N95: =IFERROR(VLOOKUP(B96,'Номенклатура'!A:N,10,0),"") | O95: =IFERROR(VLOOKUP(B95,'Номенклатура'!A:N,11,0),"") | P95: =IFERROR(VLOOKUP(B95,'Номенклатура'!A:N,12,0),"") | Q95: =IFERROR(VLOOKUP(B95,'Номенклатура'!A:N,13,0),"") | R95: =IFERROR(VLOOKUP(B95,'Номенклатура'!A:N,14,0),"")
A96: 83 | B96: ='План'!C84 | C96: =if(B96="","", VLOOKUP(B96,'Номенклатура'!A$3:B997,2,false)) | D96: ='План'!A84 | E96: =if(B96="","", VLOOKUP(B96,'Данни'!A:D,4,false)) | F96: =if(B96="","", VLOOKUP(B96,'Данни'!A:D,3,false)) | G96: =D96*F96 -> 0 | H96: =IFerror(VLOOKUP(B96,'Номенклатура'!A:F,4,0),"") | I96: =iferror(VLOOKUP(B96,'Номенклатура'!A:F,5,0),"") | J96: =iferror(VLOOKUP(B96,'Номенклатура'!A:N,6,0),"") | K96: =iferror(VLOOKUP(B96,'Номенклатура'!A:N,7,0),"") | L96: =IFERROR(VLOOKUP(B96,'Номенклатура'!A:N,8,0),"") | M96: =IFERROR(VLOOKUP(B96,'Номенклатура'!A:N,9,0),"") | N96: =IFERROR(VLOOKUP(B97,'Номенклатура'!A:N,10,0),"") | O96: =IFERROR(VLOOKUP(B96,'Номенклатура'!A:N,11,0),"") | P96: =IFERROR(VLOOKUP(B96,'Номенклатура'!A:N,12,0),"") | Q96: =IFERROR(VLOOKUP(B96,'Номенклатура'!A:N,13,0),"") | R96: =IFERROR(VLOOKUP(B96,'Номенклатура'!A:N,14,0),"")
A97: 84 | B97: ='План'!C85 | C97: =if(B97="","", VLOOKUP(B97,'Номенклатура'!A$3:B997,2,false)) | D97: ='План'!A85 | E97: =if(B97="","", VLOOKUP(B97,'Данни'!A:D,4,false)) | F97: =if(B97="","", VLOOKUP(B97,'Данни'!A:D,3,false)) | G97: =D97*F97 -> 0 | H97: =IFerror(VLOOKUP(B97,'Номенклатура'!A:F,4,0),"") | I97: =iferror(VLOOKUP(B97,'Номенклатура'!A:F,5,0),"") | J97: =iferror(VLOOKUP(B97,'Номенклатура'!A:N,6,0),"") | K97: =iferror(VLOOKUP(B97,'Номенклатура'!A:N,7,0),"") | L97: =IFERROR(VLOOKUP(B97,'Номенклатура'!A:N,8,0),"") | M97: =IFERROR(VLOOKUP(B97,'Номенклатура'!A:N,9,0),"") | N97: =IFERROR(VLOOKUP(B98,'Номенклатура'!A:N,10,0),"") | O97: =IFERROR(VLOOKUP(B97,'Номенклатура'!A:N,11,0),"") | P97: =IFERROR(VLOOKUP(B97,'Номенклатура'!A:N,12,0),"") | Q97: =IFERROR(VLOOKUP(B97,'Номенклатура'!A:N,13,0),"") | R97: =IFERROR(VLOOKUP(B97,'Номенклатура'!A:N,14,0),"")
A98: 85 | B98: ='План'!C86 | C98: =if(B98="","", VLOOKUP(B98,'Номенклатура'!A$3:B997,2,false)) | D98: ='План'!A86 | E98: =if(B98="","", VLOOKUP(B98,'Данни'!A:D,4,false)) | F98: =if(B98="","", VLOOKUP(B98,'Данни'!A:D,3,false)) | G98: =D98*F98 -> 0 | H98: =IFerror(VLOOKUP(B98,'Номенклатура'!A:F,4,0),"") | I98: =iferror(VLOOKUP(B98,'Номенклатура'!A:F,5,0),"") | J98: =iferror(VLOOKUP(B98,'Номенклатура'!A:N,6,0),"") | K98: =iferror(VLOOKUP(B98,'Номенклатура'!A:N,7,0),"") | L98: =IFERROR(VLOOKUP(B98,'Номенклатура'!A:N,8,0),"") | M98: =IFERROR(VLOOKUP(B98,'Номенклатура'!A:N,9,0),"") | N98: =IFERROR(VLOOKUP(B99,'Номенклатура'!A:N,10,0),"") | O98: =IFERROR(VLOOKUP(B98,'Номенклатура'!A:N,11,0),"") | P98: =IFERROR(VLOOKUP(B98,'Номенклатура'!A:N,12,0),"") | Q98: =IFERROR(VLOOKUP(B98,'Номенклатура'!A:N,13,0),"") | R98: =IFERROR(VLOOKUP(B98,'Номенклатура'!A:N,14,0),"")
